Workbook

Sheet active
A1: component | B1: carrier | C1: category | D1: BASE | E1: NFS | F1: NPS | G1: NFS_NPS | H1: P1 | I1: M2045 | J1: NO_GAS | K1: BLEND
A2: Generator | B2: solar_pv_rooftop | C2: renewables | D2: =TRUE() -> TRUE | E2: =TRUE() -> TRUE | F2: =TRUE() -> TRUE | G2: =TRUE() -> TRUE | H2: =TRUE() -> TRUE | I2: =TRUE() -> TRUE | J2: =TRUE() -> TRUE | K2: =TRUE() -> TRUE
A3: Generator | B3: solar_pv | C3: renewables | D3: =TRUE() -> TRUE | E3: =TRUE() -> TRUE | F3: =TRUE() -> TRUE | G3: =TRUE() -> TRUE | H3: =TRUE() -> TRUE | I3: =TRUE() -> TRUE | J3: =TRUE() -> TRUE | K3: =TRUE() -> TRUE
A4: Generator | B4: solar_pv_low | C4: renewables | D4: =TRUE() -> TRUE | E4: =TRUE() -> TRUE | F4: =TRUE() -> TRUE | G4: =TRUE() -> TRUE | H4: =TRUE() -> TRUE | I4: =TRUE() -> TRUE | J4: =TRUE() -> TRUE | K4: =TRUE() -> TRUE
A5: Generator | B5: solar_csp | C5: renewables | D5: =TRUE() -> TRUE | E5: =TRUE() -> TRUE | F5: =TRUE() -> TRUE | G5: =TRUE() -> TRUE | H5: =TRUE() -> TRUE | I5: =TRUE() -> TRUE | J5: =TRUE() -> TRUE | K5: =TRUE() -> TRUE
A6: Generator | B6: wind | C6: renewables | D6: =TRUE() -> TRUE | E6: =TRUE() -> TRUE | F6: =TRUE() -> TRUE | G6: =TRUE() -> TRUE | H6: =TRUE() -> TRUE | I6: =TRUE() -> TRUE | J6: =TRUE() -> TRUE | K6: =TRUE() -> TRUE
A7: Generator | B7: wind_low | C7: renewables | D7: =TRUE() -> TRUE | E7: =TRUE() -> TRUE | F7: =TRUE() -> TRUE | G7: =TRUE() -> TRUE | H7: =TRUE() -> TRUE | I7: =TRUE() -> TRUE | J7: =TRUE() -> TRUE | K7: =TRUE() -> TRUE
A8: Generator | B8: ccgt_steam | C8: conventional | D8: =TRUE() -> TRUE | E8: =TRUE() -> TRUE | F8: =TRUE() -> TRUE | G8: =TRUE() -> TRUE | H8: =TRUE() -> TRUE | I8: =TRUE() -> TRUE | J8: =TRUE() -> TRUE | K8: =TRUE() -> TRUE
A9: Generator | B9: ocgt_gas | C9: conventional | D9: =TRUE() -> TRUE | E9: =TRUE() -> TRUE | F9: =TRUE() -> TRUE | G9: =TRUE() -> TRUE | H9: =TRUE() -> TRUE | I9: =TRUE() -> TRUE | J9: FALSE | K9: =TRUE() -> TRUE
A10: Generator | B10: ocgt_gas_h2_40 | C10: conventional | D10: =TRUE() -> TRUE | E10: =FALSE() -> FALSE | F10: =TRUE() -> TRUE | G10: =FALSE() -> FALSE | H10: =TRUE() -> TRUE | I10: =TRUE() -> TRUE | J10: FALSE | K10: =FALSE() -> FALSE
A11: Generator | B11: ocgt_gas_h2_45 | C11: conventional | D11: =TRUE() -> TRUE | E11: =FALSE() -> FALSE | F11: =TRUE() -> TRUE | G11: =FALSE() -> FALSE | H11: =TRUE() -> TRUE | I11: =TRUE() -> TRUE | J11: FALSE | K11: =FALSE() -> FALSE
A12: Generator | B12: ocgt_gas_h2_50 | C12: conventional | D12: =TRUE() -> TRUE | E12: =FALSE() -> FALSE | F12: =TRUE() -> TRUE | G12: =FALSE() -> FALSE | H12: =TRUE() -> TRUE | I12: FALSE | J12: FALSE | K12: =FALSE() -> FALSE
A13: Generator | B13: ocgt_gas_h2_55 | C13: conventional | D13: =TRUE() -> TRUE | E13: =FALSE() -> FALSE | F13: =TRUE() -> TRUE | G13: =FALSE() -> FALSE | H13: FALSE | I13: FALSE | J13: FALSE | K13: =FALSE() -> FALSE
A14: Generator | B14: ocgt_gas_h2_60 | C14: conventional | D14: =TRUE() -> TRUE | E14: =FALSE() -> FALSE | F14: =TRUE() -> TRUE | G14: =FALSE() -> FALSE | H14: =FALSE() -> FALSE | I14: FALSE | J14: FALSE | K14: =FALSE() -> FALSE
A15: Generator | B15: ocgt_diesel | C15: conventional | D15: =TRUE() -> TRUE | E15: =TRUE() -> TRUE | F15: =TRUE() -> TRUE | G15: =TRUE() -> TRUE | H15: =TRUE() -> TRUE | I15: =TRUE() -> TRUE | J15: =TRUE() -> TRUE | K15: =TRUE() -> TRUE
A16: Generator | B16: ocgt_diesel_emg | C16: conventional | D16: =FALSE() -> FALSE | E16: =FALSE() -> FALSE | F16: =FALSE() -> FALSE | G16: =FALSE() -> FALSE | H16: =FALSE() -> FALSE | I16: =FALSE() -> FALSE | J16: =FALSE() -> FALSE | K16: =FALSE() -> FALSE
A17: Generator | B17: ocgt_blend | C17: conventional | D17: =FALSE() -> FALSE | E17: =FALSE() -> FALSE | F17: =FALSE() -> FALSE | G17: =FALSE() -> FALSE | H17: =FALSE() -> FALSE | I17: =FALSE() -> FALSE | J17: =FALSE() -> FALSE | K17: TRUE
A18: Generator | B18: coal | C18: conventional | D18: =TRUE() -> TRUE | E18: =TRUE() -> TRUE | F18: =TRUE() -> TRUE | G18: =TRUE() -> TRUE | H18: =TRUE() -> TRUE | I18: =TRUE() -> TRUE | J18: =TRUE() -> TRUE | K18: =TRUE() -> TRUE
A19: Generator | B19: nuclear | C19: conventional | D19: =TRUE() -> TRUE | E19: =TRUE() -> TRUE | F19: =TRUE() -> TRUE | G19: =TRUE() -> TRUE | H19: =TRUE() -> TRUE | I19: =TRUE() -> TRUE | J19: =TRUE() -> TRUE | K19: =TRUE() -> TRUE
A20: StorageUnit | B20: phs | C20: storage | D20: =TRUE() -> TRUE | E20: =TRUE() -> TRUE | F20: FALSE | G20: =TRUE() -> TRUE | H20: =TRUE() -> TRUE | I20: =TRUE() -> TRUE | J20: =TRUE() -> TRUE | K20: =TRUE() -> TRUE
A21: StorageUnit | B21: battery_1h | C21: storage | D21: =TRUE() -> TRUE | E21: =TRUE() -> TRUE | F21: =TRUE() -> TRUE | G21: =TRUE() -> TRUE | H21: =TRUE() -> TRUE | I21: =TRUE() -> TRUE | J21: =TRUE() -> TRUE | K21: =TRUE() -> TRUE
A22: StorageUnit | B22: battery_3h | C22: storage | D22: =FALSE() -> FALSE | E22: =FALSE() -> FALSE | F22: =FALSE() -> FALSE | G22: =FALSE() -> FALSE | H22: =FALSE() -> FALSE | I22: =FALSE() -> FALSE | J22: =FALSE() -> FALSE | K22: =FALSE() -> FALSE
A23: StorageUnit | B23: battery_4h | C23: storage | D23: =TRUE() -> TRUE | E23: =TRUE() -> TRUE | F23: =TRUE() -> TRUE | G23: =TRUE() -> TRUE | H23: =TRUE() -> TRUE | I23: =TRUE() -> TRUE | J23: =TRUE() -> TRUE | K23: =TRUE() -> TRUE
A24: StorageUnit | B24: battery_8h | C24: storage | D24: =TRUE() -> TRUE | E24: =TRUE() -> TRUE | F24: =TRUE() -> TRUE | G24: =TRUE() -> TRUE | H24: =TRUE() -> TRUE | I24: =TRUE() -> TRUE | J24: =TRUE() -> TRUE | K24: =TRUE() -> TRUE

Sheet parameter_mapping
A1: scenario | B1: carrier | C1: FOM | D1: overnight_capex | E1: total_vs_overnight_capex_ratio | F1: VOM | G1: lifetime | H1: max_hours | I1: heat_rate | J1: efficiency | K1: build_phase_in | L1: ramp_limit_up | M1: ramp_limit_down | N1: committable | O1: ramp_limit_start_up | P1: ramp_limit_shut_down | Q1: min_stable_level | R1: min_up_time | S1: min_down_time | T1: start_up_cost | U1: shut_down_cost | V1: discount_rate
A2: HIGH_PMR1 | B2: battery_1h | C2: default | D2: HIGH_PMR1 | E2: default | F2: default | G2: default | H2: default | J2: default | K2: overnight
A3: HIGH_PMR1 | B3: battery_4h | C3: default | D3: HIGH_PMR1 | E3: default | F3: default | G3: default | H3: default | J3: default | K3: overnight
A4: HIGH_PMR1 | B4: battery_8h | C4: default | D4: HIGH_PMR1 | E4: default | F4: default | G4: default | H4: default | J4: default | K4: overnight
A5: HIGH_PMR1 | B5: phs | C5: default | D5: default | E5: WACC_124 | F5: default | G5: default | H5: default | J5: default | K5: overnight
A6: HIGH_PMR1 | B6: coal | C6: default | D6: default | E6: WACC_124 | F6: default | G6: default | I6: default | J6: default | K6: overnight | L6: default | M6: default | N6: default | O6: default | P6: default | Q6: default | R6: default | S6: default | T6: default | U6: default
A7: HIGH_PMR1 | B7: nuclear | C7: default | D7: default | E7: WACC_124 | F7: default | G7: default | I7: default | J7: default | K7: overnight | L7: default | M7: default | N7: default | O7: default | P7: default | Q7: default | R7: default | S7: default | T7: default | U7: default
A8: HIGH_PMR1 | B8: ocgt_diesel | C8: default | D8: default | E8: WACC_124 | F8: default | G8: default | I8: default | J8: default | K8: overnight | N8: default | Q8: default
A9: HIGH_PMR1 | B9: ocgt_diesel_emg | C9: default | D9: default | E9: WACC_124 | F9: default | G9: default | I9: default | J9: default | K9: overnight | N9: default | Q9: default
A10: HIGH_PMR1 | B10: ocgt_gas | C10: default | D10: default | E10: WACC_124 | F10: default | G10: default | I10: default | J10: default | K10: overnight | N10: default | Q10: default
A11: HIGH_PMR1 | B11: ocgt_gas_h2_40 | C11: default | D11: default | E11: WACC_124 | F11: default | G11: default | I11: default | J11: default | K11: overnight | N11: default | Q11: default
A12: HIGH_PMR1 | B12: ocgt_gas_h2_45 | C12: default | D12: default | E12: WACC_124 | F12: default | G12: default | I12: default | J12: default | K12: overnight | N12: default | Q12: default
A13: HIGH_PMR1 | B13: ocgt_gas_h2_50 | C13: default | D13: default | E13: WACC_124 | F13: default | G13: default | I13: default | J13: default | K13: overnight | N13: default | Q13: default
A14: HIGH_PMR1 | B14: ocgt_gas_h2_55 | C14: default | D14: default | E14: WACC_124 | F14: default | G14: default | I14: default | J14: default | K14: overnight | N14: default | Q14: default
A15: HIGH_PMR1 | B15: ocgt_gas_h2_60 | C15: default | D15: default | E15: WACC_124 | F15: default | G15: default | I15: default | J15: default | K15: overnight | N15: default | Q15: default
A16: HIGH_PMR1 | B16: ccgt_steam | C16: default | D16: default | E16: WACC_124 | F16: default | G16: default | I16: default | J16: default | K16: overnight | L16: default | M16: default | N16: default | O16: default | P16: default | Q16: default | R16: default | S16: default | T16: default | U16: default
A17: HIGH_PMR1 | B17: solar_pv | C17: default | D17: HIGH_PMR1 | E17: WACC_124 | F17: default | G17: default | K17: overnight
A18: HIGH_PMR1 | B18: solar_pv_low | C18: default | D18: HIGH_PMR1 | E18: WACC_124 | F18: default | G18: default | K18: overnight
A19: HIGH_PMR1 | B19: solar_pv_rooftop | C19: default | D19: HIGH_PMR1 | E19: WACC_124 | F19: default | G19: default | K19: overnight
A20: HIGH_PMR1 | B20: solar_csp | C20: default | D20: default | E20: WACC_124 | F20: default | G20: default | K20: overnight
A21: HIGH_PMR1 | B21: wind | C21: default | D21: HIGH_PMR1 | E21: WACC_124 | F21: default | G21: default | K21: overnight
A22: HIGH_PMR1 | B22: wind_low | C22: default | D22: HIGH_PMR1 | E22: WACC_124 | F22: default | G22: default | K22: overnight
A23: BASE_PMR1 | B23: battery_1h | C23: default | D23: BASE_PMR1 | E23: default | F23: default | G23: default | H23: default | J23: default | K23: overnight
A24: BASE_PMR1 | B24: battery_4h | C24: default | D24: BASE_PMR1 | E24: default | F24: default | G24: default | H24: default | J24: default | K24: overnight
A25: BASE_PMR1 | B25: battery_8h | C25: default | D25: BASE_PMR1 | E25: default | F25: default | G25: default | H25: default | J25: default | K25: overnight
A26: BASE_PMR1 | B26: phs | C26: default | D26: default | E26: WACC_095 | F26: default | G26: default | H26: default | J26: default | K26: overnight
A27: BASE_PMR1 | B27: coal | C27: default | D27: default | E27: WACC_095 | F27: default | G27: default | I27: default | J27: default | K27: overnight | L27: default | M27: default | N27: default | O27: default | P27: default | Q27: default | R27: default | S27: default | T27: default | U27: default
A28: BASE_PMR1 | B28: nuclear | C28: default | D28: default | E28: WACC_095 | F28: default | G28: default | I28: default | J28: default | K28: overnight | L28: default | M28: default | N28: default | O28: default | P28: default | Q28: default | R28: default | S28: default | T28: default | U28: default
A29: BASE_PMR1 | B29: ocgt_diesel | C29: default | D29: default | E29: WACC_095 | F29: default | G29: default | I29: default | J29: default | K29: overnight | N29: default | Q29: default
A30: BASE_PMR1 | B30: ocgt_diesel_emg | C30: default | D30: default | E30: WACC_095 | F30: default | G30: default | I30: default | J30: default | K30: overnight | N30: default | Q30: default
A31: BASE_PMR1 | B31: ocgt_gas | C31: default | D31: default | E31: WACC_095 | F31: default | G31: default | I31: default | J31: default | K31: overnight | N31: default | Q31: default
A32: BASE_PMR1 | B32: ocgt_gas_h2_40 | C32: default | D32: default | E32: WACC_095 | F32: default | G32: default | I32: default | J32: default | K32: overnight | N32: default | Q32: default
A33: BASE_PMR1 | B33: ocgt_gas_h2_45 | C33: default | D33: default | E33: WACC_095 | F33: default | G33: default | I33: default | J33: default | K33: overnight | N33: default | Q33: default
A34: BASE_PMR1 | B34: ocgt_gas_h2_50 | C34: default | D34: default | E34: WACC_095 | F34: default | G34: default | I34: default | J34: default | K34: overnight | N34: default | Q34: default
A35: BASE_PMR1 | B35: ocgt_gas_h2_55 | C35: default | D35: default | E35: WACC_095 | F35: default | G35: default | I35: default | J35: default | K35: overnight | N35: default | Q35: default
A36: BASE_PMR1 | B36: ocgt_gas_h2_60 | C36: default | D36: default | E36: WACC_095 | F36: default | G36: default | I36: default | J36: default | K36: overnight | N36: default | Q36: default
A37: BASE_PMR1 | B37: ccgt_steam | C37: default | D37: default | E37: WACC_095 | F37: default | G37: default | I37: default | J37: default | K37: overnight | L37: default | M37: default | N37: default | O37: default | P37: default | Q37: default | R37: default | S37: default | T37: default | U37: default
A38: BASE_PMR1 | B38: solar_pv | C38: default | D38: BASE_PMR1 | E38: WACC_095 | F38: default | G38: default | K38: overnight
A39: BASE_PMR1 | B39: solar_pv_low | C39: default | D39: BASE_PMR1 | E39: WACC_095 | F39: default | G39: default | K39: overnight
A40: BASE_PMR1 | B40: solar_pv_rooftop | C40: default | D40: BASE_PMR1 | E40: WACC_095 | F40: default | G40: default | K40: overnight
A41: BASE_PMR1 | B41: solar_csp | C41: default | D41: default | E41: WACC_095 | F41: default | G41: default | K41: overnight
A42: BASE_PMR1 | B42: wind | C42: default | D42: BASE_PMR1 | E42: WACC_095 | F42: default | G42: default | K42: overnight
A43: BASE_PMR1 | B43: wind_low | C43: default | D43: BASE_PMR1 | E43: WACC_095 | F43: default | G43: default | K43: overnight
A44: LOW_PMR1 | B44: battery_1h | C44: default | D44: LOW_PMR1 | E44: default | F44: default | G44: default | H44: default | J44: default | K44: overnight
A45: LOW_PMR1 | B45: battery_4h | C45: default | D45: LOW_PMR1 | E45: default | F45: default | G45: default | H45: default | J45: default | K45: overnight
A46: LOW_PMR1 | B46: battery_8h | C46: default | D46: LOW_PMR1 | E46: default | F46: default | G46: default | H46: default | J46: default | K46: overnight
A47: LOW_PMR1 | B47: phs | C47: default | D47: default | E47: WACC_074 | F47: default | G47: default | H47: default | J47: default | K47: overnight
A48: LOW_PMR1 | B48: coal | C48: default | D48: default | E48: WACC_074 | F48: default | G48: default | I48: default | J48: default | K48: overnight | L48: default | M48: default | N48: default | O48: default | P48: default | Q48: default | R48: default | S48: default | T48: default | U48: default
A49: LOW_PMR1 | B49: nuclear | C49: default | D49: default | E49: WACC_074 | F49: default | G49: default | I49: default | J49: default | K49: overnight | L49: default | M49: default | N49: default | O49: default | P49: default | Q49: default | R49: default | S49: default | T49: default | U49: default
A50: LOW_PMR1 | B50: ocgt_diesel | C50: default | D50: default | E50: WACC_074 | F50: default | G50: default | I50: default | J50: default | K50: overnight | N50: default | Q50: default
A51: LOW_PMR1 | B51: ocgt_diesel_emg | C51: default | D51: default | E51: WACC_074 | F51: default | G51: default | I51: default | J51: default | K51: overnight | N51: default | Q51: default
A52: LOW_PMR1 | B52: ocgt_gas | C52: default | D52: default | E52: WACC_074 | F52: default | G52: default | I52: default | J52: default | K52: overnight | N52: default | Q52: default
A53: LOW_PMR1 | B53: ocgt_gas_h2_40 | C53: default | D53: default | E53: WACC_074 | F53: default | G53: default | I53: default | J53: default | K53: overnight | N53: default | Q53: default
A54: LOW_PMR1 | B54: ocgt_gas_h2_45 | C54: default | D54: default | E54: WACC_074 | F54: default | G54: default | I54: default | J54: default | K54: overnight | N54: default | Q54: default
A55: LOW_PMR1 | B55: ocgt_gas_h2_50 | C55: default | D55: default | E55: WACC_074 | F55: default | G55: default | I55: default | J55: default | K55: overnight | N55: default | Q55: default
A56: LOW_PMR1 | B56: ocgt_gas_h2_55 | C56: default | D56: default | E56: WACC_074 | F56: default | G56: default | I56: default | J56: default | K56: overnight | N56: default | Q56: default
A57: LOW_PMR1 | B57: ocgt_gas_h2_60 | C57: default | D57: default | E57: WACC_074 | F57: default | G57: default | I57: default | J57: default | K57: overnight | N57: default | Q57: default
A58: LOW_PMR1 | B58: ccgt_steam | C58: default | D58: default | E58: WACC_074 | F58: default | G58: default | I58: default | J58: default | K58: overnight | L58: default | M58: default | N58: default | O58: default | P58: default | Q58: default | R58: default | S58: default | T58: default | U58: default
A59: LOW_PMR1 | B59: solar_pv | C59: default | D59: LOW_PMR1 | E59: WACC_074 | F59: default | G59: default | K59: overnight
A60: LOW_PMR1 | B60: solar_pv_low | C60: default | D60: LOW_PMR1 | E60: WACC_074 | F60: default | G60: default | K60: overnight
A61: LOW_PMR1 | B61: solar_pv_rooftop | C61: default | D61: LOW_PMR1 | E61: WACC_074 | F61: default | G61: default | K61: overnight
A62: LOW_PMR1 | B62: solar_csp | C62: default | D62: default | E62: WACC_074 | F62: default | G62: default | K62: overnight
A63: LOW_PMR1 | B63: wind | C63: default | D63: LOW_PMR1 | E63: WACC_074 | F63: default | G63: default | K63: overnight
A64: LOW_PMR1 | B64: wind_low | C64: default | D64: LOW_PMR1 | E64: WACC_074 | F64: default | G64: default | K64: overnight
A65: HIGH_PMR1b | B65: battery_1h | C65: deg_as_VOM | D65: HIGH_PMR1b | E65: default | F65: HIGH_VOM_PMR1b | G65: default | H65: default | J65: default | K65: overnight
A66: HIGH_PMR1b | B66: battery_4h | C66: deg_as_VOM | D66: HIGH_PMR1b | E66: default | F66: HIGH_VOM_PMR1b | G66: default | H66: default | J66: default | K66: overnight
A67: HIGH_PMR1b | B67: battery_8h | C67: deg_as_VOM | D67: HIGH_PMR1b | E67: default | F67: HIGH_VOM_PMR1b | G67: default | H67: default | J67: default | K67: overnight
A68: HIGH_PMR1b | B68: phs | C68: default | D68: default | E68: WACC_1201 | F68: default | G68: default | H68: default | J68: default | K68: overnight
A69: HIGH_PMR1b | B69: coal | C69: default | D69: default | E69: WACC_1201 | F69: default | G69: default | I69: default | J69: default | K69: overnight | L69: default | M69: default | N69: default | O69: default | P69: default | Q69: default | R69: default | S69: default | T69: default | U69: default
A70: HIGH_PMR1b | B70: nuclear | C70: default | D70: default | E70: WACC_1201 | F70: default | G70: default | I70: default | J70: default | K70: overnight | L70: default | M70: default | N70: default | O70: default | P70: default | Q70: default | R70: default | S70: default | T70: default | U70: default
A71: HIGH_PMR1b | B71: ocgt_diesel | C71: default | D71: HIGH_PMR1b | E71: WACC_1201 | F71: default | G71: default | I71: default | J71: default | K71: overnight | N71: default | Q71: default
A72: HIGH_PMR1b | B72: ocgt_gas | C72: default | D72: HIGH_PMR1b | E72: WACC_1201 | F72: default | G72: default | I72: default | J72: default | K72: overnight | N72: default | Q72: default
A73: HIGH_PMR1b | B73: ocgt_gas_h2_40 | C73: default | D73: HIGH_PMR1b | E73: WACC_1201 | F73: default | G73: default | I73: default | J73: default | K73: overnight | N73: default | Q73: default
A74: HIGH_PMR1b | B74: ocgt_gas_h2_45 | C74: default | D74: HIGH_PMR1b | E74: WACC_1201 | F74: default | G74: default | I74: default | J74: default | K74: overnight | N74: default | Q74: default
A75: HIGH_PMR1b | B75: ocgt_gas_h2_50 | C75: default | D75: HIGH_PMR1b | E75: WACC_1201 | F75: default | G75: default | I75: default | J75: default | K75: overnight | N75: default | Q75: default
A76: HIGH_PMR1b | B76: ocgt_gas_h2_55 | C76: default | D76: HIGH_PMR1b | E76: WACC_1201 | F76: default | G76: default | I76: default | J76: default | K76: overnight | N76: default | Q76: default
A77: HIGH_PMR1b | B77: ocgt_gas_h2_60 | C77: default | D77: HIGH_PMR1b | E77: WACC_1201 | F77: default | G77: default | I77: default | J77: default | K77: overnight | N77: default | Q77: default
A78: HIGH_PMR1b | B78: ccgt_steam | C78: default | D78: HIGH_PMR1b | E78: WACC_1201 | F78: default | G78: default | I78: default | J78: default | K78: overnight | L78: default | M78: default | N78: default | O78: default | P78: default | Q78: default | R78: default | S78: default | T78: default | U78: default
A79: HIGH_PMR1b | B79: solar_pv | C79: default | D79: HIGH_PMR1b | E79: WACC_1201 | F79: default | G79: default | K79: overnight
A80: HIGH_PMR1b | B80: solar_pv_low | C80: default | D80: HIGH_PMR1b | E80: WACC_1201 | F80: default | G80: default | K80: overnight
A81: HIGH_PMR1b | B81: solar_pv_rooftop | C81: default | D81: HIGH_PMR1b | E81: WACC_1201 | F81: default | G81: default | K81: overnight
A82: HIGH_PMR1b | B82: solar_csp | C82: default | D82: default | E82: WACC_1201 | F82: default | G82: default | K82: overnight
A83: HIGH_PMR1b | B83: wind | C83: default | D83: HIGH_PMR1b | E83: WACC_1201 | F83: default | G83: default | K83: overnight
A84: HIGH_PMR1b | B84: wind_low | C84: default | D84: HIGH_PMR1b | E84: WACC_1201 | F84: default | G84: default | K84: overnight
A85: BASE_PMR1b | B85: battery_1h | C85: deg_as_VOM | D85: BASE_PMR1b | E85: default | F85: BASE_VOM_PMR1b | G85: default | H85: default | J85: default | K85: overnight
A86: BASE_PMR1b | B86: battery_4h | C86: deg_as_VOM | D86: BASE_PMR1b | E86: default | F86: BASE_VOM_PMR1b | G86: default | H86: default | J86: default | K86: overnight
A87: BASE_PMR1b | B87: battery_8h | C87: deg_as_VOM | D87: BASE_PMR1b | E87: default | F87: BASE_VOM_PMR1b | G87: default | H87: default | J87: default | K87: overnight
A88: BASE_PMR1b | B88: phs | C88: default | D88: default | E88: WACC_0923 | F88: default | G88: default | H88: default | J88: default | K88: overnight
A89: BASE_PMR1b | B89: coal | C89: default | D89: default | E89: WACC_0923 | F89: default | G89: default | I89: default | J89: default | K89: overnight | L89: default | M89: default | N89: default | O89: default | P89: default | Q89: default | R89: default | S89: default | T89: default | U89: default
A90: BASE_PMR1b | B90: nuclear | C90: default | D90: default | E90: WACC_0923 | F90: default | G90: default | I90: default | J90: default | K90: overnight | L90: default | M90: default | N90: default | O90: default | P90: default | Q90: default | R90: default | S90: default | T90: default | U90: default
A91: BASE_PMR1b | B91: ocgt_diesel | C91: default | D91: BASE_PMR1b | E91: WACC_0923 | F91: default | G91: default | I91: default | J91: default | K91: overnight | N91: default | Q91: default
A92: BASE_PMR1b | B92: ocgt_gas | C92: default | D92: BASE_PMR1b | E92: WACC_0923 | F92: default | G92: default | I92: default | J92: default | K92: overnight | N92: default | Q92: default
A93: BASE_PMR1b | B93: ocgt_gas_h2_40 | C93: default | D93: BASE_PMR1b | E93: WACC_0923 | F93: default | G93: default | I93: default | J93: default | K93: overnight | N93: default | Q93: default
A94: BASE_PMR1b | B94: ocgt_gas_h2_45 | C94: default | D94: BASE_PMR1b | E94: WACC_0923 | F94: default | G94: default | I94: default | J94: default | K94: overnight | N94: default | Q94: default
A95: BASE_PMR1b | B95: ocgt_gas_h2_50 | C95: default | D95: BASE_PMR1b | E95: WACC_0923 | F95: default | G95: default | I95: default | J95: default | K95: overnight | N95: default | Q95: default
A96: BASE_PMR1b | B96: ocgt_gas_h2_55 | C96: default | D96: BASE_PMR1b | E96: WACC_0923 | F96: default | G96: default | I96: default | J96: default | K96: overnight | N96: default | Q96: default
A97: BASE_PMR1b | B97: ocgt_gas_h2_60 | C97: default | D97: BASE_PMR1b | E97: WACC_0923 | F97: default | G97: default | I97: default | J97: default | K97: overnight | N97: default | Q97: default
A98: BASE_PMR1b | B98: ccgt_steam | C98: default | D98: BASE_PMR1b | E98: WACC_0923 | F98: default | G98: default | I98: default | J98: default | K98: overnight | L98: default | M98: default | N98: default | O98: default | P98: default | Q98: default | R98: default | S98: default | T98: default | U98: default
A99: BASE_PMR1b | B99: solar_pv | C99: default | D99: BASE_PMR1b | E99: WACC_0923 | F99: default | G99: default | K99: overnight
A100: BASE_PMR1b | B100: solar_pv_low | C100: default | D100: BASE_PMR1b | E100: WACC_0923 | F100: default | G100: default | K100: overnight
...

Sheet parameters
A1: scenario | B1: carrier | C1: parameter | D1: units | E1: 2024 | F1: 2025 | G1: 2026 | H1: 2027 | I1: 2028 | J1: 2029 | K1: 2030 | L1: 2031 | M1: 2032 | N1: 2033 | O1: 2034 | P1: 2035 | Q1: 2036 | R1: 2037 | S1: 2038 | T1: 2039 | U1: 2040 | V1: 2041 | W1: 2042 | X1: 2043 | Y1: 2044 | Z1: 2045 | AA1: 2046 | AB1: 2047 | AC1: 2048 | AD1: 2049 | AE1: 2050 | AF1: =AE1+1 -> 2051 | AG1: =AF1+1 -> 2052 | AH1: =AG1+1 -> 2053 | AI1: =AH1+1 -> 2054 | AJ1: =AI1+1 -> 2055 | AK1: =AJ1+1 -> 2056 | AL1: =AK1+1 -> 2057 | AM1: =AL1+1 -> 2058 | ... AO1: =AN1+1 -> 2060 | AP1: source
A2: default | B2: coal | C2: carrier_emissions | D2: tCO2/MWht | E2: 0.346 | F2: =E2 -> 0.346 | G2: =F2 -> 0.346 | H2: =G2 -> 0.346 | I2: =H2 -> 0.346 | J2: =I2 -> 0.346 | K2: =J2 -> 0.346 | L2: =K2 -> 0.346 | M2: =L2 -> 0.346 | ... AO2: =AN2 -> 0.346
A3: default | B3: sasol_coal | C3: carrier_emissions | D3: tCO2/MWht | E3: 0.346 | F3: =F2 -> 0.346 | G3: =G2 -> 0.346 | H3: =H2 -> 0.346 | I3: =I2 -> 0.346 | J3: =J2 -> 0.346 | K3: =K2 -> 0.346 | L3: =L2 -> 0.346 | M3: =M2 -> 0.346 | ... AE3: =AE2 -> 0.346 | AF3: =AE3 -> 0.346 | AG3: =AF3 -> 0.346 | AH3: =AG3 -> 0.346 | AI3: =AH3 -> 0.346 | AJ3: =AI3 -> 0.346 | AK3: =AJ3 -> 0.346 | AL3: =AK3 -> 0.346 | AM3: =AL3 -> 0.346 | ... AO3: =AN3 -> 0.346
A4: default | B4: ocgt_diesel | C4: carrier_emissions | D4: tCO2/MWht | E4: 0.267 | F4: 0.267 | G4: 0.267 | H4: 0.267 | I4: 0.267 | J4: 0.267 | K4: 0.267 | L4: 0.267 | M4: 0.267 | N4: 0.267 | O4: 0.267 | P4: 0.267 | Q4: 0.267 | R4: 0.267 | S4: 0.267 | T4: 0.267 | U4: 0 | V4: 0 | W4: 0 | X4: 0 | Y4: 0 | Z4: 0 | AA4: 0 | AB4: 0 | AC4: 0 | AD4: 0 | AE4: 0 | AF4: =AE4 -> 0 | AG4: =AF4 -> 0 | AH4: =AG4 -> 0 | AI4: =AH4 -> 0 | AJ4: =AI4 -> 0 | AK4: =AJ4 -> 0 | AL4: =AK4 -> 0 | AM4: =AL4 -> 0 | ... AO4: =AN4 -> 0
A5: default | B5: ocgt_diesel_emg | C5: carrier_emissions | D5: tCO2/MWht | E5: 0.267 | F5: 0.267 | G5: 0.267 | H5: 0.267 | I5: 0.267 | J5: 0.267 | K5: 0.267 | L5: 0.267 | M5: 0.267 | N5: 0.267 | O5: 0.267 | P5: 0.267 | Q5: 0.267 | R5: 0.267 | S5: 0.267 | T5: 0.267 | U5: 0 | V5: 0 | W5: 0 | X5: 0 | Y5: 0 | Z5: 0 | AA5: 0 | AB5: 0 | AC5: 0 | AD5: 0 | AE5: 0 | AF5: =AE5 -> 0 | AG5: =AF5 -> 0 | AH5: =AG5 -> 0 | AI5: =AH5 -> 0 | AJ5: =AI5 -> 0 | AK5: =AJ5 -> 0 | AL5: =AK5 -> 0 | AM5: =AL5 -> 0 | ... AO5: =AN5 -> 0
A6: default | B6: ocgt_avf | C6: carrier_emissions | D6: tCO2/MWht | E6: 0.267 | F6: 0.267 | G6: 0.267 | H6: 0.267 | I6: 0.267 | J6: 0.267 | K6: 0.267 | L6: 0.267 | M6: 0.267 | N6: 0.267 | O6: 0.267 | P6: 0.267 | Q6: 0.267 | R6: 0.267 | S6: 0.267 | T6: 0.267 | U6: =T6 -> 0.267 | V6: =U6 -> 0.267 | W6: =V6 -> 0.267 | X6: =W6 -> 0.267 | Y6: =X6 -> 0.267 | Z6: =Y6 -> 0.267 | AA6: =Z6 -> 0.267 | AB6: =AA6 -> 0.267 | ... AO6: =AN6 -> 0.267
A7: default | B7: ocgt_gas | C7: carrier_emissions | D7: tCO2/MWht | E7: 0.249 | F7: 0.249 | G7: 0.249 | H7: 0.249 | I7: 0.249 | J7: 0.249 | K7: 0.249 | L7: 0.249 | M7: 0.249 | N7: 0.249 | O7: 0.249 | P7: 0.249 | Q7: 0.249 | R7: 0.249 | S7: 0.249 | T7: 0.249 | U7: 0.249 | V7: 0.249 | W7: 0.249 | X7: 0.249 | Y7: 0.249 | Z7: 0.249 | AA7: 0.249 | AB7: 0.249 | AC7: 0.249 | AD7: 0.249 | AE7: 0.249 | AF7: =AE7 -> 0.249 | AG7: =AF7 -> 0.249 | AH7: =AG7 -> 0.249 | AI7: =AH7 -> 0.249 | AJ7: =AI7 -> 0.249 | AK7: =AJ7 -> 0.249 | AL7: =AK7 -> 0.249 | AM7: =AL7 -> 0.249 | ... AO7: =AN7 -> 0.249
A8: default | B8: ocgt_gas_h2_40 | C8: carrier_emissions | D8: tCO2/MWht | E8: 0.249 | F8: 0.249 | G8: 0.249 | H8: 0.249 | I8: 0.249 | J8: 0.249 | K8: 0.249 | L8: 0.249 | M8: 0.249 | N8: 0.249 | O8: 0.249 | P8: 0.249 | Q8: 0.249 | R8: 0.249 | S8: 0.249 | T8: 0.249 | U8: 0 | V8: 0 | W8: 0 | X8: 0 | Y8: 0 | Z8: 0 | AA8: 0 | AB8: 0 | AC8: 0 | AD8: 0 | AE8: 0 | AF8: =AE8 -> 0 | AG8: =AF8 -> 0 | AH8: =AG8 -> 0 | AI8: =AH8 -> 0 | AJ8: =AI8 -> 0 | AK8: =AJ8 -> 0 | AL8: =AK8 -> 0 | AM8: =AL8 -> 0 | ... AO8: =AN8 -> 0
A9: default | B9: ocgt_gas_h2_45 | C9: carrier_emissions | D9: tCO2/MWht | E9: 0.249 | F9: 0.249 | G9: 0.249 | H9: 0.249 | I9: 0.249 | J9: 0.249 | K9: 0.249 | L9: 0.249 | M9: 0.249 | N9: 0.249 | O9: 0.249 | P9: 0.249 | Q9: 0.249 | R9: 0.249 | S9: 0.249 | T9: 0.249 | U9: 0.249 | V9: 0.249 | W9: 0.249 | X9: 0.249 | Y9: 0.249 | Z9: 0 | AA9: 0 | AB9: 0 | AC9: 0 | AD9: 0 | AE9: 0 | AF9: =AE9 -> 0 | AG9: =AF9 -> 0 | AH9: =AG9 -> 0 | AI9: =AH9 -> 0 | AJ9: =AI9 -> 0 | AK9: =AJ9 -> 0 | AL9: =AK9 -> 0 | AM9: =AL9 -> 0 | ... AO9: =AN9 -> 0
A10: default | B10: ocgt_gas_h2_50 | C10: carrier_emissions | D10: tCO2/MWht | E10: 0.249 | F10: 0.249 | G10: 0.249 | H10: 0.249 | I10: 0.249 | J10: 0.249 | K10: 0.249 | L10: 0.249 | M10: 0.249 | N10: 0.249 | O10: 0.249 | P10: 0.249 | Q10: 0.249 | R10: 0.249 | S10: 0.249 | T10: 0.249 | U10: 0.249 | V10: 0.249 | W10: 0.249 | X10: 0.249 | Y10: 0.249 | Z10: 0.249 | AA10: 0.249 | AB10: 0.249 | AC10: 0.249 | AD10: 0.249 | AE10: 0 | AF10: =AE10 -> 0 | AG10: =AF10 -> 0 | AH10: =AG10 -> 0 | AI10: =AH10 -> 0 | AJ10: =AI10 -> 0 | AK10: =AJ10 -> 0 | AL10: =AK10 -> 0 | AM10: =AL10 -> 0 | ... AO10: =AN10 -> 0
A11: default | B11: ocgt_gas_h2_55 | C11: carrier_emissions | D11: tCO2/MWht | E11: 0.249 | F11: 0.249 | G11: 0.249 | H11: 0.249 | I11: 0.249 | J11: 0.249 | K11: 0.249 | L11: 0.249 | M11: 0.249 | N11: 0.249 | O11: 0.249 | P11: 0.249 | Q11: 0.249 | R11: 0.249 | S11: 0.249 | T11: 0.249 | U11: 0.249 | V11: 0.249 | W11: 0.249 | X11: 0.249 | Y11: 0.249 | Z11: 0.249 | AA11: 0.249 | AB11: 0.249 | AC11: 0.249 | AD11: 0.249 | AE11: 0.249 | AF11: 0.249 | AG11: 0.249 | AH11: 0.249 | AI11: 0.249 | AJ11: 0 | AK11: 0 | AL11: 0 | AM11: 0 | AN11: 0 | AO11: 0
A12: default | B12: ocgt_gas_h2_60 | C12: carrier_emissions | D12: tCO2/MWht | E12: 0.249 | F12: 0.249 | G12: 0.249 | H12: 0.249 | I12: 0.249 | J12: 0.249 | K12: 0.249 | L12: 0.249 | M12: 0.249 | N12: 0.249 | O12: 0.249 | P12: 0.249 | Q12: 0.249 | R12: 0.249 | S12: 0.249 | T12: 0.249 | U12: 0.249 | V12: 0.249 | W12: 0.249 | X12: 0.249 | Y12: 0.249 | Z12: 0.249 | AA12: 0.249 | AB12: 0.249 | AC12: 0.249 | AD12: 0.249 | AE12: 0.249 | AF12: 0.249 | AG12: 0.249 | AH12: 0.249 | AI12: 0.249 | AJ12: 0.249 | AK12: 0.249 | AL12: 0.249 | AM12: 0.249 | AN12: 0.249 | AO12: 0
A13: default | B13: sasol_gas | C13: carrier_emissions | D13: tCO2/MWht | E13: 0.249 | F13: 0.249 | G13: 0.249 | H13: 0.249 | I13: 0.249 | J13: 0.249 | K13: 0.249 | L13: 0.249 | M13: 0.249 | N13: 0.249 | O13: 0.249 | P13: 0.249 | Q13: 0.249 | R13: 0.249 | S13: 0.249 | T13: 0.249 | U13: =T13 -> 0.249 | V13: =U13 -> 0.249 | W13: =V13 -> 0.249 | X13: =W13 -> 0.249 | Y13: =X13 -> 0.249 | Z13: =Y13 -> 0.249 | AA13: =Z13 -> 0.249 | AB13: =AA13 -> 0.249 | ... AN13: =AM13 -> 0.249 | AO13: 0.249
A14: default | B14: coal | C14: output_emissions | D14: tCO2/MWh | E14: 0.93958222 | F14: =F2/F55 -> 0.93958222 | G14: =G2/G55 -> 0.93958222 | H14: =H2/H55 -> 0.93958222 | I14: =I2/I55 -> 0.93958222 | J14: =J2/J55 -> 0.93958222 | K14: =K2/K55 -> 0.93958222 | L14: =L2/L55 -> 0.93958222 | M14: =M2/M55 -> 0.93958222 | ... AE14: =AE2/AE55 -> 0.93958222 | AF14: =AE14 -> 0.93958222 | AG14: =AF14 -> 0.93958222 | AH14: =AG14 -> 0.93958222 | AI14: =AH14 -> 0.93958222 | AJ14: =AI14 -> 0.93958222 | AK14: =AJ14 -> 0.93958222 | AL14: =AK14 -> 0.93958222 | AM14: =AL14 -> 0.93958222 | ... AO14: =AN14 -> 0.93958222
A15: default | B15: sasol_coal | C15: output_emissions | D15: tCO2/MWh | E15: 0.93958222 | F15: =F14 -> 0.93958222 | G15: =G14 -> 0.93958222 | H15: =H14 -> 0.93958222 | I15: =I14 -> 0.93958222 | J15: =J14 -> 0.93958222 | K15: =K14 -> 0.93958222 | L15: =L14 -> 0.93958222 | M15: =M14 -> 0.93958222 | ... AE15: =AE14 -> 0.93958222 | AF15: =AE15 -> 0.93958222 | AG15: =AF15 -> 0.93958222 | AH15: =AG15 -> 0.93958222 | AI15: =AH15 -> 0.93958222 | AJ15: =AI15 -> 0.93958222 | AK15: =AJ15 -> 0.93958222 | AL15: =AK15 -> 0.93958222 | AM15: =AL15 -> 0.93958222 | ... AO15: =AN15 -> 0.93958222
A16: default | B16: ocgt_diesel | C16: output_emissions | D16: tCO2/MWh | E16: =E4/E57 -> 0.7010975 | F16: =F4/F57 -> 0.7010975 | G16: =G4/G57 -> 0.7010975 | H16: =H4/H57 -> 0.7010975 | I16: =I4/I57 -> 0.7010975 | J16: =J4/J57 -> 0.7010975 | K16: =K4/K57 -> 0.7010975 | L16: =L4/L57 -> 0.7010975 | ... AO16: =AO4/AO57 -> 0
A17: default | B17: ocgt_diesel_emg | C17: output_emissions | D17: tCO2/MWh | E17: =E5/E58 -> 0.7010975 | F17: =F5/F58 -> 0.7010975 | G17: =G5/G58 -> 0.7010975 | H17: =H5/H58 -> 0.7010975 | I17: =I5/I58 -> 0.7010975 | J17: =J5/J58 -> 0.7010975 | K17: =K5/K58 -> 0.7010975 | L17: =L5/L58 -> 0.7010975 | ... AO17: =AO5/AO58 -> 0
A18: default | B18: ocgt_avf | C18: output_emissions | D18: tCO2/MWh | E18: =E6/E59 -> 0.7010975 | F18: =F6/F59 -> 0.7010975 | G18: =G6/G59 -> 0.7010975 | H18: =H6/H59 -> 0.7010975 | I18: =I6/I59 -> 0.7010975 | J18: =J6/J59 -> 0.7010975 | K18: =K6/K59 -> 0.7010975 | L18: =L6/L59 -> 0.7010975 | ... AO18: =AO6/AO59 -> 0.7010975
A19: default | B19: ocgt_gas | C19: output_emissions | D19: tCO2/MWh | E19: =E7/E60 -> 0.6538325 | F19: =F7/F60 -> 0.6538325 | G19: =G7/G60 -> 0.6538325 | H19: =H7/H60 -> 0.6538325 | I19: =I7/I60 -> 0.6538325 | J19: =J7/J60 -> 0.6538325 | K19: =K7/K60 -> 0.6538325 | L19: =L7/L60 -> 0.6538325 | ... AO19: =AO7/AO60 -> 0.6538325
A20: default | B20: ocgt_gas_h2_40 | C20: output_emissions | D20: tCO2/MWh | E20: =E8/E61 -> 0.6538325 | F20: =F8/F61 -> 0.6538325 | G20: =G8/G61 -> 0.6538325 | H20: =H8/H61 -> 0.6538325 | I20: =I8/I61 -> 0.6538325 | J20: =J8/J61 -> 0.6538325 | K20: =K8/K61 -> 0.6538325 | L20: =L8/L61 -> 0.6538325 | ... AO20: =AO8/AO61 -> 0
A21: default | B21: ocgt_gas_h2_45 | C21: output_emissions | D21: tCO2/MWh | E21: =E9/E62 -> 0.6538325 | F21: =F9/F62 -> 0.6538325 | G21: =G9/G62 -> 0.6538325 | H21: =H9/H62 -> 0.6538325 | I21: =I9/I62 -> 0.6538325 | J21: =J9/J62 -> 0.6538325 | K21: =K9/K62 -> 0.6538325 | L21: =L9/L62 -> 0.6538325 | ... AO21: =AO9/AO62 -> 0
A22: default | B22: ocgt_gas_h2_50 | C22: output_emissions | D22: tCO2/MWh | E22: =E10/E63 -> 0.6538325 | F22: =F10/F63 -> 0.6538325 | G22: =G10/G63 -> 0.6538325 | H22: =H10/H63 -> 0.6538325 | I22: =I10/I63 -> 0.6538325 | J22: =J10/J63 -> 0.6538325 | K22: =K10/K63 -> 0.6538325 | L22: =L10/L63 -> 0.6538325 | ... AO22: =AO10/AO63 -> 0
A23: default | B23: ocgt_gas_h2_55 | C23: output_emissions | D23: tCO2/MWh | E23: =E11/E64 -> 0.6538325 | F23: =F11/F64 -> 0.6538325 | G23: =G11/G64 -> 0.6538325 | H23: =H11/H64 -> 0.6538325 | I23: =I11/I64 -> 0.6538325 | J23: =J11/J64 -> 0.6538325 | K23: =K11/K64 -> 0.6538325 | L23: =L11/L64 -> 0.6538325 | ... AO23: =AO11/AO64 -> 0
A24: default | B24: ocgt_gas_h2_60 | C24: output_emissions | D24: tCO2/MWh | E24: =E12/E66 -> 0.31923077 | F24: =F12/F66 -> 0.31923077 | G24: =G12/G66 -> 0.31923077 | H24: =H12/H66 -> 0.31923077 | I24: =I12/I66 -> 0.31923077 | J24: =J12/J66 -> 0.31923077 | K24: =K12/K66 -> 0.31923077 | L24: =L12/L66 -> 0.31923077 | ... AO24: =AO12/AO66 -> 0
A25: default | B25: sasol_gas | C25: output_emissions | D25: tCO2/MWh | E25: =E13/E67 -> 0.498 | F25: =F13/F67 -> 0.498 | G25: =G13/G67 -> 0.498 | H25: =H13/H67 -> 0.498 | I25: =I13/I67 -> 0.498 | J25: =J13/J67 -> 0.498 | K25: =K13/K67 -> 0.498 | L25: =L13/L67 -> 0.498 | ... AO25: =AO13/AO67 -> 0.498
A26: default | B26: solar_pv | C26: discount_rate | D26: per unit | E26: 0.082 | F26: 0.082 | G26: 0.082 | H26: 0.082 | I26: 0.082 | J26: 0.082 | K26: 0.082 | L26: 0.082 | M26: 0.082 | N26: 0.082 | O26: 0.082 | P26: 0.082 | Q26: 0.082 | R26: 0.082 | S26: 0.082 | T26: 0.082 | U26: 0.082 | V26: 0.082 | W26: 0.082 | X26: 0.082 | Y26: 0.082 | Z26: 0.082 | AA26: 0.082 | AB26: 0.082 | AC26: 0.082 | AD26: 0.082 | AE26: 0.082 | AF26: =AE26 -> 0.082 | AG26: =AF26 -> 0.082 | AH26: =AG26 -> 0.082 | AI26: =AH26 -> 0.082 | AJ26: =AI26 -> 0.082 | AK26: =AJ26 -> 0.082 | AL26: =AK26 -> 0.082 | AM26: =AL26 -> 0.082 | ... AO26: =AN26 -> 0.082
A27: default | B27: solar_pv_rooftop | C27: discount_rate | D27: per unit | E27: 0.082 | F27: 0.082 | G27: 0.082 | H27: 0.082 | I27: 0.082 | J27: 0.082 | K27: 0.082 | L27: 0.082 | M27: 0.082 | N27: 0.082 | O27: 0.082 | P27: 0.082 | Q27: 0.082 | R27: 0.082 | S27: 0.082 | T27: 0.082 | U27: 0.082 | V27: 0.082 | W27: 0.082 | X27: 0.082 | Y27: 0.082 | Z27: 0.082 | AA27: 0.082 | AB27: 0.082 | AC27: 0.082 | AD27: 0.082 | AE27: 0.082 | AF27: =AE27 -> 0.082 | AG27: =AF27 -> 0.082 | AH27: =AG27 -> 0.082 | AI27: =AH27 -> 0.082 | AJ27: =AI27 -> 0.082 | AK27: =AJ27 -> 0.082 | AL27: =AK27 -> 0.082 | AM27: =AL27 -> 0.082 | ... AO27: =AN27 -> 0.082
A28: default | B28: solar_pv_low | C28: discount_rate | D28: per unit | E28: 0.082 | F28: 0.082 | G28: 0.082 | H28: 0.082 | I28: 0.082 | J28: 0.082 | K28: 0.082 | L28: 0.082 | M28: 0.082 | N28: 0.082 | O28: 0.082 | P28: 0.082 | Q28: 0.082 | R28: 0.082 | S28: 0.082 | T28: 0.082 | U28: 0.082 | V28: 0.082 | W28: 0.082 | X28: 0.082 | Y28: 0.082 | Z28: 0.082 | AA28: 0.082 | AB28: 0.082 | AC28: 0.082 | AD28: 0.082 | AE28: 0.082 | AF28: =AE28 -> 0.082 | AG28: =AF28 -> 0.082 | AH28: =AG28 -> 0.082 | AI28: =AH28 -> 0.082 | AJ28: =AI28 -> 0.082 | AK28: =AJ28 -> 0.082 | AL28: =AK28 -> 0.082 | AM28: =AL28 -> 0.082 | ... AO28: =AN28 -> 0.082
A29: default | B29: wind | C29: discount_rate | D29: per unit | E29: 0.082 | F29: 0.082 | G29: 0.082 | H29: 0.082 | I29: 0.082 | J29: 0.082 | K29: 0.082 | L29: 0.082 | M29: 0.082 | N29: 0.082 | O29: 0.082 | P29: 0.082 | Q29: 0.082 | R29: 0.082 | S29: 0.082 | T29: 0.082 | U29: 0.082 | V29: 0.082 | W29: 0.082 | X29: 0.082 | Y29: 0.082 | Z29: 0.082 | AA29: 0.082 | AB29: 0.082 | AC29: 0.082 | AD29: 0.082 | AE29: 0.082 | AF29: =AE29 -> 0.082 | AG29: =AF29 -> 0.082 | AH29: =AG29 -> 0.082 | AI29: =AH29 -> 0.082 | AJ29: =AI29 -> 0.082 | AK29: =AJ29 -> 0.082 | AL29: =AK29 -> 0.082 | AM29: =AL29 -> 0.082 | ... AO29: =AN29 -> 0.082
A30: default | B30: wind_low | C30: discount_rate | D30: per unit | E30: 0.082 | F30: 0.082 | G30: 0.082 | H30: 0.082 | I30: 0.082 | J30: 0.082 | K30: 0.082 | L30: 0.082 | M30: 0.082 | N30: 0.082 | O30: 0.082 | P30: 0.082 | Q30: 0.082 | R30: 0.082 | S30: 0.082 | T30: 0.082 | U30: 0.082 | V30: 0.082 | W30: 0.082 | X30: 0.082 | Y30: 0.082 | Z30: 0.082 | AA30: 0.082 | AB30: 0.082 | AC30: 0.082 | AD30: 0.082 | AE30: 0.082 | AF30: =AE30 -> 0.082 | AG30: =AF30 -> 0.082 | AH30: =AG30 -> 0.082 | AI30: =AH30 -> 0.082 | AJ30: =AI30 -> 0.082 | AK30: =AJ30 -> 0.082 | AL30: =AK30 -> 0.082 | AM30: =AL30 -> 0.082 | ... AO30: =AN30 -> 0.082
A31: default | B31: biomass_forestry | C31: heat_rate | D31: GJ/MWh | E31: 14.132 | F31: 14.132 | G31: 14.132 | H31: 14.132 | I31: 14.132 | J31: 14.132 | K31: 14.132 | L31: 14.132 | M31: 14.132 | N31: 14.132 | O31: 14.132 | P31: 14.132 | Q31: 14.132 | R31: 14.132 | S31: 14.132 | T31: 14.132 | U31: 14.132 | V31: 14.132 | W31: 14.132 | X31: 14.132 | Y31: 14.132 | Z31: 14.132 | AA31: 14.132 | AB31: 14.132 | AC31: 14.132 | AD31: 14.132 | AE31: 14.132 | AF31: =AE31 -> 14.132 | AG31: =AF31 -> 14.132 | AH31: =AG31 -> 14.132 | AI31: =AH31 -> 14.132 | AJ31: =AI31 -> 14.132 | AK31: =AJ31 -> 14.132 | AL31: =AK31 -> 14.132 | AM31: =AL31 -> 14.132 | ... AO31: =AN31 -> 14.132
A32: default | B32: biomass_landfill_gas | C32: heat_rate | D32: GJ/MWh | E32: 12.302 | F32: 12.302 | G32: 12.302 | H32: 12.302 | I32: 12.302 | J32: 12.302 | K32: 12.302 | L32: 12.302 | M32: 12.302 | N32: 12.302 | O32: 12.302 | P32: 12.302 | Q32: 12.302 | R32: 12.302 | S32: 12.302 | T32: 12.302 | U32: 12.302 | V32: 12.302 | W32: 12.302 | X32: 12.302 | Y32: 12.302 | Z32: 12.302 | AA32: 12.302 | AB32: 12.302 | AC32: 12.302 | AD32: 12.302 | AE32: 12.302 | AF32: =AE32 -> 12.302 | AG32: =AF32 -> 12.302 | AH32: =AG32 -> 12.302 | AI32: =AH32 -> 12.302 | AJ32: =AI32 -> 12.302 | AK32: =AJ32 -> 12.302 | AL32: =AK32 -> 12.302 | AM32: =AL32 -> 12.302 | ... AO32: =AN32 -> 12.302
A33: default | B33: biomass_biogas | C33: heat_rate | D33: GJ/MWh | E33: 11.999 | F33: 11.999 | G33: 11.999 | H33: 11.999 | I33: 11.999 | J33: 11.999 | K33: 11.999 | L33: 11.999 | M33: 11.999 | N33: 11.999 | O33: 11.999 | P33: 11.999 | Q33: 11.999 | R33: 11.999 | S33: 11.999 | T33: 11.999 | U33: 11.999 | V33: 11.999 | W33: 11.999 | X33: 11.999 | Y33: 11.999 | Z33: 11.999 | AA33: 11.999 | AB33: 11.999 | AC33: 11.999 | AD33: 11.999 | AE33: 11.999 | AF33: =AE33 -> 11.999 | AG33: =AF33 -> 11.999 | AH33: =AG33 -> 11.999 | AI33: =AH33 -> 11.999 | AJ33: =AI33 -> 11.999 | AK33: =AJ33 -> 11.999 | AL33: =AK33 -> 11.999 | AM33: =AL33 -> 11.999 | ... AO33: =AN33 -> 11.999
A34: default | B34: biomass_MSW | C34: heat_rate | D34: GJ/MWh | E34: 18.991 | F34: 18.991 | G34: 18.991 | H34: 18.991 | I34: 18.991 | J34: 18.991 | K34: 18.991 | L34: 18.991 | M34: 18.991 | N34: 18.991 | O34: 18.991 | P34: 18.991 | Q34: 18.991 | R34: 18.991 | S34: 18.991 | T34: 18.991 | U34: 18.991 | V34: 18.991 | W34: 18.991 | X34: 18.991 | Y34: 18.991 | Z34: 18.991 | AA34: 18.991 | AB34: 18.991 | AC34: 18.991 | AD34: 18.991 | AE34: 18.991 | AF34: =AE34 -> 18.991 | AG34: =AF34 -> 18.991 | AH34: =AG34 -> 18.991 | AI34: =AH34 -> 18.991 | AJ34: =AI34 -> 18.991 | AK34: =AJ34 -> 18.991 | AL34: =AK34 -> 18.991 | AM34: =AL34 -> 18.991 | ... AO34: =AN34 -> 18.991
A35: default | B35: ccgt_steam | C35: heat_rate | D35: GJ/MWh | E35: 0 | F35: 0 | G35: 0 | H35: 0 | I35: 0 | J35: 0 | K35: 0 | L35: 0 | M35: 0 | N35: 0 | O35: 0 | P35: 0 | Q35: 0 | R35: 0 | S35: 0 | T35: 0 | U35: 0 | V35: 0 | W35: 0 | X35: 0 | Y35: 0 | Z35: 0 | AA35: 0 | AB35: 0 | AC35: 0 | AD35: 0 | AE35: 0 | AF35: =AE35 -> 0 | AG35: =AF35 -> 0 | AH35: =AG35 -> 0 | AI35: =AH35 -> 0 | AJ35: =AI35 -> 0 | AK35: =AJ35 -> 0 | AL35: =AK35 -> 0 | AM35: =AL35 -> 0 | ... AO35: =AN35 -> 0
A36: default | B36: coal | C36: heat_rate | D36: GJ/MWh | E36: 9.776 | F36: 9.776 | G36: 9.776 | H36: 9.776 | I36: 9.776 | J36: 9.776 | K36: 9.776 | L36: 9.776 | M36: 9.776 | N36: 9.776 | O36: 9.776 | P36: 9.776 | Q36: 9.776 | R36: 9.776 | S36: 9.776 | T36: 9.776 | U36: 9.776 | V36: 9.776 | W36: 9.776 | X36: 9.776 | Y36: 9.776 | Z36: 9.776 | AA36: 9.776 | AB36: 9.776 | AC36: 9.776 | AD36: 9.776 | AE36: 9.776 | AF36: =AE36 -> 9.776 | AG36: =AF36 -> 9.776 | AH36: =AG36 -> 9.776 | AI36: =AH36 -> 9.776 | AJ36: =AI36 -> 9.776 | AK36: =AJ36 -> 9.776 | AL36: =AK36 -> 9.776 | AM36: =AL36 -> 9.776 | ... AO36: =AN36 -> 9.776
A37: default | B37: nuclear | C37: heat_rate | D37: GJ/MWh | E37: 11.25 | F37: 11.25 | G37: 11.25 | H37: 11.25 | I37: 11.25 | J37: 11.25 | K37: 11.25 | L37: 11.25 | M37: 11.25 | N37: 11.25 | O37: 11.25 | P37: 11.25 | Q37: 11.25 | R37: 11.25 | S37: 11.25 | T37: 11.25 | U37: 11.25 | V37: 11.25 | W37: 11.25 | X37: 11.25 | Y37: 11.25 | Z37: 11.25 | AA37: 11.25 | AB37: 11.25 | AC37: 11.25 | AD37: 11.25 | AE37: 11.25 | AF37: =AE37 -> 11.25 | AG37: =AF37 -> 11.25 | AH37: =AG37 -> 11.25 | AI37: =AH37 -> 11.25 | AJ37: =AI37 -> 11.25 | AK37: =AJ37 -> 11.25 | AL37: =AK37 -> 11.25 | AM37: =AL37 -> 11.25 | ... AO37: =AN37 -> 11.25
A38: default | B38: ocgt_diesel | C38: heat_rate | D38: GJ/MWh | E38: 9.453 | F38: 9.453 | G38: 9.453 | H38: 9.453 | I38: 9.453 | J38: 9.453 | K38: 9.453 | L38: 9.453 | M38: 9.453 | N38: 9.453 | O38: 9.453 | P38: 9.453 | Q38: 9.453 | R38: 9.453 | S38: 9.453 | T38: 9.453 | U38: 9.453 | V38: 9.453 | W38: 9.453 | X38: 9.453 | Y38: 9.453 | Z38: 9.453 | AA38: 9.453 | AB38: 9.453 | AC38: 9.453 | AD38: 9.453 | AE38: 9.453 | AF38: =AE38 -> 9.453 | AG38: =AF38 -> 9.453 | AH38: =AG38 -> 9.453 | AI38: =AH38 -> 9.453 | AJ38: =AI38 -> 9.453 | AK38: =AJ38 -> 9.453 | AL38: =AK38 -> 9.453 | AM38: =AL38 -> 9.453 | ... AO38: =AN38 -> 9.453
A39: default | B39: ocgt_diesel_emg | C39: heat_rate | D39: =D38 -> GJ/MWh | E39: 9.453 | F39: =F38 -> 9.453 | G39: =G38 -> 9.453 | H39: =H38 -> 9.453 | I39: =I38 -> 9.453 | J39: =J38 -> 9.453 | K39: =K38 -> 9.453 | L39: =L38 -> 9.453 | M39: =M38 -> 9.453 | ... AE39: =AE38 -> 9.453 | AF39: =AE39 -> 9.453 | AG39: =AF39 -> 9.453 | AH39: =AG39 -> 9.453 | AI39: =AH39 -> 9.453 | AJ39: =AI39 -> 9.453 | AK39: =AJ39 -> 9.453 | AL39: =AK39 -> 9.453 | AM39: =AL39 -> 9.453 | ... AO39: =AN39 -> 9.453
A40: default | B40: ocgt_gas | C40: heat_rate | D40: GJ/MWh | E40: 9.453 | F40: 9.453 | G40: 9.453 | H40: 9.453 | I40: 9.453 | J40: 9.453 | K40: 9.453 | L40: 9.453 | M40: 9.453 | N40: 9.453 | O40: 9.453 | P40: 9.453 | Q40: 9.453 | R40: 9.453 | S40: 9.453 | T40: 9.453 | U40: 9.453 | V40: 9.453 | W40: 9.453 | X40: 9.453 | Y40: 9.453 | Z40: 9.453 | AA40: 9.453 | AB40: 9.453 | AC40: 9.453 | AD40: 9.453 | AE40: 9.453 | AF40: =AE40 -> 9.453 | AG40: =AF40 -> 9.453 | AH40: =AG40 -> 9.453 | AI40: =AH40 -> 9.453 | AJ40: =AI40 -> 9.453 | AK40: =AJ40 -> 9.453 | AL40: =AK40 -> 9.453 | AM40: =AL40 -> 9.453 | ... AO40: =AN40 -> 9.453
A41: default | B41: ocgt_gas_h2_40 | C41: heat_rate | D41: GJ/MWh | E41: 9.453 | F41: =F40 -> 9.453 | G41: =G40 -> 9.453 | H41: =H40 -> 9.453 | I41: =I40 -> 9.453 | J41: =J40 -> 9.453 | K41: =K40 -> 9.453 | L41: =L40 -> 9.453 | M41: =M40 -> 9.453 | ... AE41: =AE40 -> 9.453 | AF41: =AE41 -> 9.453 | AG41: =AF41 -> 9.453 | AH41: =AG41 -> 9.453 | AI41: =AH41 -> 9.453 | AJ41: =AI41 -> 9.453 | AK41: =AJ41 -> 9.453 | AL41: =AK41 -> 9.453 | AM41: =AL41 -> 9.453 | ... AO41: =AN41 -> 9.453
A42: default | B42: ocgt_gas_h2_45 | C42: heat_rate | D42: GJ/MWh | E42: 9.453 | F42: =F41 -> 9.453 | G42: =G41 -> 9.453 | H42: =H41 -> 9.453 | I42: =I41 -> 9.453 | J42: =J41 -> 9.453 | K42: =K41 -> 9.453 | L42: =L41 -> 9.453 | M42: =M41 -> 9.453 | ... AE42: =AE41 -> 9.453 | AF42: =AE42 -> 9.453 | AG42: =AF42 -> 9.453 | AH42: =AG42 -> 9.453 | AI42: =AH42 -> 9.453 | AJ42: =AI42 -> 9.453 | AK42: =AJ42 -> 9.453 | AL42: =AK42 -> 9.453 | AM42: =AL42 -> 9.453 | ... AO42: =AN42 -> 9.453
A43: default | B43: ocgt_gas_h2_50 | C43: heat_rate | D43: GJ/MWh | E43: 9.453 | F43: =F42 -> 9.453 | G43: =G42 -> 9.453 | H43: =H42 -> 9.453 | I43: =I42 -> 9.453 | J43: =J42 -> 9.453 | K43: =K42 -> 9.453 | L43: =L42 -> 9.453 | M43: =M42 -> 9.453 | ... AE43: =AE42 -> 9.453 | AF43: =AE43 -> 9.453 | AG43: =AF43 -> 9.453 | AH43: =AG43 -> 9.453 | AI43: =AH43 -> 9.453 | AJ43: =AI43 -> 9.453 | AK43: =AJ43 -> 9.453 | AL43: =AK43 -> 9.453 | AM43: =AL43 -> 9.453 | ... AO43: =AN43 -> 9.453
A44: default | B44: ocgt_gas_h2_55 | C44: heat_rate | D44: GJ/MWh | E44: 9.453 | F44: =F43 -> 9.453 | G44: =G43 -> 9.453 | H44: =H43 -> 9.453 | I44: =I43 -> 9.453 | J44: =J43 -> 9.453 | K44: =K43 -> 9.453 | L44: =L43 -> 9.453 | M44: =M43 -> 9.453 | ... AE44: =AE43 -> 9.453 | AF44: =AE44 -> 9.453 | AG44: =AF44 -> 9.453 | AH44: =AG44 -> 9.453 | AI44: =AH44 -> 9.453 | AJ44: =AI44 -> 9.453 | AK44: =AJ44 -> 9.453 | AL44: =AK44 -> 9.453 | AM44: =AL44 -> 9.453 | ... AO44: =AN44 -> 9.453
A45: default | B45: ocgt_gas_h2_60 | C45: heat_rate | D45: GJ/MWh | E45: 9.453 | F45: =F44 -> 9.453 | G45: =G44 -> 9.453 | H45: =H44 -> 9.453 | I45: =I44 -> 9.453 | J45: =J44 -> 9.453 | K45: =K44 -> 9.453 | L45: =L44 -> 9.453 | M45: =M44 -> 9.453 | ... AE45: =AE44 -> 9.453 | AF45: =AE45 -> 9.453 | AG45: =AF45 -> 9.453 | AH45: =AG45 -> 9.453 | AI45: =AH45 -> 9.453 | AJ45: =AI45 -> 9.453 | AK45: =AJ45 -> 9.453 | AL45: =AK45 -> 9.453 | AM45: =AL45 -> 9.453 | ... AO45: =AN45 -> 9.453
A46: default | B46: ocgt_blend | C46: heat_rate | D46: GJ/MWh | E46: 9.453 | F46: =F45 -> 9.453 | G46: =G45 -> 9.453 | H46: =H45 -> 9.453 | I46: =I45 -> 9.453 | J46: =J45 -> 9.453 | K46: =K45 -> 9.453 | L46: =L45 -> 9.453 | M46: =M45 -> 9.453 | ... AE46: =AE45 -> 9.453 | AF46: =AE46 -> 9.453 | AG46: =AF46 -> 9.453 | AH46: =AG46 -> 9.453 | AI46: =AH46 -> 9.453 | AJ46: =AI46 -> 9.453 | AK46: =AJ46 -> 9.453 | AL46: =AK46 -> 9.453 | AM46: =AL46 -> 9.453 | ... AO46: =AN46 -> 9.453
A47: default | B47: battery_1h | C47: efficiency | D47: per unit | E47: 0.89 | F47: 0.89 | G47: 0.89 | H47: 0.89 | I47: 0.89 | J47: 0.89 | K47: 0.89 | L47: 0.89 | M47: 0.89 | N47: 0.89 | O47: 0.89 | P47: 0.89 | Q47: 0.89 | R47: 0.89 | S47: 0.89 | T47: 0.89 | U47: 0.89 | V47: 0.89 | W47: 0.89 | X47: 0.89 | Y47: 0.89 | Z47: 0.89 | AA47: 0.89 | AB47: 0.89 | AC47: 0.89 | AD47: 0.89 | AE47: 0.89 | AF47: =AE47 -> 0.89 | AG47: =AF47 -> 0.89 | AH47: =AG47 -> 0.89 | AI47: =AH47 -> 0.89 | AJ47: =AI47 -> 0.89 | AK47: =AJ47 -> 0.89 | AL47: =AK47 -> 0.89 | AM47: =AL47 -> 0.89 | ... AO47: =AN47 -> 0.89
A48: default | B48: battery_4h | C48: efficiency | D48: per unit | E48: 0.89 | F48: 0.89 | G48: 0.89 | H48: 0.89 | I48: 0.89 | J48: 0.89 | K48: 0.89 | L48: 0.89 | M48: 0.89 | N48: 0.89 | O48: 0.89 | P48: 0.89 | Q48: 0.89 | R48: 0.89 | S48: 0.89 | T48: 0.89 | U48: 0.89 | V48: 0.89 | W48: 0.89 | X48: 0.89 | Y48: 0.89 | Z48: 0.89 | AA48: 0.89 | AB48: 0.89 | AC48: 0.89 | AD48: 0.89 | AE48: 0.89 | AF48: =AE48 -> 0.89 | AG48: =AF48 -> 0.89 | AH48: =AG48 -> 0.89 | AI48: =AH48 -> 0.89 | AJ48: =AI48 -> 0.89 | AK48: =AJ48 -> 0.89 | AL48: =AK48 -> 0.89 | AM48: =AL48 -> 0.89 | ... AO48: =AN48 -> 0.89
A49: default | B49: battery_8h | C49: efficiency | D49: per unit | E49: 0.89 | F49: 0.89 | G49: 0.89 | H49: 0.89 | I49: 0.89 | J49: 0.89 | K49: 0.89 | L49: 0.89 | M49: 0.89 | N49: 0.89 | O49: 0.89 | P49: 0.89 | Q49: 0.89 | R49: 0.89 | S49: 0.89 | T49: 0.89 | U49: 0.89 | V49: 0.89 | W49: 0.89 | X49: 0.89 | Y49: 0.89 | Z49: 0.89 | AA49: 0.89 | AB49: 0.89 | AC49: 0.89 | AD49: 0.89 | AE49: 0.89 | AF49: =AE49 -> 0.89 | AG49: =AF49 -> 0.89 | AH49: =AG49 -> 0.89 | AI49: =AH49 -> 0.89 | AJ49: =AI49 -> 0.89 | AK49: =AJ49 -> 0.89 | AL49: =AK49 -> 0.89 | AM49: =AL49 -> 0.89 | ... AO49: =AN49 -> 0.89
A50: default | B50: biomass_forestry | C50: efficiency | D50: per unit | E50: 0.25474101 | F50: 0.25474101 | G50: 0.25474101 | H50: 0.25474101 | I50: 0.25474101 | J50: 0.25474101 | K50: 0.25474101 | L50: 0.25474101 | M50: 0.25474101 | N50: 0.25474101 | O50: 0.25474101 | P50: 0.25474101 | Q50: 0.25474101 | R50: 0.25474101 | S50: 0.25474101 | T50: 0.25474101 | U50: 0.25474101 | V50: 0.25474101 | W50: 0.25474101 | X50: 0.25474101 | Y50: 0.25474101 | Z50: 0.25474101 | AA50: 0.25474101 | AB50: 0.25474101 | AC50: 0.25474101 | AD50: 0.25474101 | AE50: 0.25474101 | AF50: =AE50 -> 0.25474101 | AG50: =AF50 -> 0.25474101 | AH50: =AG50 -> 0.25474101 | AI50: =AH50 -> 0.25474101 | AJ50: =AI50 -> 0.25474101 | AK50: =AJ50 -> 0.25474101 | AL50: =AK50 -> 0.25474101 | AM50: =AL50 -> 0.25474101 | ... AO50: =AN50 -> 0.25474101
A51: default | B51: biomass_landfill_gas | C51: efficiency | D51: per unit | E51: 0.29263534 | F51: 0.29263534 | G51: 0.29263534 | H51: 0.29263534 | I51: 0.29263534 | J51: 0.29263534 | K51: 0.29263534 | L51: 0.29263534 | M51: 0.29263534 | N51: 0.29263534 | O51: 0.29263534 | P51: 0.29263534 | Q51: 0.29263534 | R51: 0.29263534 | S51: 0.29263534 | T51: 0.29263534 | U51: 0.29263534 | V51: 0.29263534 | W51: 0.29263534 | X51: 0.29263534 | Y51: 0.29263534 | Z51: 0.29263534 | AA51: 0.29263534 | AB51: 0.29263534 | AC51: 0.29263534 | AD51: 0.29263534 | AE51: 0.29263534 | AF51: =AE51 -> 0.29263534 | AG51: =AF51 -> 0.29263534 | AH51: =AG51 -> 0.29263534 | AI51: =AH51 -> 0.29263534 | AJ51: =AI51 -> 0.29263534 | AK51: =AJ51 -> 0.29263534 | AL51: =AK51 -> 0.29263534 | AM51: =AL51 -> 0.29263534 | ... AO51: =AN51 -> 0.29263534
A52: default | B52: biomass_biogas | C52: efficiency | D52: per unit | E52: 0.300025 | F52: 0.300025 | G52: 0.300025 | H52: 0.300025 | I52: 0.300025 | J52: 0.300025 | K52: 0.300025 | L52: 0.300025 | M52: 0.300025 | N52: 0.300025 | O52: 0.300025 | P52: 0.300025 | Q52: 0.300025 | R52: 0.300025 | S52: 0.300025 | T52: 0.300025 | U52: 0.300025 | V52: 0.300025 | W52: 0.300025 | X52: 0.300025 | Y52: 0.300025 | Z52: 0.300025 | AA52: 0.300025 | AB52: 0.300025 | AC52: 0.300025 | AD52: 0.300025 | AE52: 0.300025 | AF52: =AE52 -> 0.300025 | AG52: =AF52 -> 0.300025 | AH52: =AG52 -> 0.300025 | AI52: =AH52 -> 0.300025 | AJ52: =AI52 -> 0.300025 | AK52: =AJ52 -> 0.300025 | AL52: =AK52 -> 0.300025 | AM52: =AL52 -> 0.300025 | ... AO52: =AN52 -> 0.300025
A53: default | B53: biomass_MSW | C53: efficiency | D53: per unit | E53: 0.18956348 | F53: 0.18956348 | G53: 0.18956348 | H53: 0.18956348 | I53: 0.18956348 | J53: 0.18956348 | K53: 0.18956348 | L53: 0.18956348 | M53: 0.18956348 | N53: 0.18956348 | O53: 0.18956348 | P53: 0.18956348 | Q53: 0.18956348 | R53: 0.18956348 | S53: 0.18956348 | T53: 0.18956348 | U53: 0.18956348 | V53: 0.18956348 | W53: 0.18956348 | X53: 0.18956348 | Y53: 0.18956348 | Z53: 0.18956348 | AA53: 0.18956348 | AB53: 0.18956348 | AC53: 0.18956348 | AD53: 0.18956348 | AE53: 0.18956348 | AF53: =AE53 -> 0.18956348 | AG53: =AF53 -> 0.18956348 | AH53: =AG53 -> 0.18956348 | AI53: =AH53 -> 0.18956348 | AJ53: =AI53 -> 0.18956348 | AK53: =AJ53 -> 0.18956348 | AL53: =AK53 -> 0.18956348 | AM53: =AL53 -> 0.18956348 | ... AO53: =AN53 -> 0.18956348
A54: default | B54: ccgt_steam | C54: efficiency | D54: per unit | E54: 1 | F54: 1 | G54: 1 | H54: 1 | I54: 1 | J54: 1 | K54: 1 | L54: 1 | M54: 1 | N54: 1 | O54: 1 | P54: 1 | Q54: 1 | R54: 1 | S54: 1 | T54: 1 | U54: 1 | V54: 1 | W54: 1 | X54: 1 | Y54: 1 | Z54: 1 | AA54: 1 | AB54: 1 | AC54: 1 | AD54: 1 | AE54: 1 | AF54: =AE54 -> 1 | AG54: =AF54 -> 1 | AH54: =AG54 -> 1 | AI54: =AH54 -> 1 | AJ54: =AI54 -> 1 | AK54: =AJ54 -> 1 | AL54: =AK54 -> 1 | AM54: =AL54 -> 1 | ... AO54: =AN54 -> 1
A55: default | B55: coal | C55: efficiency | D55: per unit | E55: 0.36824877 | F55: 0.36824877 | G55: 0.36824877 | H55: 0.36824877 | I55: 0.36824877 | J55: 0.36824877 | K55: 0.36824877 | L55: 0.36824877 | M55: 0.36824877 | N55: 0.36824877 | O55: 0.36824877 | P55: 0.36824877 | Q55: 0.36824877 | R55: 0.36824877 | S55: 0.36824877 | T55: 0.36824877 | U55: 0.36824877 | V55: 0.36824877 | W55: 0.36824877 | X55: 0.36824877 | Y55: 0.36824877 | Z55: 0.36824877 | AA55: 0.36824877 | AB55: 0.36824877 | AC55: 0.36824877 | AD55: 0.36824877 | AE55: 0.36824877 | AF55: =AE55 -> 0.36824877 | AG55: =AF55 -> 0.36824877 | AH55: =AG55 -> 0.36824877 | AI55: =AH55 -> 0.36824877 | AJ55: =AI55 -> 0.36824877 | AK55: =AJ55 -> 0.36824877 | AL55: =AK55 -> 0.36824877 | AM55: =AL55 -> 0.36824877 | ... AO55: =AN55 -> 0.36824877
A56: default | B56: nuclear | C56: efficiency | D56: per unit | E56: 0.32 | F56: 0.32 | G56: 0.32 | H56: 0.32 | I56: 0.32 | J56: 0.32 | K56: 0.32 | L56: 0.32 | M56: 0.32 | N56: 0.32 | O56: 0.32 | P56: 0.32 | Q56: 0.32 | R56: 0.32 | S56: 0.32 | T56: 0.32 | U56: 0.32 | V56: 0.32 | W56: 0.32 | X56: 0.32 | Y56: 0.32 | Z56: 0.32 | AA56: 0.32 | AB56: 0.32 | AC56: 0.32 | AD56: 0.32 | AE56: 0.32 | AF56: =AE56 -> 0.32 | AG56: =AF56 -> 0.32 | AH56: =AG56 -> 0.32 | AI56: =AH56 -> 0.32 | AJ56: =AI56 -> 0.32 | AK56: =AJ56 -> 0.32 | AL56: =AK56 -> 0.32 | AM56: =AL56 -> 0.32 | ... AO56: =AN56 -> 0.32
A57: default | B57: ocgt_diesel | C57: efficiency | D57: per unit | E57: 0.38083148 | F57: 0.38083148 | G57: 0.38083148 | H57: 0.38083148 | I57: 0.38083148 | J57: 0.38083148 | K57: 0.38083148 | L57: 0.38083148 | M57: 0.38083148 | N57: 0.38083148 | O57: 0.38083148 | P57: 0.38083148 | Q57: 0.38083148 | R57: 0.38083148 | S57: 0.38083148 | T57: 0.38083148 | U57: 0.38083148 | V57: 0.38083148 | W57: 0.38083148 | X57: 0.38083148 | Y57: 0.38083148 | Z57: 0.38083148 | AA57: 0.38083148 | AB57: 0.38083148 | AC57: 0.38083148 | AD57: 0.38083148 | AE57: 0.38083148 | AF57: =AE57 -> 0.38083148 | AG57: =AF57 -> 0.38083148 | AH57: =AG57 -> 0.38083148 | AI57: =AH57 -> 0.38083148 | AJ57: =AI57 -> 0.38083148 | AK57: =AJ57 -> 0.38083148 | AL57: =AK57 -> 0.38083148 | AM57: =AL57 -> 0.38083148 | ... AO57: =AN57 -> 0.38083148
A58: default | B58: ocgt_diesel_emg | C58: efficiency | D58: =D57 -> per unit | E58: 0.38083148 | F58: =F57 -> 0.38083148 | G58: =G57 -> 0.38083148 | H58: =H57 -> 0.38083148 | I58: =I57 -> 0.38083148 | J58: =J57 -> 0.38083148 | K58: =K57 -> 0.38083148 | L58: =L57 -> 0.38083148 | M58: =M57 -> 0.38083148 | ... AE58: =AE57 -> 0.38083148 | AF58: =AE58 -> 0.38083148 | AG58: =AF58 -> 0.38083148 | AH58: =AG58 -> 0.38083148 | AI58: =AH58 -> 0.38083148 | AJ58: =AI58 -> 0.38083148 | AK58: =AJ58 -> 0.38083148 | AL58: =AK58 -> 0.38083148 | AM58: =AL58 -> 0.38083148 | ... AO58: =AN58 -> 0.38083148
A59: default | B59: ocgt_gas | C59: =C57 -> efficiency | D59: per unit | E59: 0.38083148 | F59: 0.38083148 | G59: 0.38083148 | H59: 0.38083148 | I59: 0.38083148 | J59: 0.38083148 | K59: 0.38083148 | L59: 0.38083148 | M59: 0.38083148 | N59: 0.38083148 | O59: 0.38083148 | P59: 0.38083148 | Q59: 0.38083148 | R59: 0.38083148 | S59: 0.38083148 | T59: 0.38083148 | U59: 0.38083148 | V59: 0.38083148 | W59: 0.38083148 | X59: 0.38083148 | Y59: 0.38083148 | Z59: 0.38083148 | AA59: 0.38083148 | AB59: 0.38083148 | AC59: 0.38083148 | AD59: 0.38083148 | AE59: 0.38083148 | AF59: =AE59 -> 0.38083148 | AG59: =AF59 -> 0.38083148 | AH59: =AG59 -> 0.38083148 | AI59: =AH59 -> 0.38083148 | AJ59: =AI59 -> 0.38083148 | AK59: =AJ59 -> 0.38083148 | AL59: =AK59 -> 0.38083148 | AM59: =AL59 -> 0.38083148 | ... AO59: =AN59 -> 0.38083148
A60: default | B60: ocgt_gas_h2_40 | C60: =C58 -> efficiency | D60: per unit | E60: 0.38083148 | F60: 0.38083148 | G60: 0.38083148 | H60: 0.38083148 | I60: 0.38083148 | J60: 0.38083148 | K60: 0.38083148 | L60: 0.38083148 | M60: 0.38083148 | N60: 0.38083148 | O60: 0.38083148 | P60: 0.38083148 | Q60: 0.38083148 | R60: 0.38083148 | S60: 0.38083148 | T60: 0.38083148 | U60: 0.38083148 | V60: 0.38083148 | W60: 0.38083148 | X60: 0.38083148 | Y60: 0.38083148 | Z60: 0.38083148 | AA60: 0.38083148 | AB60: 0.38083148 | AC60: 0.38083148 | AD60: 0.38083148 | AE60: 0.38083148 | AF60: =AE60 -> 0.38083148 | AG60: =AF60 -> 0.38083148 | AH60: =AG60 -> 0.38083148 | AI60: =AH60 -> 0.38083148 | AJ60: =AI60 -> 0.38083148 | AK60: =AJ60 -> 0.38083148 | AL60: =AK60 -> 0.38083148 | AM60: =AL60 -> 0.38083148 | ... AO60: =AN60 -> 0.38083148
A61: default | B61: ocgt_gas_h2_45 | C61: =C59 -> efficiency | D61: per unit | E61: 0.38083148 | F61: 0.38083148 | G61: 0.38083148 | H61: 0.38083148 | I61: 0.38083148 | J61: 0.38083148 | K61: 0.38083148 | L61: 0.38083148 | M61: 0.38083148 | N61: 0.38083148 | O61: 0.38083148 | P61: 0.38083148 | Q61: 0.38083148 | R61: 0.38083148 | S61: 0.38083148 | T61: 0.38083148 | U61: 0.38083148 | V61: 0.38083148 | W61: 0.38083148 | X61: 0.38083148 | Y61: 0.38083148 | Z61: 0.38083148 | AA61: 0.38083148 | AB61: 0.38083148 | AC61: 0.38083148 | AD61: 0.38083148 | AE61: 0.38083148 | AF61: =AE61 -> 0.38083148 | AG61: =AF61 -> 0.38083148 | AH61: =AG61 -> 0.38083148 | AI61: =AH61 -> 0.38083148 | AJ61: =AI61 -> 0.38083148 | AK61: =AJ61 -> 0.38083148 | AL61: =AK61 -> 0.38083148 | AM61: =AL61 -> 0.38083148 | ... AO61: =AN61 -> 0.38083148
A62: default | B62: ocgt_gas_h2_50 | C62: =C60 -> efficiency | D62: per unit | E62: 0.38083148 | F62: 0.38083148 | G62: 0.38083148 | H62: 0.38083148 | I62: 0.38083148 | J62: 0.38083148 | K62: 0.38083148 | L62: 0.38083148 | M62: 0.38083148 | N62: 0.38083148 | O62: 0.38083148 | P62: 0.38083148 | Q62: 0.38083148 | R62: 0.38083148 | S62: 0.38083148 | T62: 0.38083148 | U62: 0.38083148 | V62: 0.38083148 | W62: 0.38083148 | X62: 0.38083148 | Y62: 0.38083148 | Z62: 0.38083148 | AA62: 0.38083148 | AB62: 0.38083148 | AC62: 0.38083148 | AD62: 0.38083148 | AE62: 0.38083148 | AF62: =AE62 -> 0.38083148 | AG62: =AF62 -> 0.38083148 | AH62: =AG62 -> 0.38083148 | AI62: =AH62 -> 0.38083148 | AJ62: =AI62 -> 0.38083148 | AK62: =AJ62 -> 0.38083148 | AL62: =AK62 -> 0.38083148 | AM62: =AL62 -> 0.38083148 | ... AO62: =AN62 -> 0.38083148
A63: default | B63: ocgt_gas_h2_55 | C63: =C61 -> efficiency | D63: per unit | E63: 0.38083148 | F63: 0.38083148 | G63: 0.38083148 | H63: 0.38083148 | I63: 0.38083148 | J63: 0.38083148 | K63: 0.38083148 | L63: 0.38083148 | M63: 0.38083148 | N63: 0.38083148 | O63: 0.38083148 | P63: 0.38083148 | Q63: 0.38083148 | R63: 0.38083148 | S63: 0.38083148 | T63: 0.38083148 | U63: 0.38083148 | V63: 0.38083148 | W63: 0.38083148 | X63: 0.38083148 | Y63: 0.38083148 | Z63: 0.38083148 | AA63: 0.38083148 | AB63: 0.38083148 | AC63: 0.38083148 | AD63: 0.38083148 | AE63: 0.38083148 | AF63: =AE63 -> 0.38083148 | AG63: =AF63 -> 0.38083148 | AH63: =AG63 -> 0.38083148 | AI63: =AH63 -> 0.38083148 | AJ63: =AI63 -> 0.38083148 | AK63: =AJ63 -> 0.38083148 | AL63: =AK63 -> 0.38083148 | AM63: =AL63 -> 0.38083148 | ... AO63: =AN63 -> 0.38083148
A64: default | B64: ocgt_gas_h2_60 | C64: =C62 -> efficiency | D64: per unit | E64: 0.38083148 | F64: 0.38083148 | G64: 0.38083148 | H64: 0.38083148 | I64: 0.38083148 | J64: 0.38083148 | K64: 0.38083148 | L64: 0.38083148 | M64: 0.38083148 | N64: 0.38083148 | O64: 0.38083148 | P64: 0.38083148 | Q64: 0.38083148 | R64: 0.38083148 | S64: 0.38083148 | T64: 0.38083148 | U64: 0.38083148 | V64: 0.38083148 | W64: 0.38083148 | X64: 0.38083148 | Y64: 0.38083148 | Z64: 0.38083148 | AA64: 0.38083148 | AB64: 0.38083148 | AC64: 0.38083148 | AD64: 0.38083148 | AE64: 0.38083148 | AF64: =AE64 -> 0.38083148 | AG64: =AF64 -> 0.38083148 | AH64: =AG64 -> 0.38083148 | AI64: =AH64 -> 0.38083148 | AJ64: =AI64 -> 0.38083148 | AK64: =AJ64 -> 0.38083148 | AL64: =AK64 -> 0.38083148 | AM64: =AL64 -> 0.38083148 | ... AO64: =AN64 -> 0.38083148
A65: default | B65: ocgt_blend | C65: =C63 -> efficiency | D65: per unit | E65: 0.38083148 | F65: 0.38083148 | G65: 0.38083148 | H65: 0.38083148 | I65: 0.38083148 | J65: 0.38083148 | K65: 0.38083148 | L65: 0.38083148 | M65: 0.38083148 | N65: 0.38083148 | O65: 0.38083148 | P65: 0.38083148 | Q65: 0.38083148 | R65: 0.38083148 | S65: 0.38083148 | T65: 0.38083148 | U65: 0.38083148 | V65: 0.38083148 | W65: 0.38083148 | X65: 0.38083148 | Y65: 0.38083148 | Z65: 0.38083148 | AA65: 0.38083148 | AB65: 0.38083148 | AC65: 0.38083148 | AD65: 0.38083148 | AE65: 0.38083148 | AF65: =AE65 -> 0.38083148 | AG65: =AF65 -> 0.38083148 | AH65: =AG65 -> 0.38083148 | AI65: =AH65 -> 0.38083148 | AJ65: =AI65 -> 0.38083148 | AK65: =AJ65 -> 0.38083148 | AL65: =AK65 -> 0.38083148 | AM65: =AL65 -> 0.38083148 | ... AO65: =AN65 -> 0.38083148
A66: default | B66: phs | C66: efficiency | D66: per unit | E66: 0.78 | F66: 0.78 | G66: 0.78 | H66: 0.78 | I66: 0.78 | J66: 0.78 | K66: 0.78 | L66: 0.78 | M66: 0.78 | N66: 0.78 | O66: 0.78 | P66: 0.78 | Q66: 0.78 | R66: 0.78 | S66: 0.78 | T66: 0.78 | U66: 0.78 | V66: 0.78 | W66: 0.78 | X66: 0.78 | Y66: 0.78 | Z66: 0.78 | AA66: 0.78 | AB66: 0.78 | AC66: 0.78 | AD66: 0.78 | AE66: 0.78 | AF66: =AE66 -> 0.78 | AG66: =AF66 -> 0.78 | AH66: =AG66 -> 0.78 | AI66: =AH66 -> 0.78 | AJ66: =AI66 -> 0.78 | AK66: =AJ66 -> 0.78 | AL66: =AK66 -> 0.78 | AM66: =AL66 -> 0.78 | ... AO66: =AN66 -> 0.78
A67: default | B67: biomass_forestry | C67: ramp_limit_up | D67: %p_nom/h | E67: 0.5 | F67: 0.5 | G67: 0.5 | H67: 0.5 | I67: 0.5 | J67: 0.5 | K67: 0.5 | L67: 0.5 | M67: 0.5 | N67: 0.5 | O67: 0.5 | P67: 0.5 | Q67: 0.5 | R67: 0.5 | S67: 0.5 | T67: 0.5 | U67: 0.5 | V67: 0.5 | W67: 0.5 | X67: 0.5 | Y67: 0.5 | Z67: 0.5 | AA67: 0.5 | AB67: 0.5 | AC67: 0.5 | AD67: 0.5 | AE67: 0.5 | AF67: =AE67 -> 0.5 | AG67: =AF67 -> 0.5 | AH67: =AG67 -> 0.5 | AI67: =AH67 -> 0.5 | AJ67: =AI67 -> 0.5 | AK67: =AJ67 -> 0.5 | AL67: =AK67 -> 0.5 | AM67: =AL67 -> 0.5 | ... AO67: =AN67 -> 0.5
A68: default | B68: biomass_landfill_gas | C68: ramp_limit_up | D68: %p_nom/h | E68: 1 | F68: 1 | G68: 1 | H68: 1 | I68: 1 | J68: 1 | K68: 1 | L68: 1 | M68: 1 | N68: 1 | O68: 1 | P68: 1 | Q68: 1 | R68: 1 | S68: 1 | T68: 1 | U68: 1 | V68: 1 | W68: 1 | X68: 1 | Y68: 1 | Z68: 1 | AA68: 1 | AB68: 1 | AC68: 1 | AD68: 1 | AE68: 1 | AF68: =AE68 -> 1 | AG68: =AF68 -> 1 | AH68: =AG68 -> 1 | AI68: =AH68 -> 1 | AJ68: =AI68 -> 1 | AK68: =AJ68 -> 1 | AL68: =AK68 -> 1 | AM68: =AL68 -> 1 | ... AO68: =AN68 -> 1
A69: default | B69: biomass_biogas | C69: ramp_limit_up | D69: %p_nom/h | E69: 1 | F69: 1 | G69: 1 | H69: 1 | I69: 1 | J69: 1 | K69: 1 | L69: 1 | M69: 1 | N69: 1 | O69: 1 | P69: 1 | Q69: 1 | R69: 1 | S69: 1 | T69: 1 | U69: 1 | V69: 1 | W69: 1 | X69: 1 | Y69: 1 | Z69: 1 | AA69: 1 | AB69: 1 | AC69: 1 | AD69: 1 | AE69: 1 | AF69: =AE69 -> 1 | AG69: =AF69 -> 1 | AH69: =AG69 -> 1 | AI69: =AH69 -> 1 | AJ69: =AI69 -> 1 | AK69: =AJ69 -> 1 | AL69: =AK69 -> 1 | AM69: =AL69 -> 1 | ... AO69: =AN69 -> 1
A70: default | B70: biomass_MSW | C70: ramp_limit_up | D70: %p_nom/h | E70: 1 | F70: 1 | G70: 1 | H70: 1 | I70: 1 | J70: 1 | K70: 1 | L70: 1 | M70: 1 | N70: 1 | O70: 1 | P70: 1 | Q70: 1 | R70: 1 | S70: 1 | T70: 1 | U70: 1 | V70: 1 | W70: 1 | X70: 1 | Y70: 1 | Z70: 1 | AA70: 1 | AB70: 1 | AC70: 1 | AD70: 1 | AE70: 1 | AF70: =AE70 -> 1 | AG70: =AF70 -> 1 | AH70: =AG70 -> 1 | AI70: =AH70 -> 1 | AJ70: =AI70 -> 1 | AK70: =AJ70 -> 1 | AL70: =AK70 -> 1 | AM70: =AL70 -> 1 | ... AO70: =AN70 -> 1
A71: default | B71: ccgt_steam | C71: ramp_limit_up | D71: %p_nom/h | E71: 0.5 | F71: 0.5 | G71: 0.5 | H71: 0.5 | I71: 0.5 | J71: 0.5 | K71: 0.5 | L71: 0.5 | M71: 0.5 | N71: 0.5 | O71: 0.5 | P71: 0.5 | Q71: 0.5 | R71: 0.5 | S71: 0.5 | T71: 0.5 | U71: 0.5 | V71: 0.5 | W71: 0.5 | X71: 0.5 | Y71: 0.5 | Z71: 0.5 | AA71: 0.5 | AB71: 0.5 | AC71: 0.5 | AD71: 0.5 | AE71: 0.5 | AF71: =AE71 -> 0.5 | AG71: =AF71 -> 0.5 | AH71: =AG71 -> 0.5 | AI71: =AH71 -> 0.5 | AJ71: =AI71 -> 0.5 | AK71: =AJ71 -> 0.5 | AL71: =AK71 -> 0.5 | AM71: =AL71 -> 0.5 | ... AO71: =AN71 -> 0.5
A72: default | B72: coal | C72: ramp_limit_up | D72: %p_nom/h | E72: 0.5 | F72: 0.5 | G72: 0.5 | H72: 0.5 | I72: 0.5 | J72: 0.5 | K72: 0.5 | L72: 0.5 | M72: 0.5 | N72: 0.5 | O72: 0.5 | P72: 0.5 | Q72: 0.5 | R72: 0.5 | S72: 0.5 | T72: 0.5 | U72: 0.5 | V72: 0.5 | W72: 0.5 | X72: 0.5 | Y72: 0.5 | Z72: 0.5 | AA72: 0.5 | AB72: 0.5 | AC72: 0.5 | AD72: 0.5 | AE72: 0.5 | AF72: =AE72 -> 0.5 | AG72: =AF72 -> 0.5 | AH72: =AG72 -> 0.5 | AI72: =AH72 -> 0.5 | AJ72: =AI72 -> 0.5 | AK72: =AJ72 -> 0.5 | AL72: =AK72 -> 0.5 | AM72: =AL72 -> 0.5 | ... AO72: =AN72 -> 0.5
A73: default | B73: nuclear | C73: ramp_limit_up | D73: %p_nom/h | E73: 0.15 | F73: 0.15 | G73: 0.15 | H73: 0.15 | I73: 0.15 | J73: 0.15 | K73: 0.15 | L73: 0.15 | M73: 0.15 | N73: 0.15 | O73: 0.15 | P73: 0.15 | Q73: 0.15 | R73: 0.15 | S73: 0.15 | T73: 0.15 | U73: 0.15 | V73: 0.15 | W73: 0.15 | X73: 0.15 | Y73: 0.15 | Z73: 0.15 | AA73: 0.15 | AB73: 0.15 | AC73: 0.15 | AD73: 0.15 | AE73: 0.15 | AF73: =AE73 -> 0.15 | AG73: =AF73 -> 0.15 | AH73: =AG73 -> 0.15 | AI73: =AH73 -> 0.15 | AJ73: =AI73 -> 0.15 | AK73: =AJ73 -> 0.15 | AL73: =AK73 -> 0.15 | AM73: =AL73 -> 0.15 | ... AO73: =AN73 -> 0.15
A74: default | B74: ocgt_diesel | C74: ramp_limit_up | D74: %p_nom/h | E74: 1 | F74: 1 | G74: 1 | H74: 1 | I74: 1 | J74: 1 | K74: 1 | L74: 1 | M74: 1 | N74: 1 | O74: 1 | P74: 1 | Q74: 1 | R74: 1 | S74: 1 | T74: 1 | U74: 1 | V74: 1 | W74: 1 | X74: 1 | Y74: 1 | Z74: 1 | AA74: 1 | AB74: 1 | AC74: 1 | AD74: 1 | AE74: 1 | AF74: =AE74 -> 1 | AG74: =AF74 -> 1 | AH74: =AG74 -> 1 | AI74: =AH74 -> 1 | AJ74: =AI74 -> 1 | AK74: =AJ74 -> 1 | AL74: =AK74 -> 1 | AM74: =AL74 -> 1 | ... AO74: =AN74 -> 1
A75: default | B75: ocgt_gas | C75: ramp_limit_up | D75: %p_nom/h | E75: 1 | F75: 1 | G75: 1 | H75: 1 | I75: 1 | J75: 1 | K75: 1 | L75: 1 | M75: 1 | N75: 1 | O75: 1 | P75: 1 | Q75: 1 | R75: 1 | S75: 1 | T75: 1 | U75: 1 | V75: 1 | W75: 1 | X75: 1 | Y75: 1 | Z75: 1 | AA75: 1 | AB75: 1 | AC75: 1 | AD75: 1 | AE75: 1 | AF75: =AE75 -> 1 | AG75: =AF75 -> 1 | AH75: =AG75 -> 1 | AI75: =AH75 -> 1 | AJ75: =AI75 -> 1 | AK75: =AJ75 -> 1 | AL75: =AK75 -> 1 | AM75: =AL75 -> 1 | ... AO75: =AN75 -> 1
A76: default | B76: ocgt_gas | C76: ramp_limit_up | D76: %p_nom/h | E76: 1 | F76: 1 | G76: 1 | H76: 1 | I76: 1 | J76: 1 | K76: 1 | L76: 1 | M76: 1 | N76: 1 | O76: 1 | P76: 1 | Q76: 1 | R76: 1 | S76: 1 | T76: 1 | U76: 1 | V76: 1 | W76: 1 | X76: 1 | Y76: 1 | Z76: 1 | AA76: 1 | AB76: 1 | AC76: 1 | AD76: 1 | AE76: 1 | AF76: =AE76 -> 1 | AG76: =AF76 -> 1 | AH76: =AG76 -> 1 | AI76: =AH76 -> 1 | AJ76: =AI76 -> 1 | AK76: =AJ76 -> 1 | AL76: =AK76 -> 1 | AM76: =AL76 -> 1 | ... AO76: =AN76 -> 1
A77: default | B77: biomass_forestry | C77: ramp_limit_down | D77: %p_nom/h | E77: 0.5 | F77: 0.5 | G77: 0.5 | H77: 0.5 | I77: 0.5 | J77: 0.5 | K77: 0.5 | L77: 0.5 | M77: 0.5 | N77: 0.5 | O77: 0.5 | P77: 0.5 | Q77: 0.5 | R77: 0.5 | S77: 0.5 | T77: 0.5 | U77: 0.5 | V77: 0.5 | W77: 0.5 | X77: 0.5 | Y77: 0.5 | Z77: 0.5 | AA77: 0.5 | AB77: 0.5 | AC77: 0.5 | AD77: 0.5 | AE77: 0.5 | AF77: =AE77 -> 0.5 | AG77: =AF77 -> 0.5 | AH77: =AG77 -> 0.5 | AI77: =AH77 -> 0.5 | AJ77: =AI77 -> 0.5 | AK77: =AJ77 -> 0.5 | AL77: =AK77 -> 0.5 | AM77: =AL77 -> 0.5 | ... AO77: =AN77 -> 0.5
... A102: default | B102: ccgt_steam | C102: lifetime | D102: years | E102: 30 | F102: 30 | G102: 30 | H102: 30 | I102: 30 | J102: 30 | K102: 30 | L102: 30 | M102: 30 | N102: 30 | O102: 30 | P102: 30 | Q102: 30 | R102: 30 | S102: 30 | T102: 30 | U102: 30 | V102: 30 | W102: 30 | X102: 30 | Y102: 30 | Z102: 30 | AA102: 30 | AB102: 30 | AC102: 30 | AD102: 30 | AE102: 30 | AF102: =AE102 -> 30 | AG102: =AF102 -> 30 | AH102: =AG102 -> 30 | AI102: =AH102 -> 30 | AJ102: =AI102 -> 30 | AK102: =AJ102 -> 30 | AL102: =AK102 -> 30 | AM102: =AL102 -> 30 | ... AO102: =AN102 -> 30
A103: default | B103: coal | C103: lifetime | D103: years | E103: 50 | F103: =E103 -> 50 | G103: =F103 -> 50 | H103: =G103 -> 50 | I103: =H103 -> 50 | J103: =I103 -> 50 | K103: =J103 -> 50 | L103: =K103 -> 50 | M103: =L103 -> 50 | ... AO103: =AN103 -> 50
A104: default | B104: solar_csp | C104: lifetime | D104: years | E104: 30 | F104: 30 | G104: 30 | H104: 30 | I104: 30 | J104: 30 | K104: 30 | L104: 30 | M104: 30 | N104: 30 | O104: 30 | P104: 30 | Q104: 30 | R104: 30 | S104: 30 | T104: 30 | U104: 30 | V104: 30 | W104: 30 | X104: 30 | Y104: 30 | Z104: 30 | AA104: 30 | AB104: 30 | AC104: 30 | AD104: 30 | AE104: 30 | AF104: =AE104 -> 30 | AG104: =AF104 -> 30 | AH104: =AG104 -> 30 | AI104: =AH104 -> 30 | AJ104: =AI104 -> 30 | AK104: =AJ104 -> 30 | AL104: =AK104 -> 30 | AM104: =AL104 -> 30 | ... AO104: =AN104 -> 30
A105: default | B105: HVAC_overhead | C105: lifetime | D105: years | E105: 40 | F105: 40 | G105: 40 | H105: 40 | I105: 40 | J105: 40 | K105: 40 | L105: 40 | M105: 40 | N105: 40 | O105: 40 | P105: 40 | Q105: 40 | R105: 40 | S105: 40 | T105: 40 | U105: 40 | V105: 40 | W105: 40 | X105: 40 | Y105: 40 | Z105: 40 | AA105: 40 | AB105: 40 | AC105: 40 | AD105: 40 | AE105: 40 | AF105: =AE105 -> 40 | AG105: =AF105 -> 40 | AH105: =AG105 -> 40 | AI105: =AH105 -> 40 | AJ105: =AI105 -> 40 | AK105: =AJ105 -> 40 | AL105: =AK105 -> 40 | AM105: =AL105 -> 40 | ... AO105: =AN105 -> 40
A106: default | B106: HVDC_inverter_pair | C106: lifetime | D106: years | E106: 40 | F106: 40 | G106: 40 | H106: 40 | I106: 40 | J106: 40 | K106: 40 | L106: 40 | M106: 40 | N106: 40 | O106: 40 | P106: 40 | Q106: 40 | R106: 40 | S106: 40 | T106: 40 | U106: 40 | V106: 40 | W106: 40 | X106: 40 | Y106: 40 | Z106: 40 | AA106: 40 | AB106: 40 | AC106: 40 | AD106: 40 | AE106: 40 | AF106: =AE106 -> 40 | AG106: =AF106 -> 40 | AH106: =AG106 -> 40 | AI106: =AH106 -> 40 | AJ106: =AI106 -> 40 | AK106: =AJ106 -> 40 | AL106: =AK106 -> 40 | AM106: =AL106 -> 40 | ... AO106: =AN106 -> 40
A107: default | B107: HVDC_overhead | C107: lifetime | D107: years | E107: 40 | F107: 40 | G107: 40 | H107: 40 | I107: 40 | J107: 40 | K107: 40 | L107: 40 | M107: 40 | N107: 40 | O107: 40 | P107: 40 | Q107: 40 | R107: 40 | S107: 40 | T107: 40 | U107: 40 | V107: 40 | W107: 40 | X107: 40 | Y107: 40 | Z107: 40 | AA107: 40 | AB107: 40 | AC107: 40 | AD107: 40 | AE107: 40 | AF107: =AE107 -> 40 | AG107: =AF107 -> 40 | AH107: =AG107 -> 40 | AI107: =AH107 -> 40 | AJ107: =AI107 -> 40 | AK107: =AJ107 -> 40 | AL107: =AK107 -> 40 | AM107: =AL107 -> 40 | ... AO107: =AN107 -> 40
A108: default | B108: HVDC_submarine | C108: lifetime | D108: years | E108: 40 | F108: 40 | G108: 40 | H108: 40 | I108: 40 | J108: 40 | K108: 40 | L108: 40 | M108: 40 | N108: 40 | O108: 40 | P108: 40 | Q108: 40 | R108: 40 | S108: 40 | T108: 40 | U108: 40 | V108: 40 | W108: 40 | X108: 40 | Y108: 40 | Z108: 40 | AA108: 40 | AB108: 40 | AC108: 40 | AD108: 40 | AE108: 40 | AF108: =AE108 -> 40 | AG108: =AF108 -> 40 | AH108: =AG108 -> 40 | AI108: =AH108 -> 40 | AJ108: =AI108 -> 40 | AK108: =AJ108 -> 40 | AL108: =AK108 -> 40 | AM108: =AL108 -> 40 | ... AO108: =AN108 -> 40
A109: default | B109: nuclear | C109: lifetime | D109: years | E109: 60 | F109: 60 | G109: 60 | H109: 60 | I109: 60 | J109: 60 | K109: 60 | L109: 60 | M109: 60 | N109: 60 | O109: 60 | P109: 60 | Q109: 60 | R109: 60 | S109: 60 | T109: 60 | U109: 60 | V109: 60 | W109: 60 | X109: 60 | Y109: 60 | Z109: 60 | AA109: 60 | AB109: 60 | AC109: 60 | AD109: 60 | AE109: 60 | AF109: =AE109 -> 60 | AG109: =AF109 -> 60 | AH109: =AG109 -> 60 | AI109: =AH109 -> 60 | AJ109: =AI109 -> 60 | AK109: =AJ109 -> 60 | AL109: =AK109 -> 60 | AM109: =AL109 -> 60 | ... AO109: =AN109 -> 60
A110: default | B110: ocgt_diesel | C110: lifetime | D110: years | E110: 30 | F110: 30 | G110: 30 | H110: 30 | I110: 30 | J110: 30 | K110: 30 | L110: 30 | M110: 30 | N110: 30 | O110: 30 | P110: 30 | Q110: 30 | R110: 30 | S110: 30 | T110: 30 | U110: 30 | V110: 30 | W110: 30 | X110: 30 | Y110: 30 | Z110: 30 | AA110: 30 | AB110: 30 | AC110: 30 | AD110: 30 | AE110: 30 | AF110: =AE110 -> 30 | AG110: =AF110 -> 30 | AH110: =AG110 -> 30 | AI110: =AH110 -> 30 | AJ110: =AI110 -> 30 | AK110: =AJ110 -> 30 | AL110: =AK110 -> 30 | AM110: =AL110 -> 30 | ... AO110: =AN110 -> 30
A111: default | B111: ocgt_diesel_emg | C111: lifetime | D111: years | E111: 10 | F111: =E111 -> 10 | G111: =F111 -> 10 | H111: =G111 -> 10 | I111: =H111 -> 10 | J111: =I111 -> 10 | K111: =J111 -> 10 | L111: =K111 -> 10 | M111: =L111 -> 10 | ... AO111: =AN111 -> 10
A112: default | B112: ocgt_gas | C112: lifetime | D112: years | E112: 30 | F112: 30 | G112: 30 | H112: 30 | I112: 30 | J112: 30 | K112: 30 | L112: 30 | M112: 30 | N112: 30 | O112: 30 | P112: 30 | Q112: 30 | R112: 30 | S112: 30 | T112: 30 | U112: 30 | V112: 30 | W112: 30 | X112: 30 | Y112: 30 | Z112: 30 | AA112: 30 | AB112: 30 | AC112: 30 | AD112: 30 | AE112: 30 | AF112: =AE112 -> 30 | AG112: =AF112 -> 30 | AH112: =AG112 -> 30 | AI112: =AH112 -> 30 | AJ112: =AI112 -> 30 | AK112: =AJ112 -> 30 | AL112: =AK112 -> 30 | AM112: =AL112 -> 30 | ... AO112: =AN112 -> 30
A113: default | B113: ocgt_gas_h2_40 | C113: lifetime | D113: years | E113: 30 | F113: 30 | G113: 30 | H113: 30 | I113: 30 | J113: 30 | K113: 30 | L113: 30 | M113: 30 | N113: 30 | O113: 30 | P113: 30 | Q113: 30 | R113: 30 | S113: 30 | T113: 30 | U113: 30 | V113: 30 | W113: 30 | X113: 30 | Y113: 30 | Z113: 30 | AA113: 30 | AB113: 30 | AC113: 30 | AD113: 30 | AE113: 30 | AF113: =AE113 -> 30 | AG113: =AF113 -> 30 | AH113: =AG113 -> 30 | AI113: =AH113 -> 30 | AJ113: =AI113 -> 30 | AK113: =AJ113 -> 30 | AL113: =AK113 -> 30 | AM113: =AL113 -> 30 | ... AO113: =AN113 -> 30
A114: default | B114: ocgt_gas_h2_45 | C114: lifetime | D114: years | E114: 30 | F114: 30 | G114: 30 | H114: 30 | I114: 30 | J114: 30 | K114: 30 | L114: 30 | M114: 30 | N114: 30 | O114: 30 | P114: 30 | Q114: 30 | R114: 30 | S114: 30 | T114: 30 | U114: 30 | V114: 30 | W114: 30 | X114: 30 | Y114: 30 | Z114: 30 | AA114: 30 | AB114: 30 | AC114: 30 | AD114: 30 | AE114: 30 | AF114: =AE114 -> 30 | AG114: =AF114 -> 30 | AH114: =AG114 -> 30 | AI114: =AH114 -> 30 | AJ114: =AI114 -> 30 | AK114: =AJ114 -> 30 | AL114: =AK114 -> 30 | AM114: =AL114 -> 30 | ... AO114: =AN114 -> 30
A115: default | B115: ocgt_gas_h2_50 | C115: lifetime | D115: years | E115: 30 | F115: 30 | G115: 30 | H115: 30 | I115: 30 | J115: 30 | K115: 30 | L115: 30 | M115: 30 | N115: 30 | O115: 30 | P115: 30 | Q115: 30 | R115: 30 | S115: 30 | T115: 30 | U115: 30 | V115: 30 | W115: 30 | X115: 30 | Y115: 30 | Z115: 30 | AA115: 30 | AB115: 30 | AC115: 30 | AD115: 30 | AE115: 30 | AF115: =AE115 -> 30 | AG115: =AF115 -> 30 | AH115: =AG115 -> 30 | AI115: =AH115 -> 30 | AJ115: =AI115 -> 30 | AK115: =AJ115 -> 30 | AL115: =AK115 -> 30 | AM115: =AL115 -> 30 | ... AO115: =AN115 -> 30
A116: default | B116: ocgt_gas_h2_55 | C116: lifetime | D116: years | E116: 30 | F116: 30 | G116: 30 | H116: 30 | I116: 30 | J116: 30 | K116: 30 | L116: 30 | M116: 30 | N116: 30 | O116: 30 | P116: 30 | Q116: 30 | R116: 30 | S116: 30 | T116: 30 | U116: 30 | V116: 30 | W116: 30 | X116: 30 | Y116: 30 | Z116: 30 | AA116: 30 | AB116: 30 | AC116: 30 | AD116: 30 | AE116: 30 | AF116: =AE116 -> 30 | AG116: =AF116 -> 30 | AH116: =AG116 -> 30 | AI116: =AH116 -> 30 | AJ116: =AI116 -> 30 | AK116: =AJ116 -> 30 | AL116: =AK116 -> 30 | AM116: =AL116 -> 30 | ... AO116: =AN116 -> 30
A117: default | B117: ocgt_gas_h2_60 | C117: lifetime | D117: years | E117: 30 | F117: 30 | G117: 30 | H117: 30 | I117: 30 | J117: 30 | K117: 30 | L117: 30 | M117: 30 | N117: 30 | O117: 30 | P117: 30 | Q117: 30 | R117: 30 | S117: 30 | T117: 30 | U117: 30 | V117: 30 | W117: 30 | X117: 30 | Y117: 30 | Z117: 30 | AA117: 30 | AB117: 30 | AC117: 30 | AD117: 30 | AE117: 30 | AF117: =AE117 -> 30 | AG117: =AF117 -> 30 | AH117: =AG117 -> 30 | AI117: =AH117 -> 30 | AJ117: =AI117 -> 30 | AK117: =AJ117 -> 30 | AL117: =AK117 -> 30 | AM117: =AL117 -> 30 | ... AO117: =AN117 -> 30
A118: default | B118: ocgt_blend | C118: lifetime | D118: years | E118: 30 | F118: 30 | G118: 30 | H118: 30 | I118: 30 | J118: 30 | K118: 30 | L118: 30 | M118: 30 | N118: 30 | O118: 30 | P118: 30 | Q118: 30 | R118: 30 | S118: 30 | T118: 30 | U118: 30 | V118: 30 | W118: 30 | X118: 30 | Y118: 30 | Z118: 30 | AA118: 30 | AB118: 30 | AC118: 30 | AD118: 30 | AE118: 30 | AF118: =AE118 -> 30 | AG118: =AF118 -> 30 | AH118: =AG118 -> 30 | AI118: =AH118 -> 30 | AJ118: =AI118 -> 30 | AK118: =AJ118 -> 30 | AL118: =AK118 -> 30 | AM118: =AL118 -> 30 | ... AO118: =AN118 -> 30
A119: default | B119: wind | C119: lifetime | D119: years | E119: 25 | F119: 25 | G119: 25 | H119: 25 | I119: 25 | J119: 25 | K119: 25 | L119: 25 | M119: 25 | N119: 25 | O119: 25 | P119: 25 | Q119: 25 | R119: 25 | S119: 25 | T119: 25 | U119: 25 | V119: 25 | W119: 25 | X119: 25 | Y119: 25 | Z119: 25 | AA119: 25 | AB119: 25 | AC119: 25 | AD119: 25 | AE119: 25 | AF119: =AE119 -> 25 | AG119: =AF119 -> 25 | AH119: =AG119 -> 25 | AI119: =AH119 -> 25 | AJ119: =AI119 -> 25 | AK119: =AJ119 -> 25 | AL119: =AK119 -> 25 | AM119: =AL119 -> 25 | ... AO119: =AN119 -> 25
A120: default | B120: wind_low | C120: lifetime | D120: years | E120: 25 | F120: 25 | G120: 25 | H120: 25 | I120: 25 | J120: 25 | K120: 25 | L120: 25 | M120: 25 | N120: 25 | O120: 25 | P120: 25 | Q120: 25 | R120: 25 | S120: 25 | T120: 25 | U120: 25 | V120: 25 | W120: 25 | X120: 25 | Y120: 25 | Z120: 25 | AA120: 25 | AB120: 25 | AC120: 25 | AD120: 25 | AE120: 25 | AF120: =AE120 -> 25 | AG120: =AF120 -> 25 | AH120: =AG120 -> 25 | AI120: =AH120 -> 25 | AJ120: =AI120 -> 25 | AK120: =AJ120 -> 25 | AL120: =AK120 -> 25 | AM120: =AL120 -> 25 | ... AO120: =AN120 -> 25
A121: default | B121: phs | C121: lifetime | D121: years | E121: 50 | F121: 50 | G121: 50 | H121: 50 | I121: 50 | J121: 50 | K121: 50 | L121: 50 | M121: 50 | N121: 50 | O121: 50 | P121: 50 | Q121: 50 | R121: 50 | S121: 50 | T121: 50 | U121: 50 | V121: 50 | W121: 50 | X121: 50 | Y121: 50 | Z121: 50 | AA121: 50 | AB121: 50 | AC121: 50 | AD121: 50 | AE121: 50 | AF121: =AE121 -> 50 | AG121: =AF121 -> 50 | AH121: =AG121 -> 50 | AI121: =AH121 -> 50 | AJ121: =AI121 -> 50 | AK121: =AJ121 -> 50 | AL121: =AK121 -> 50 | AM121: =AL121 -> 50 | ... AO121: =AN121 -> 50
A122: default | B122: solar_pv | C122: lifetime | D122: years | E122: 25 | F122: 25 | G122: 25 | H122: 25 | I122: 25 | J122: 25 | K122: 25 | L122: 25 | M122: 25 | N122: 25 | O122: 25 | P122: 25 | Q122: 25 | R122: 25 | S122: 25 | T122: 25 | U122: 25 | V122: 25 | W122: 25 | X122: 25 | Y122: 25 | Z122: 25 | AA122: 25 | AB122: 25 | AC122: 25 | AD122: 25 | AE122: 25 | AF122: =AE122 -> 25 | AG122: =AF122 -> 25 | AH122: =AG122 -> 25 | AI122: =AH122 -> 25 | AJ122: =AI122 -> 25 | AK122: =AJ122 -> 25 | AL122: =AK122 -> 25 | AM122: =AL122 -> 25 | ... AO122: =AN122 -> 25
A123: default | B123: solar_pv_rooftop | C123: lifetime | D123: years | E123: 25 | F123: 25 | G123: 25 | H123: 25 | I123: 25 | J123: 25 | K123: 25 | L123: 25 | M123: 25 | N123: 25 | O123: 25 | P123: 25 | Q123: 25 | R123: 25 | S123: 25 | T123: 25 | U123: 25 | V123: 25 | W123: 25 | X123: 25 | Y123: 25 | Z123: 25 | AA123: 25 | AB123: 25 | AC123: 25 | AD123: 25 | AE123: 25 | AF123: =AE123 -> 25 | AG123: =AF123 -> 25 | AH123: =AG123 -> 25 | AI123: =AH123 -> 25 | AJ123: =AI123 -> 25 | AK123: =AJ123 -> 25 | AL123: =AK123 -> 25 | AM123: =AL123 -> 25 | ... AO123: =AN123 -> 25
... A127: default | B127: coal | C127: ramp_limit_start_up | D127: %p_nom/h | E127: 0.25 | F127: 0.25 | G127: 0.25 | H127: 0.25 | I127: 0.25 | J127: 0.25 | K127: 0.25 | L127: 0.25 | M127: 0.25 | N127: 0.25 | O127: 0.25 | P127: 0.25 | Q127: 0.25 | R127: 0.25 | S127: 0.25 | T127: 0.25 | U127: 0.25 | V127: 0.25 | W127: 0.25 | X127: 0.25 | Y127: 0.25 | Z127: 0.25 | AA127: 0.25 | AB127: 0.25 | AC127: 0.25 | AD127: 0.25 | AE127: 0.25 | AF127: =AE127 -> 0.25 | AG127: =AF127 -> 0.25 | AH127: =AG127 -> 0.25 | AI127: =AH127 -> 0.25 | AJ127: =AI127 -> 0.25 | AK127: =AJ127 -> 0.25 | AL127: =AK127 -> 0.25 | AM127: =AL127 -> 0.25 | ... AO127: =AN127 -> 0.25
...

Sheet max_total_installed
A1: scenario | B1: supply_region | C1: location | D1: component | E1: carrier | F1: category | G1: 2020 | H1: 2021 | I1: 2022 | J1: 2023 | K1: 2024 | L1: 2025 | M1: 2026 | N1: 2027 | O1: 2028 | P1: 2029 | Q1: 2030 | R1: 2031 | S1: 2032 | T1: 2033 | U1: 2034 | V1: 2035 | W1: 2036 | X1: 2037 | Y1: 2038 | Z1: 2039 | AA1: 2040 | AB1: 2041 | AC1: 2042 | AD1: 2043 | AE1: 2044 | AF1: 2045 | AG1: 2046 | AH1: 2047 | AI1: 2048 | AJ1: 2049 | AK1: 2050 | AL1: =AK1+1 -> 2051 | AM1: =AL1+1 -> 2052 | AN1: =AM1+1 -> 2053 | AO1: =AN1+1 -> 2054 | AP1: =AO1+1 -> 2055 | AQ1: =AP1+1 -> 2056 | AR1: =AQ1+1 -> 2057 | AS1: =AR1+1 -> 2058 | ... AU1: =AT1+1 -> 2060
A2: LEAST_CNST | B2: 1 | C2: RSA | D2: Generator | E2: solar_pv | F2: renewables | L2: unc | M2: unc | N2: unc | O2: unc | P2: unc | Q2: unc | R2: unc | S2: unc | T2: unc | U2: unc | V2: unc | W2: unc | X2: unc | Y2: unc | Z2: unc | AA2: unc | AB2: unc | AC2: unc | AD2: unc | AE2: unc | AF2: unc | AG2: unc | AH2: unc | AI2: unc | AJ2: unc | AK2: unc | AL2: =AK2 -> unc | AM2: =AL2 -> unc | AN2: =AM2 -> unc | AO2: =AN2 -> unc | AP2: =AO2 -> unc | AQ2: =AP2 -> unc | AR2: =AQ2 -> unc | AS2: =AR2 -> unc | ... AU2: =AT2 -> unc
A3: =A2 -> LEAST_CNST | B3: 1 | C3: RSA | D3: Generator | E3: solar_pv_low | F3: renewables | L3: unc | M3: unc | N3: unc | O3: unc | P3: unc | Q3: unc | R3: unc | S3: =R3 -> unc | T3: =S3 -> unc | U3: =T3 -> unc | V3: =U3 -> unc | W3: =V3 -> unc | X3: =W3 -> unc | Y3: =X3 -> unc | Z3: =Y3 -> unc | ... AU3: =AT3 -> unc
A4: =A3 -> LEAST_CNST | B4: 1 | C4: RSA | D4: Generator | E4: solar_pv_rooftop | F4: renewables | G4: 0 | H4: 0 | I4: 0 | J4: 0 | K4: 0 | L4: =min_total_installed!G2 -> 4624 | M4: =min_total_installed!H2 -> 5299 | N4: =min_total_installed!I2 -> 5974 | O4: =min_total_installed!J2 -> 6649 | P4: =min_total_installed!K2 -> 7324 | Q4: =min_total_installed!L2 -> 7999 | R4: =min_total_installed!M2 -> 8674 | S4: =min_total_installed!N2 -> 9349 | ... AU4: =min_total_installed!AP2 -> 11374
A5: =A4 -> LEAST_CNST | B5: 1 | C5: RSA | D5: Generator | E5: solar_csp | F5: renewables | L5: unc | M5: unc | N5: unc | O5: unc | P5: unc | Q5: unc | R5: unc | S5: =R5 -> unc | T5: =S5 -> unc | U5: =T5 -> unc | V5: =U5 -> unc | W5: =V5 -> unc | X5: =W5 -> unc | Y5: =X5 -> unc | Z5: =Y5 -> unc | ... AU5: =AT5 -> unc
A6: =A5 -> LEAST_CNST | B6: 1 | C6: RSA | D6: Generator | E6: wind | F6: renewables | L6: unc | M6: unc | N6: unc | O6: unc | P6: unc | Q6: 11000 | R6: unc | S6: =R6 -> unc | T6: =S6 -> unc | U6: =T6 -> unc | V6: =U6 -> unc | W6: =V6 -> unc | X6: =W6 -> unc | Y6: =X6 -> unc | Z6: =Y6 -> unc | ... AU6: =AT6 -> unc
A7: =A6 -> LEAST_CNST | B7: 1 | C7: RSA | D7: Generator | E7: wind_low | F7: renewables | L7: unc | M7: unc | N7: unc | O7: unc | P7: unc | Q7: unc | R7: unc | S7: =R7 -> unc | T7: =S7 -> unc | U7: =T7 -> unc | V7: =U7 -> unc | W7: =V7 -> unc | X7: =W7 -> unc | Y7: =X7 -> unc | Z7: =Y7 -> unc | ... AU7: =AT7 -> unc
A8: =A7 -> LEAST_CNST | B8: 1 | C8: RSA | D8: Generator | E8: ccgt_steam | F8: conventional | L8: unc | M8: unc | N8: unc | O8: unc | P8: unc | Q8: unc | R8: unc | S8: =R8 -> unc | T8: =S8 -> unc | U8: =T8 -> unc | V8: =U8 -> unc | W8: =V8 -> unc | X8: =W8 -> unc | Y8: =X8 -> unc | Z8: =Y8 -> unc | ... AU8: =AT8 -> unc
A9: =A8 -> LEAST_CNST | B9: 1 | C9: RSA | D9: Generator | E9: ocgt_gas | F9: conventional | L9: unc | M9: unc | N9: unc | O9: unc | P9: unc | Q9: unc | R9: unc | S9: =R9 -> unc | T9: =S9 -> unc | U9: =T9 -> unc | V9: =U9 -> unc | W9: =V9 -> unc | X9: =W9 -> unc | Y9: =X9 -> unc | Z9: =Y9 -> unc | ... AU9: =AT9 -> unc
A10: =A9 -> LEAST_CNST | B10: 1 | C10: RSA | D10: Generator | E10: ocgt_gas_h2_40 | F10: conventional | L10: unc | M10: unc | N10: unc | O10: unc | P10: unc | Q10: unc | R10: unc | S10: =R10 -> unc | T10: =S10 -> unc | U10: =T10 -> unc | V10: =U10 -> unc | W10: =V10 -> unc | X10: =W10 -> unc | Y10: =X10 -> unc | Z10: =Y10 -> unc | ... AU10: =AT10 -> unc
A11: =A10 -> LEAST_CNST | B11: 1 | C11: RSA | D11: Generator | E11: ocgt_gas_h2_45 | F11: conventional | L11: unc | M11: unc | N11: unc | O11: unc | P11: unc | Q11: unc | R11: unc | S11: =R11 -> unc | T11: =S11 -> unc | U11: =T11 -> unc | V11: =U11 -> unc | W11: =V11 -> unc | X11: =W11 -> unc | Y11: =X11 -> unc | Z11: =Y11 -> unc | ... AU11: =AT11 -> unc
A12: =A11 -> LEAST_CNST | B12: 1 | C12: RSA | D12: Generator | E12: ocgt_gas_h2_50 | F12: conventional | L12: unc | M12: unc | N12: unc | O12: unc | P12: unc | Q12: unc | R12: unc | S12: =R12 -> unc | T12: =S12 -> unc | U12: =T12 -> unc | V12: =U12 -> unc | W12: =V12 -> unc | X12: =W12 -> unc | Y12: =X12 -> unc | Z12: =Y12 -> unc | ... AU12: =AT12 -> unc
A13: =A12 -> LEAST_CNST | B13: 1 | C13: RSA | D13: Generator | E13: ocgt_gas_h2_55 | F13: conventional | L13: unc | M13: unc | N13: unc | O13: unc | P13: unc | Q13: unc | R13: unc | S13: =R13 -> unc | T13: =S13 -> unc | U13: =T13 -> unc | V13: =U13 -> unc | W13: =V13 -> unc | X13: =W13 -> unc | Y13: =X13 -> unc | Z13: =Y13 -> unc | ... AU13: =AT13 -> unc
A14: =A13 -> LEAST_CNST | B14: 1 | C14: RSA | D14: Generator | E14: ocgt_gas_h2_60 | F14: conventional | L14: unc | M14: unc | N14: unc | O14: unc | P14: unc | Q14: unc | R14: unc | S14: =R14 -> unc | T14: =S14 -> unc | U14: =T14 -> unc | V14: =U14 -> unc | W14: =V14 -> unc | X14: =W14 -> unc | Y14: =X14 -> unc | Z14: =Y14 -> unc | ... AU14: =AT14 -> unc
A15: =A12 -> LEAST_CNST | B15: 1 | C15: RSA | D15: Generator | E15: ocgt_diesel | F15: conventional | L15: unc | M15: unc | N15: unc | O15: unc | P15: unc | Q15: unc | R15: unc | S15: =R15 -> unc | T15: =S15 -> unc | U15: =T15 -> unc | V15: =U15 -> unc | W15: =V15 -> unc | X15: =W15 -> unc | Y15: =X15 -> unc | Z15: =Y15 -> unc | ... AU15: =AT15 -> unc
A16: =A13 -> LEAST_CNST | B16: 1 | C16: RSA | D16: Generator | E16: ocgt_blend | F16: conventional | L16: unc | M16: unc | N16: unc | O16: unc | P16: unc | Q16: unc | R16: unc | S16: =R16 -> unc | T16: =S16 -> unc | U16: =T16 -> unc | V16: =U16 -> unc | W16: =V16 -> unc | X16: =W16 -> unc | Y16: =X16 -> unc | Z16: =Y16 -> unc | ... AU16: =AT16 -> unc
A17: =A15 -> LEAST_CNST | B17: 1 | C17: RSA | D17: Generator | E17: coal | F17: conventional | L17: 0 | M17: 0 | N17: 0 | O17: 0 | P17: 0 | Q17: 0 | R17: 0 | S17: 0 | T17: 0 | U17: 0 | V17: unc | W17: unc | X17: unc | Y17: unc | Z17: unc | AA17: unc | AB17: unc | AC17: unc | AD17: unc | AE17: unc | AF17: unc | AG17: unc | AH17: unc | AI17: unc | AJ17: unc | AK17: unc | AL17: =AK17 -> unc | AM17: =AL17 -> unc | AN17: =AM17 -> unc | AO17: =AN17 -> unc | AP17: =AO17 -> unc | AQ17: =AP17 -> unc | AR17: =AQ17 -> unc | AS17: =AR17 -> unc | ... AU17: =AT17 -> unc
A18: =A17 -> LEAST_CNST | B18: 1 | C18: RSA | D18: Generator | E18: nuclear | F18: conventional | L18: 0 | M18: 0 | N18: 0 | O18: 0 | P18: 0 | Q18: 0 | R18: 0 | S18: 0 | T18: 0 | U18: 0 | V18: unc | W18: unc | X18: unc | Y18: unc | Z18: unc | AA18: unc | AB18: unc | AC18: unc | AD18: unc | AE18: unc | AF18: unc | AG18: unc | AH18: unc | AI18: unc | AJ18: unc | AK18: unc | AL18: =AK18 -> unc | AM18: =AL18 -> unc | AN18: =AM18 -> unc | AO18: =AN18 -> unc | AP18: =AO18 -> unc | AQ18: =AP18 -> unc | AR18: =AQ18 -> unc | AS18: =AR18 -> unc | ... AU18: =AT18 -> unc
A19: =A18 -> LEAST_CNST | B19: 1 | C19: RSA | D19: StorageUnit | E19: phs | F19: storage | L19: 0 | M19: 0 | N19: 0 | O19: 0 | P19: 0 | Q19: 0 | R19: 0 | S19: 0 | T19: 0 | U19: 0 | V19: 1500 | W19: =V19 -> 1500 | X19: =W19 -> 1500 | Y19: =X19 -> 1500 | Z19: =Y19 -> 1500 | AA19: =Z19 -> 1500 | AB19: =AA19 -> 1500 | AC19: =AB19 -> 1500 | AD19: =AC19 -> 1500 | ... AU19: =AT19 -> 1500
A20: =A19 -> LEAST_CNST | B20: 1 | C20: RSA | D20: StorageUnit | E20: battery_1h | F20: storage | L20: unc | M20: unc | N20: unc | O20: unc | P20: unc | Q20: unc | R20: unc | S20: unc | T20: unc | U20: unc | V20: unc | W20: unc | X20: unc | Y20: unc | Z20: unc | AA20: unc | AB20: unc | AC20: unc | AD20: unc | AE20: unc | AF20: unc | AG20: unc | AH20: unc | AI20: unc | AJ20: unc | AK20: unc | AL20: =AK20 -> unc | AM20: =AL20 -> unc | AN20: =AM20 -> unc | AO20: =AN20 -> unc | AP20: =AO20 -> unc | AQ20: =AP20 -> unc | AR20: =AQ20 -> unc | AS20: =AR20 -> unc | ... AU20: =AT20 -> unc
A21: =A20 -> LEAST_CNST | B21: 1 | C21: RSA | D21: StorageUnit | E21: battery_4h | F21: storage | L21: unc | M21: unc | N21: unc | O21: unc | P21: unc | Q21: unc | R21: unc | S21: unc | T21: unc | U21: unc | V21: unc | W21: unc | X21: unc | Y21: unc | Z21: unc | AA21: unc | AB21: unc | AC21: unc | AD21: unc | AE21: unc | AF21: unc | AG21: unc | AH21: unc | AI21: unc | AJ21: unc | AK21: unc | AL21: =AK21 -> unc | AM21: =AL21 -> unc | AN21: =AM21 -> unc | AO21: =AN21 -> unc | AP21: =AO21 -> unc | AQ21: =AP21 -> unc | AR21: =AQ21 -> unc | AS21: =AR21 -> unc | ... AU21: =AT21 -> unc
A22: =A21 -> LEAST_CNST | B22: 1 | C22: RSA | D22: StorageUnit | E22: battery_8h | F22: storage | L22: unc | M22: unc | N22: unc | O22: unc | P22: unc | Q22: unc | R22: unc | S22: unc | T22: unc | U22: unc | V22: unc | W22: unc | X22: unc | Y22: unc | Z22: unc | AA22: unc | AB22: unc | AC22: unc | AD22: unc | AE22: unc | AF22: unc | AG22: unc | AH22: unc | AI22: unc | AJ22: unc | AK22: unc | AL22: =AK22 -> unc | AM22: =AL22 -> unc | AN22: =AM22 -> unc | AO22: =AN22 -> unc | AP22: =AO22 -> unc | AQ22: =AP22 -> unc | AR22: =AQ22 -> unc | AS22: =AR22 -> unc | ... AU22: =AT22 -> unc
A23: MOD_CNST | B23: 1 | C23: RSA | D23: Generator | E23: solar_pv | F23: renewables | L23: unc | M23: unc | N23: unc | O23: unc | P23: unc | Q23: unc | R23: unc | S23: =R23 -> unc | T23: =S23 -> unc | U23: =T23 -> unc | V23: =U23 -> unc | W23: =V23 -> unc | X23: =W23 -> unc | Y23: =X23 -> unc | Z23: =Y23 -> unc | ... AU23: =AT23 -> unc
A24: =A23 -> MOD_CNST | B24: 1 | C24: RSA | D24: Generator | E24: solar_pv_low | F24: renewables | L24: unc | M24: unc | N24: unc | O24: unc | P24: unc | Q24: unc | R24: unc | S24: =R24 -> unc | T24: =S24 -> unc | U24: =T24 -> unc | V24: =U24 -> unc | W24: =V24 -> unc | X24: =W24 -> unc | Y24: =X24 -> unc | Z24: =Y24 -> unc | ... AU24: =AT24 -> unc
A25: =A24 -> MOD_CNST | B25: 1 | C25: RSA | D25: Generator | E25: solar_pv_rooftop | F25: renewables | L25: =min_total_installed!G2 -> 4624 | M25: =min_total_installed!H2 -> 5299 | N25: =min_total_installed!I2 -> 5974 | O25: =min_total_installed!J2 -> 6649 | P25: =min_total_installed!K2 -> 7324 | Q25: =min_total_installed!L2 -> 7999 | R25: =min_total_installed!M2 -> 8674 | S25: =min_total_installed!N2 -> 9349 | ... AU25: =min_total_installed!AP2 -> 11374
A26: =A25 -> MOD_CNST | B26: 1 | C26: RSA | D26: Generator | E26: solar_csp | F26: renewables | L26: unc | M26: unc | N26: unc | O26: unc | P26: unc | Q26: unc | R26: unc | S26: =R26 -> unc | T26: =S26 -> unc | U26: =T26 -> unc | V26: =U26 -> unc | W26: =V26 -> unc | X26: =W26 -> unc | Y26: =X26 -> unc | Z26: =Y26 -> unc | ... AU26: =AT26 -> unc
A27: =A26 -> MOD_CNST | B27: 1 | C27: RSA | D27: Generator | E27: wind | F27: renewables | L27: unc | M27: unc | N27: unc | O27: unc | P27: unc | Q27: 9000 | R27: unc | S27: =R27 -> unc | T27: =S27 -> unc | U27: =T27 -> unc | V27: =U27 -> unc | W27: =V27 -> unc | X27: =W27 -> unc | Y27: =X27 -> unc | Z27: =Y27 -> unc | ... AU27: =AT27 -> unc
A28: =A27 -> MOD_CNST | B28: 1 | C28: RSA | D28: Generator | E28: wind_low | F28: renewables | L28: unc | M28: unc | N28: unc | O28: unc | P28: unc | Q28: unc | R28: unc | S28: =R28 -> unc | T28: =S28 -> unc | U28: =T28 -> unc | V28: =U28 -> unc | W28: =V28 -> unc | X28: =W28 -> unc | Y28: =X28 -> unc | Z28: =Y28 -> unc | ... AU28: =AT28 -> unc
A29: =A28 -> MOD_CNST | B29: 1 | C29: RSA | D29: Generator | E29: ccgt_steam | F29: conventional | L29: unc | M29: unc | N29: unc | O29: unc | P29: unc | Q29: unc | R29: unc | S29: =R29 -> unc | T29: =S29 -> unc | U29: =T29 -> unc | V29: =U29 -> unc | W29: =V29 -> unc | X29: =W29 -> unc | Y29: =X29 -> unc | Z29: =Y29 -> unc | ... AU29: =AT29 -> unc
A30: =A29 -> MOD_CNST | B30: 1 | C30: RSA | D30: Generator | E30: ocgt_gas | F30: conventional | L30: unc | M30: unc | N30: unc | O30: unc | P30: unc | Q30: unc | R30: unc | S30: =R30 -> unc | T30: =S30 -> unc | U30: =T30 -> unc | V30: =U30 -> unc | W30: =V30 -> unc | X30: =W30 -> unc | Y30: =X30 -> unc | Z30: =Y30 -> unc | ... AU30: =AT30 -> unc
A31: =A30 -> MOD_CNST | B31: 1 | C31: RSA | D31: Generator | E31: ocgt_gas_h2_40 | F31: conventional | L31: unc | M31: unc | N31: unc | O31: unc | P31: unc | Q31: unc | R31: unc | S31: =R31 -> unc | T31: =S31 -> unc | U31: =T31 -> unc | V31: =U31 -> unc | W31: =V31 -> unc | X31: =W31 -> unc | Y31: =X31 -> unc | Z31: =Y31 -> unc | ... AU31: =AT31 -> unc
A32: =A31 -> MOD_CNST | B32: 1 | C32: RSA | D32: Generator | E32: ocgt_gas_h2_45 | F32: conventional | L32: unc | M32: unc | N32: unc | O32: unc | P32: unc | Q32: unc | R32: unc | S32: =R32 -> unc | T32: =S32 -> unc | U32: =T32 -> unc | V32: =U32 -> unc | W32: =V32 -> unc | X32: =W32 -> unc | Y32: =X32 -> unc | Z32: =Y32 -> unc | ... AU32: =AT32 -> unc
A33: =A32 -> MOD_CNST | B33: 1 | C33: RSA | D33: Generator | E33: ocgt_gas_h2_50 | F33: conventional | L33: unc | M33: unc | N33: unc | O33: unc | P33: unc | Q33: unc | R33: unc | S33: =R33 -> unc | T33: =S33 -> unc | U33: =T33 -> unc | V33: =U33 -> unc | W33: =V33 -> unc | X33: =W33 -> unc | Y33: =X33 -> unc | Z33: =Y33 -> unc | ... AU33: =AT33 -> unc
A34: =A33 -> MOD_CNST | B34: 1 | C34: RSA | D34: Generator | E34: ocgt_gas_h2_55 | F34: conventional | L34: unc | M34: unc | N34: unc | O34: unc | P34: unc | Q34: unc | R34: unc | S34: =R34 -> unc | T34: =S34 -> unc | U34: =T34 -> unc | V34: =U34 -> unc | W34: =V34 -> unc | X34: =W34 -> unc | Y34: =X34 -> unc | Z34: =Y34 -> unc | ... AU34: =AT34 -> unc
A35: =A34 -> MOD_CNST | B35: 1 | C35: RSA | D35: Generator | E35: ocgt_gas_h2_60 | F35: conventional | L35: unc | M35: unc | N35: unc | O35: unc | P35: unc | Q35: unc | R35: unc | S35: =R35 -> unc | T35: =S35 -> unc | U35: =T35 -> unc | V35: =U35 -> unc | W35: =V35 -> unc | X35: =W35 -> unc | Y35: =X35 -> unc | Z35: =Y35 -> unc | ... AU35: =AT35 -> unc
A36: =A33 -> MOD_CNST | B36: 1 | C36: RSA | D36: Generator | E36: ocgt_diesel | F36: conventional | L36: unc | M36: unc | N36: unc | O36: unc | P36: unc | Q36: unc | R36: unc | S36: =R36 -> unc | T36: =S36 -> unc | U36: =T36 -> unc | V36: =U36 -> unc | W36: =V36 -> unc | X36: =W36 -> unc | Y36: =X36 -> unc | Z36: =Y36 -> unc | ... AU36: =AT36 -> unc
A37: =A34 -> MOD_CNST | B37: 1 | C37: RSA | D37: Generator | E37: ocgt_blend | F37: conventional | L37: 0 | M37: 0 | N37: 0 | O37: 0 | P37: 0 | Q37: 0 | R37: 0 | S37: 0 | T37: 0 | U37: 0 | V37: 0 | W37: =V37 -> 0 | X37: =W37 -> 0 | Y37: =X37 -> 0 | Z37: =Y37 -> 0 | AA37: =Z37 -> 0 | AB37: =AA37 -> 0 | AC37: =AB37 -> 0 | AD37: =AC37 -> 0 | ... AU37: =AT37 -> 0
A38: =A36 -> MOD_CNST | B38: 1 | C38: RSA | D38: Generator | E38: coal | F38: conventional | L38: 0 | M38: 0 | N38: 0 | O38: 0 | P38: 0 | Q38: 0 | R38: 0 | S38: 0 | T38: 0 | U38: 0 | V38: unc | W38: unc | X38: unc | Y38: unc | Z38: unc | AA38: unc | AB38: =AA38 -> unc | AC38: =AB38 -> unc | AD38: =AC38 -> unc | AE38: =AD38 -> unc | AF38: =AE38 -> unc | AG38: =AF38 -> unc | AH38: =AG38 -> unc | AI38: =AH38 -> unc | ... AU38: =AT38 -> unc
A39: =A38 -> MOD_CNST | B39: 1 | C39: RSA | D39: Generator | E39: nuclear | F39: conventional | L39: 0 | M39: 0 | N39: 0 | O39: 0 | P39: 0 | Q39: 0 | R39: 0 | S39: 0 | T39: 0 | U39: 0 | V39: unc | W39: unc | X39: unc | Y39: unc | Z39: unc | AA39: unc | AB39: =AA39 -> unc | AC39: =AB39 -> unc | AD39: =AC39 -> unc | AE39: =AD39 -> unc | AF39: =AE39 -> unc | AG39: =AF39 -> unc | AH39: =AG39 -> unc | AI39: =AH39 -> unc | ... AU39: =AT39 -> unc
A40: =A39 -> MOD_CNST | B40: 1 | C40: RSA | D40: StorageUnit | E40: phs | F40: storage | L40: 0 | M40: 0 | N40: 0 | O40: 0 | P40: 0 | Q40: 0 | R40: 0 | S40: 0 | T40: 0 | U40: 0 | V40: 1500 | W40: =V40 -> 1500 | X40: =W40 -> 1500 | Y40: =X40 -> 1500 | Z40: =Y40 -> 1500 | AA40: =Z40 -> 1500 | AB40: =AA40 -> 1500 | AC40: =AB40 -> 1500 | AD40: =AC40 -> 1500 | ... AU40: =AT40 -> 1500
A41: =A40 -> MOD_CNST | B41: 1 | C41: RSA | D41: StorageUnit | E41: battery_1h | F41: storage | L41: unc | M41: unc | N41: unc | O41: unc | P41: unc | Q41: unc | R41: unc | S41: unc | T41: unc | U41: unc | V41: unc | W41: unc | X41: unc | Y41: unc | Z41: unc | AA41: unc | AB41: =AA41 -> unc | AC41: =AB41 -> unc | AD41: =AC41 -> unc | AE41: =AD41 -> unc | AF41: =AE41 -> unc | AG41: =AF41 -> unc | AH41: =AG41 -> unc | AI41: =AH41 -> unc | ... AU41: =AT41 -> unc
A42: =A41 -> MOD_CNST | B42: 1 | C42: RSA | D42: StorageUnit | E42: battery_4h | F42: storage | L42: unc | M42: unc | N42: unc | O42: unc | P42: unc | Q42: unc | R42: unc | S42: unc | T42: unc | U42: unc | V42: unc | W42: unc | X42: unc | Y42: unc | Z42: unc | AA42: unc | AB42: =AA42 -> unc | AC42: =AB42 -> unc | AD42: =AC42 -> unc | AE42: =AD42 -> unc | AF42: =AE42 -> unc | AG42: =AF42 -> unc | AH42: =AG42 -> unc | AI42: =AH42 -> unc | ... AU42: =AT42 -> unc
A43: =A42 -> MOD_CNST | B43: 1 | C43: RSA | D43: StorageUnit | E43: battery_8h | F43: storage | L43: unc | M43: unc | N43: unc | O43: unc | P43: unc | Q43: unc | R43: unc | S43: unc | T43: unc | U43: unc | V43: unc | W43: unc | X43: unc | Y43: unc | Z43: unc | AA43: unc | AB43: =AA43 -> unc | AC43: =AB43 -> unc | AD43: =AC43 -> unc | AE43: =AD43 -> unc | AF43: =AE43 -> unc | AG43: =AF43 -> unc | AH43: =AG43 -> unc | AI43: =AH43 -> unc | ... AU43: =AT43 -> unc
A44: MOST_CNST | B44: 1 | C44: RSA | D44: Generator | E44: solar_pv | F44: renewables | L44: unc | M44: unc | N44: unc | O44: unc | P44: unc | Q44: unc | R44: unc | S44: =R44 -> unc | T44: =S44 -> unc | U44: =T44 -> unc | V44: =U44 -> unc | W44: =V44 -> unc | X44: =W44 -> unc | Y44: =X44 -> unc | Z44: =Y44 -> unc | ... AU44: =AT44 -> unc
A45: =A44 -> MOST_CNST | B45: 1 | C45: RSA | D45: Generator | E45: solar_pv_low | F45: renewables | L45: unc | M45: unc | N45: unc | O45: unc | P45: unc | Q45: unc | R45: unc | S45: unc | T45: unc | U45: unc | V45: unc | W45: unc | X45: unc | Y45: unc | Z45: unc | AA45: unc | AB45: unc | AC45: unc | AD45: unc | AE45: unc | AF45: unc | AG45: unc | AH45: unc | AI45: unc | AJ45: unc | AK45: unc | AL45: =AK45 -> unc | AM45: =AL45 -> unc | AN45: =AM45 -> unc | AO45: =AN45 -> unc | AP45: =AO45 -> unc | AQ45: =AP45 -> unc | AR45: =AQ45 -> unc | AS45: =AR45 -> unc | ... AU45: =AT45 -> unc
A46: =A45 -> MOST_CNST | B46: 1 | C46: RSA | D46: Generator | E46: solar_pv_rooftop | F46: renewables | L46: =min_total_installed!G2 -> 4624 | M46: =min_total_installed!H2 -> 5299 | N46: =min_total_installed!I2 -> 5974 | O46: =min_total_installed!J2 -> 6649 | P46: =min_total_installed!K2 -> 7324 | Q46: =min_total_installed!L2 -> 7999 | R46: =min_total_installed!M2 -> 8674 | S46: =min_total_installed!N2 -> 9349 | ... AU46: =min_total_installed!AP2 -> 11374
A47: =A46 -> MOST_CNST | B47: 1 | C47: RSA | D47: Generator | E47: solar_csp | F47: renewables | L47: unc | M47: unc | N47: unc | O47: unc | P47: unc | Q47: unc | R47: unc | S47: =R47 -> unc | T47: =S47 -> unc | U47: =T47 -> unc | V47: =U47 -> unc | W47: =V47 -> unc | X47: =W47 -> unc | Y47: =X47 -> unc | Z47: =Y47 -> unc | ... AU47: =AT47 -> unc
A48: =A47 -> MOST_CNST | B48: 1 | C48: RSA | D48: Generator | E48: wind | F48: renewables | L48: unc | M48: unc | N48: unc | O48: unc | P48: unc | Q48: 7000 | R48: unc | S48: =R48 -> unc | T48: =S48 -> unc | U48: =T48 -> unc | V48: =U48 -> unc | W48: =V48 -> unc | X48: =W48 -> unc | Y48: =X48 -> unc | Z48: =Y48 -> unc | ... AU48: =AT48 -> unc
A49: =A48 -> MOST_CNST | B49: 1 | C49: RSA | D49: Generator | E49: wind_low | F49: renewables | L49: unc | M49: unc | N49: unc | O49: unc | P49: unc | Q49: unc | R49: unc | S49: =R49 -> unc | T49: =S49 -> unc | U49: =T49 -> unc | V49: =U49 -> unc | W49: =V49 -> unc | X49: =W49 -> unc | Y49: =X49 -> unc | Z49: =Y49 -> unc | ... AU49: =AT49 -> unc
A50: =A49 -> MOST_CNST | B50: 1 | C50: RSA | D50: Generator | E50: ccgt_steam | F50: conventional | L50: unc | M50: unc | N50: unc | O50: unc | P50: unc | Q50: unc | R50: unc | S50: =R50 -> unc | T50: =S50 -> unc | U50: =T50 -> unc | V50: =U50 -> unc | W50: =V50 -> unc | X50: =W50 -> unc | Y50: =X50 -> unc | Z50: =Y50 -> unc | ... AU50: =AT50 -> unc
A51: =A50 -> MOST_CNST | B51: 1 | C51: RSA | D51: Generator | E51: ocgt_gas | F51: conventional | L51: unc | M51: unc | N51: unc | O51: unc | P51: unc | Q51: unc | R51: unc | S51: =R51 -> unc | T51: =S51 -> unc | U51: =T51 -> unc | V51: =U51 -> unc | W51: =V51 -> unc | X51: =W51 -> unc | Y51: =X51 -> unc | Z51: =Y51 -> unc | ... AU51: =AT51 -> unc
A52: =A51 -> MOST_CNST | B52: 1 | C52: RSA | D52: Generator | E52: ocgt_gas_h2_40 | F52: conventional | L52: unc | M52: unc | N52: unc | O52: unc | P52: unc | Q52: unc | R52: unc | S52: =R52 -> unc | T52: =S52 -> unc | U52: =T52 -> unc | V52: =U52 -> unc | W52: =V52 -> unc | X52: =W52 -> unc | Y52: =X52 -> unc | Z52: =Y52 -> unc | ... AU52: =AT52 -> unc
A53: =A52 -> MOST_CNST | B53: 1 | C53: RSA | D53: Generator | E53: ocgt_gas_h2_45 | F53: conventional | L53: unc | M53: unc | N53: unc | O53: unc | P53: unc | Q53: unc | R53: unc | S53: =R53 -> unc | T53: =S53 -> unc | U53: =T53 -> unc | V53: =U53 -> unc | W53: =V53 -> unc | X53: =W53 -> unc | Y53: =X53 -> unc | Z53: =Y53 -> unc | ... AU53: =AT53 -> unc
A54: =A53 -> MOST_CNST | B54: 1 | C54: RSA | D54: Generator | E54: ocgt_gas_h2_50 | F54: conventional | L54: unc | M54: unc | N54: unc | O54: unc | P54: unc | Q54: unc | R54: unc | S54: =R54 -> unc | T54: =S54 -> unc | U54: =T54 -> unc | V54: =U54 -> unc | W54: =V54 -> unc | X54: =W54 -> unc | Y54: =X54 -> unc | Z54: =Y54 -> unc | ... AU54: =AT54 -> unc
A55: =A54 -> MOST_CNST | B55: 1 | C55: RSA | D55: Generator | E55: ocgt_gas_h2_55 | F55: conventional | L55: unc | M55: unc | N55: unc | O55: unc | P55: unc | Q55: unc | R55: unc | S55: =R55 -> unc | T55: =S55 -> unc | U55: =T55 -> unc | V55: =U55 -> unc | W55: =V55 -> unc | X55: =W55 -> unc | Y55: =X55 -> unc | Z55: =Y55 -> unc | ... AU55: =AT55 -> unc
A56: =A55 -> MOST_CNST | B56: 1 | C56: RSA | D56: Generator | E56: ocgt_gas_h2_60 | F56: conventional | L56: unc | M56: unc | N56: unc | O56: unc | P56: unc | Q56: unc | R56: unc | S56: =R56 -> unc | T56: =S56 -> unc | U56: =T56 -> unc | V56: =U56 -> unc | W56: =V56 -> unc | X56: =W56 -> unc | Y56: =X56 -> unc | Z56: =Y56 -> unc | ... AU56: =AT56 -> unc
A57: =A54 -> MOST_CNST | B57: 1 | C57: RSA | D57: Generator | E57: ocgt_diesel | F57: conventional | L57: unc | M57: unc | N57: unc | O57: unc | P57: unc | Q57: unc | R57: unc | S57: =R57 -> unc | T57: =S57 -> unc | U57: =T57 -> unc | V57: =U57 -> unc | W57: =V57 -> unc | X57: =W57 -> unc | Y57: =X57 -> unc | Z57: =Y57 -> unc | ... AU57: =AT57 -> unc
A58: =A55 -> MOST_CNST | B58: 1 | C58: RSA | D58: Generator | E58: ocgt_blend | F58: conventional | L58: 0 | M58: 0 | N58: 0 | O58: 0 | P58: 0 | Q58: 0 | R58: 0 | S58: 0 | T58: 0 | U58: 0 | V58: 0 | W58: =V58 -> 0 | X58: =W58 -> 0 | Y58: =X58 -> 0 | Z58: =Y58 -> 0 | AA58: =Z58 -> 0 | AB58: =AA58 -> 0 | AC58: =AB58 -> 0 | AD58: =AC58 -> 0 | ... AU58: =AT58 -> 0
A59: =A57 -> MOST_CNST | B59: 1 | C59: RSA | D59: Generator | E59: coal | F59: conventional | L59: 0 | M59: 0 | N59: 0 | O59: 0 | P59: 0 | Q59: 0 | R59: 0 | S59: 0 | T59: 0 | U59: 0 | V59: unc | W59: unc | X59: unc | Y59: unc | Z59: unc | AA59: unc | AB59: unc | AC59: unc | AD59: unc | AE59: unc | AF59: unc | AG59: =AF59 -> unc | AH59: =AG59 -> unc | AI59: =AH59 -> unc | AJ59: =AI59 -> unc | AK59: =AJ59 -> unc | AL59: =AK59 -> unc | AM59: =AL59 -> unc | AN59: =AM59 -> unc | ... AU59: =AT59 -> unc
A60: =A59 -> MOST_CNST | B60: 1 | C60: RSA | D60: Generator | E60: nuclear | F60: conventional | L60: 0 | M60: 0 | N60: 0 | O60: 0 | P60: 0 | Q60: 0 | R60: 0 | S60: 0 | T60: 0 | U60: 0 | V60: unc | W60: unc | X60: unc | Y60: unc | Z60: unc | AA60: unc | AB60: unc | AC60: unc | AD60: unc | AE60: unc | AF60: unc | AG60: =AF60 -> unc | AH60: =AG60 -> unc | AI60: =AH60 -> unc | AJ60: =AI60 -> unc | AK60: =AJ60 -> unc | AL60: =AK60 -> unc | AM60: =AL60 -> unc | AN60: =AM60 -> unc | ... AU60: =AT60 -> unc
A61: =A60 -> MOST_CNST | B61: 1 | C61: RSA | D61: StorageUnit | E61: phs | F61: storage | L61: 0 | M61: 0 | N61: 0 | O61: 0 | P61: 0 | Q61: 0 | R61: 0 | S61: 0 | T61: 0 | U61: 0 | V61: 1500 | W61: =V61 -> 1500 | X61: =W61 -> 1500 | Y61: =X61 -> 1500 | Z61: =Y61 -> 1500 | AA61: =Z61 -> 1500 | AB61: =AA61 -> 1500 | AC61: =AB61 -> 1500 | AD61: =AC61 -> 1500 | ... AU61: =AT61 -> 1500
A62: =A61 -> MOST_CNST | B62: 1 | C62: RSA | D62: StorageUnit | E62: battery_1h | F62: storage | L62: unc | M62: unc | N62: unc | O62: unc | P62: unc | Q62: unc | R62: unc | S62: unc | T62: unc | U62: unc | V62: unc | W62: unc | X62: unc | Y62: unc | Z62: unc | AA62: unc | AB62: unc | AC62: unc | AD62: unc | AE62: unc | AF62: unc | AG62: =AF62 -> unc | AH62: =AG62 -> unc | AI62: =AH62 -> unc | AJ62: =AI62 -> unc | AK62: =AJ62 -> unc | AL62: =AK62 -> unc | AM62: =AL62 -> unc | AN62: =AM62 -> unc | ... AU62: =AT62 -> unc
A63: =A62 -> MOST_CNST | B63: 1 | C63: RSA | D63: StorageUnit | E63: battery_4h | F63: storage | L63: unc | M63: unc | N63: unc | O63: unc | P63: unc | Q63: unc | R63: unc | S63: unc | T63: unc | U63: unc | V63: unc | W63: unc | X63: unc | Y63: unc | Z63: unc | AA63: unc | AB63: unc | AC63: unc | AD63: unc | AE63: unc | AF63: unc | AG63: =AF63 -> unc | AH63: =AG63 -> unc | AI63: =AH63 -> unc | AJ63: =AI63 -> unc | AK63: =AJ63 -> unc | AL63: =AK63 -> unc | AM63: =AL63 -> unc | AN63: =AM63 -> unc | ... AU63: =AT63 -> unc
A64: =A63 -> MOST_CNST | B64: 1 | C64: RSA | D64: StorageUnit | E64: battery_8h | F64: storage | L64: unc | M64: unc | N64: unc | O64: unc | P64: unc | Q64: unc | R64: unc | S64: unc | T64: unc | U64: unc | V64: unc | W64: unc | X64: unc | Y64: unc | Z64: unc | AA64: unc | AB64: unc | AC64: unc | AD64: unc | AE64: unc | AF64: unc | AG64: =AF64 -> unc | AH64: =AG64 -> unc | AI64: =AH64 -> unc | AJ64: =AI64 -> unc | AK64: =AJ64 -> unc | AL64: =AK64 -> unc | AM64: =AL64 -> unc | AN64: =AM64 -> unc | ... AU64: =AT64 -> unc
A65: LEAST_CNST_NO_COAL_NUC | B65: 1 | C65: RSA | D65: Generator | E65: solar_pv | F65: renewables | L65: unc | M65: unc | N65: unc | O65: unc | P65: unc | Q65: unc | R65: unc | S65: unc | T65: unc | U65: unc | V65: unc | W65: unc | X65: unc | Y65: unc | Z65: unc | AA65: unc | AB65: unc | AC65: unc | AD65: unc | AE65: unc | AF65: unc | AG65: unc | AH65: unc | AI65: unc | AJ65: unc | AK65: unc | AL65: =AK65 -> unc | AM65: =AL65 -> unc | AN65: =AM65 -> unc | AO65: =AN65 -> unc | AP65: =AO65 -> unc | AQ65: =AP65 -> unc | AR65: =AQ65 -> unc | AS65: =AR65 -> unc | ... AU65: =AT65 -> unc
A66: =A65 -> LEAST_CNST_NO_COAL_NUC | B66: 1 | C66: RSA | D66: Generator | E66: solar_pv_low | F66: renewables | L66: unc | M66: unc | N66: unc | O66: unc | P66: unc | Q66: unc | R66: unc | S66: =R66 -> unc | T66: =S66 -> unc | U66: =T66 -> unc | V66: =U66 -> unc | W66: =V66 -> unc | X66: =W66 -> unc | Y66: =X66 -> unc | Z66: =Y66 -> unc | ... AU66: =AT66 -> unc
A67: =A66 -> LEAST_CNST_NO_COAL_NUC | B67: 1 | C67: RSA | D67: Generator | E67: solar_pv_rooftop | F67: renewables | G67: 0 | H67: 0 | I67: 0 | J67: 0 | K67: 0 | L67: 4624 | M67: 5299 | N67: 5974 | O67: 6649 | P67: 7324 | Q67: 7999 | R67: 8674 | S67: 9349 | T67: 10024 | U67: 10699 | V67: 11374 | W67: 11374 | X67: 11374 | Y67: 11374 | Z67: 11374 | AA67: 11374 | AB67: 11374 | AC67: 11374 | AD67: 11374 | AE67: 11374 | AF67: 11374 | AG67: 11374 | AH67: 11374 | AI67: 11374 | AJ67: 11374 | AK67: 11374 | AL67: 11374 | AM67: 11374 | AN67: 11374 | AO67: 11374 | AP67: 11374 | AQ67: 11374 | AR67: 11374 | AS67: 11374 | AT67: 11374 | AU67: 11374
A68: =A67 -> LEAST_CNST_NO_COAL_NUC | B68: 1 | C68: RSA | D68: Generator | E68: solar_csp | F68: renewables | L68: unc | M68: unc | N68: unc | O68: unc | P68: unc | Q68: unc | R68: unc | S68: =R68 -> unc | T68: =S68 -> unc | U68: =T68 -> unc | V68: =U68 -> unc | W68: =V68 -> unc | X68: =W68 -> unc | Y68: =X68 -> unc | Z68: =Y68 -> unc | ... AU68: =AT68 -> unc
A69: =A68 -> LEAST_CNST_NO_COAL_NUC | B69: 1 | C69: RSA | D69: Generator | E69: wind | F69: renewables | L69: unc | M69: unc | N69: unc | O69: unc | P69: unc | Q69: 11000 | R69: unc | S69: =R69 -> unc | T69: =S69 -> unc | U69: =T69 -> unc | V69: =U69 -> unc | W69: =V69 -> unc | X69: =W69 -> unc | Y69: =X69 -> unc | Z69: =Y69 -> unc | ... AU69: =AT69 -> unc
A70: =A69 -> LEAST_CNST_NO_COAL_NUC | B70: 1 | C70: RSA | D70: Generator | E70: wind_low | F70: renewables | L70: unc | M70: unc | N70: unc | O70: unc | P70: unc | Q70: unc | R70: unc | S70: =R70 -> unc | T70: =S70 -> unc | U70: =T70 -> unc | V70: =U70 -> unc | W70: =V70 -> unc | X70: =W70 -> unc | Y70: =X70 -> unc | Z70: =Y70 -> unc | ... AU70: =AT70 -> unc
A71: =A70 -> LEAST_CNST_NO_COAL_NUC | B71: 1 | C71: RSA | D71: Generator | E71: ccgt_steam | F71: conventional | L71: unc | M71: unc | N71: unc | O71: unc | P71: unc | Q71: unc | R71: unc | S71: =R71 -> unc | T71: =S71 -> unc | U71: =T71 -> unc | V71: =U71 -> unc | W71: =V71 -> unc | X71: =W71 -> unc | Y71: =X71 -> unc | Z71: =Y71 -> unc | ... AU71: =AT71 -> unc
A72: =A71 -> LEAST_CNST_NO_COAL_NUC | B72: 1 | C72: RSA | D72: Generator | E72: ocgt_gas | F72: conventional | L72: unc | M72: unc | N72: unc | O72: unc | P72: unc | Q72: unc | R72: unc | S72: =R72 -> unc | T72: =S72 -> unc | U72: =T72 -> unc | V72: =U72 -> unc | W72: =V72 -> unc | X72: =W72 -> unc | Y72: =X72 -> unc | Z72: =Y72 -> unc | ... AU72: =AT72 -> unc
A73: =A72 -> LEAST_CNST_NO_COAL_NUC | B73: 1 | C73: RSA | D73: Generator | E73: ocgt_gas_h2_40 | F73: conventional | L73: unc | M73: unc | N73: unc | O73: unc | P73: unc | Q73: unc | R73: unc | S73: =R73 -> unc | T73: =S73 -> unc | U73: =T73 -> unc | V73: =U73 -> unc | W73: =V73 -> unc | X73: =W73 -> unc | Y73: =X73 -> unc | Z73: =Y73 -> unc | ... AU73: =AT73 -> unc
A74: =A73 -> LEAST_CNST_NO_COAL_NUC | B74: 1 | C74: RSA | D74: Generator | E74: ocgt_gas_h2_45 | F74: conventional | L74: unc | M74: unc | N74: unc | O74: unc | P74: unc | Q74: unc | R74: unc | S74: =R74 -> unc | T74: =S74 -> unc | U74: =T74 -> unc | V74: =U74 -> unc | W74: =V74 -> unc | X74: =W74 -> unc | Y74: =X74 -> unc | Z74: =Y74 -> unc | ... AU74: =AT74 -> unc
A75: =A74 -> LEAST_CNST_NO_COAL_NUC | B75: 1 | C75: RSA | D75: Generator | E75: ocgt_gas_h2_50 | F75: conventional | L75: unc | M75: unc | N75: unc | O75: unc | P75: unc | Q75: unc | R75: unc | S75: =R75 -> unc | T75: =S75 -> unc | U75: =T75 -> unc | V75: =U75 -> unc | W75: =V75 -> unc | X75: =W75 -> unc | Y75: =X75 -> unc | Z75: =Y75 -> unc | ... AU75: =AT75 -> unc
A76: =A75 -> LEAST_CNST_NO_COAL_NUC | B76: 1 | C76: RSA | D76: Generator | E76: ocgt_gas_h2_55 | F76: conventional | L76: unc | M76: unc | N76: unc | O76: unc | P76: unc | Q76: unc | R76: unc | S76: =R76 -> unc | T76: =S76 -> unc | U76: =T76 -> unc | V76: =U76 -> unc | W76: =V76 -> unc | X76: =W76 -> unc | Y76: =X76 -> unc | Z76: =Y76 -> unc | ... AU76: =AT76 -> unc
A77: =A76 -> LEAST_CNST_NO_COAL_NUC | B77: 1 | C77: RSA | D77: Generator | E77: ocgt_gas_h2_60 | F77: conventional | L77: unc | M77: unc | N77: unc | O77: unc | P77: unc | Q77: unc | R77: unc | S77: =R77 -> unc | T77: =S77 -> unc | U77: =T77 -> unc | V77: =U77 -> unc | W77: =V77 -> unc | X77: =W77 -> unc | Y77: =X77 -> unc | Z77: =Y77 -> unc | ... AU77: =AT77 -> unc
A78: =A75 -> LEAST_CNST_NO_COAL_NUC | B78: 1 | C78: RSA | D78: Generator | E78: ocgt_diesel | F78: conventional | L78: unc | M78: unc | N78: unc | O78: unc | P78: unc | Q78: unc | R78: unc | S78: =R78 -> unc | T78: =S78 -> unc | U78: =T78 -> unc | V78: =U78 -> unc | W78: =V78 -> unc | X78: =W78 -> unc | Y78: =X78 -> unc | Z78: =Y78 -> unc | ... AU78: =AT78 -> unc
A79: =A76 -> LEAST_CNST_NO_COAL_NUC | B79: 1 | C79: RSA | D79: Generator | E79: ocgt_blend | F79: conventional | L79: 0 | M79: 0 | N79: 0 | O79: 0 | P79: 0 | Q79: 0 | R79: 0 | S79: 0 | T79: 0 | U79: 0 | V79: 0 | W79: =V79 -> 0 | X79: =W79 -> 0 | Y79: =X79 -> 0 | Z79: =Y79 -> 0 | AA79: =Z79 -> 0 | AB79: =AA79 -> 0 | AC79: =AB79 -> 0 | AD79: =AC79 -> 0 | ... AU79: =AT79 -> 0
A80: =A78 -> LEAST_CNST_NO_COAL_NUC | B80: 1 | C80: RSA | D80: Generator | E80: coal | F80: conventional | L80: 0 | M80: 0 | N80: 0 | O80: 0 | P80: 0 | Q80: 0 | R80: 0 | S80: 0 | T80: 0 | U80: 0 | V80: 0 | W80: =V80 -> 0 | X80: =W80 -> 0 | Y80: =X80 -> 0 | Z80: =Y80 -> 0 | AA80: =Z80 -> 0 | AB80: =AA80 -> 0 | AC80: =AB80 -> 0 | AD80: =AC80 -> 0 | ... AU80: =AT80 -> 0
A81: =A80 -> LEAST_CNST_NO_COAL_NUC | B81: 1 | C81: RSA | D81: Generator | E81: nuclear | F81: conventional | L81: 0 | M81: 0 | N81: 0 | O81: 0 | P81: 0 | Q81: 0 | R81: 0 | S81: 0 | T81: 0 | U81: 0 | V81: 0 | W81: =V81 -> 0 | X81: =W81 -> 0 | Y81: =X81 -> 0 | Z81: =Y81 -> 0 | AA81: =Z81 -> 0 | AB81: =AA81 -> 0 | AC81: =AB81 -> 0 | AD81: =AC81 -> 0 | ... AU81: =AT81 -> 0
A82: =A81 -> LEAST_CNST_NO_COAL_NUC | B82: 1 | C82: RSA | D82: StorageUnit | E82: phs | F82: storage | L82: 0 | M82: 0 | N82: 0 | O82: 0 | P82: 0 | Q82: 0 | R82: 0 | S82: 0 | T82: 0 | U82: 0 | V82: 1500 | W82: =V82 -> 1500 | X82: =W82 -> 1500 | Y82: =X82 -> 1500 | Z82: =Y82 -> 1500 | AA82: =Z82 -> 1500 | AB82: =AA82 -> 1500 | AC82: =AB82 -> 1500 | AD82: =AC82 -> 1500 | ... AU82: =AT82 -> 1500
A83: =A82 -> LEAST_CNST_NO_COAL_NUC | B83: 1 | C83: RSA | D83: StorageUnit | E83: battery_1h | F83: storage | L83: unc | M83: unc | N83: unc | O83: unc | P83: unc | Q83: unc | R83: unc | S83: unc | T83: unc | U83: unc | V83: unc | W83: unc | X83: unc | Y83: unc | Z83: unc | AA83: unc | AB83: unc | AC83: unc | AD83: unc | AE83: unc | AF83: unc | AG83: unc | AH83: unc | AI83: unc | AJ83: unc | AK83: unc | AL83: =AK83 -> unc | AM83: =AL83 -> unc | AN83: =AM83 -> unc | AO83: =AN83 -> unc | AP83: =AO83 -> unc | AQ83: =AP83 -> unc | AR83: =AQ83 -> unc | AS83: =AR83 -> unc | ... AU83: =AT83 -> unc
A84: =A83 -> LEAST_CNST_NO_COAL_NUC | B84: 1 | C84: RSA | D84: StorageUnit | E84: battery_4h | F84: storage | L84: unc | M84: unc | N84: unc | O84: unc | P84: unc | Q84: unc | R84: unc | S84: unc | T84: unc | U84: unc | V84: unc | W84: unc | X84: unc | Y84: unc | Z84: unc | AA84: unc | AB84: unc | AC84: unc | AD84: unc | AE84: unc | AF84: unc | AG84: unc | AH84: unc | AI84: unc | AJ84: unc | AK84: unc | AL84: =AK84 -> unc | AM84: =AL84 -> unc | AN84: =AM84 -> unc | AO84: =AN84 -> unc | AP84: =AO84 -> unc | AQ84: =AP84 -> unc | AR84: =AQ84 -> unc | AS84: =AR84 -> unc | ... AU84: =AT84 -> unc
A85: =A84 -> LEAST_CNST_NO_COAL_NUC | B85: 1 | C85: RSA | D85: StorageUnit | E85: battery_8h | F85: storage | L85: unc | M85: unc | N85: unc | O85: unc | P85: unc | Q85: unc | R85: unc | S85: unc | T85: unc | U85: unc | V85: unc | W85: unc | X85: unc | Y85: unc | Z85: unc | AA85: unc | AB85: unc | AC85: unc | AD85: unc | AE85: unc | AF85: unc | AG85: unc | AH85: unc | AI85: unc | AJ85: unc | AK85: unc | AL85: =AK85 -> unc | AM85: =AL85 -> unc | AN85: =AM85 -> unc | AO85: =AN85 -> unc | AP85: =AO85 -> unc | AQ85: =AP85 -> unc | AR85: =AQ85 -> unc | AS85: =AR85 -> unc | ... AU85: =AT85 -> unc
A86: MOD_CNST_NO_COAL_NUC | B86: 1 | C86: RSA | D86: Generator | E86: solar_pv | F86: renewables | L86: unc | M86: unc | N86: unc | O86: unc | P86: unc | Q86: unc | R86: unc | S86: =R86 -> unc | T86: =S86 -> unc | U86: =T86 -> unc | V86: =U86 -> unc | W86: =V86 -> unc | X86: =W86 -> unc | Y86: =X86 -> unc | Z86: =Y86 -> unc | ... AU86: =AT86 -> unc
A87: =A86 -> MOD_CNST_NO_COAL_NUC | B87: 1 | C87: RSA | D87: Generator | E87: solar_pv_low | F87: renewables | L87: unc | M87: unc | N87: unc | O87: unc | P87: unc | Q87: unc | R87: unc | S87: =R87 -> unc | T87: =S87 -> unc | U87: =T87 -> unc | V87: =U87 -> unc | W87: =V87 -> unc | X87: =W87 -> unc | Y87: =X87 -> unc | Z87: =Y87 -> unc | ... AU87: =AT87 -> unc
A88: =A87 -> MOD_CNST_NO_COAL_NUC | B88: 1 | C88: RSA | D88: Generator | E88: solar_pv_rooftop | F88: renewables | L88: 4624 | M88: 5299 | N88: 5974 | O88: 6649 | P88: 7324 | Q88: 7999 | R88: 8674 | S88: 9349 | T88: 10024 | U88: 10699 | V88: 11374 | W88: 11374 | X88: 11374 | Y88: 11374 | Z88: 11374 | AA88: 11374 | AB88: 11374 | AC88: 11374 | AD88: 11374 | AE88: 11374 | AF88: 11374 | AG88: 11374 | AH88: 11374 | AI88: 11374 | AJ88: 11374 | AK88: 11374 | AL88: 11374 | AM88: 11374 | AN88: 11374 | AO88: 11374 | AP88: 11374 | AQ88: 11374 | AR88: 11374 | AS88: 11374 | AT88: 11374 | AU88: 11374
A89: =A88 -> MOD_CNST_NO_COAL_NUC | B89: 1 | C89: RSA | D89: Generator | E89: solar_csp | F89: renewables | L89: unc | M89: unc | N89: unc | O89: unc | P89: unc | Q89: unc | R89: unc | S89: =R89 -> unc | T89: =S89 -> unc | U89: =T89 -> unc | V89: =U89 -> unc | W89: =V89 -> unc | X89: =W89 -> unc | Y89: =X89 -> unc | Z89: =Y89 -> unc | ... AU89: =AT89 -> unc
A90: =A89 -> MOD_CNST_NO_COAL_NUC | B90: 1 | C90: RSA | D90: Generator | E90: wind | F90: renewables | L90: unc | M90: unc | N90: unc | O90: unc | P90: unc | Q90: 9000 | R90: unc | S90: =R90 -> unc | T90: =S90 -> unc | U90: =T90 -> unc | V90: =U90 -> unc | W90: =V90 -> unc | X90: =W90 -> unc | Y90: =X90 -> unc | Z90: =Y90 -> unc | ... AU90: =AT90 -> unc
A91: =A90 -> MOD_CNST_NO_COAL_NUC | B91: 1 | C91: RSA | D91: Generator | E91: wind_low | F91: renewables | L91: unc | M91: unc | N91: unc | O91: unc | P91: unc | Q91: unc | R91: unc | S91: =R91 -> unc | T91: =S91 -> unc | U91: =T91 -> unc | V91: =U91 -> unc | W91: =V91 -> unc | X91: =W91 -> unc | Y91: =X91 -> unc | Z91: =Y91 -> unc | ... AU91: =AT91 -> unc
A92: =A91 -> MOD_CNST_NO_COAL_NUC | B92: 1 | C92: RSA | D92: Generator | E92: ccgt_steam | F92: conventional | L92: unc | M92: unc | N92: unc | O92: unc | P92: unc | Q92: unc | R92: unc | S92: =R92 -> unc | T92: =S92 -> unc | U92: =T92 -> unc | V92: =U92 -> unc | W92: =V92 -> unc | X92: =W92 -> unc | Y92: =X92 -> unc | Z92: =Y92 -> unc | ... AU92: =AT92 -> unc
A93: =A92 -> MOD_CNST_NO_COAL_NUC | B93: 1 | C93: RSA | D93: Generator | E93: ocgt_gas | F93: conventional | L93: unc | M93: unc | N93: unc | O93: unc | P93: unc | Q93: unc | R93: unc | S93: =R93 -> unc | T93: =S93 -> unc | U93: =T93 -> unc | V93: =U93 -> unc | W93: =V93 -> unc | X93: =W93 -> unc | Y93: =X93 -> unc | Z93: =Y93 -> unc | ... AU93: =AT93 -> unc
A94: =A93 -> MOD_CNST_NO_COAL_NUC | B94: 1 | C94: RSA | D94: Generator | E94: ocgt_gas_h2_40 | F94: conventional | L94: unc | M94: unc | N94: unc | O94: unc | P94: unc | Q94: unc | R94: unc | S94: =R94 -> unc | T94: =S94 -> unc | U94: =T94 -> unc | V94: =U94 -> unc | W94: =V94 -> unc | X94: =W94 -> unc | Y94: =X94 -> unc | Z94: =Y94 -> unc | ... AU94: =AT94 -> unc
A95: =A94 -> MOD_CNST_NO_COAL_NUC | B95: 1 | C95: RSA | D95: Generator | E95: ocgt_gas_h2_45 | F95: conventional | L95: unc | M95: unc | N95: unc | O95: unc | P95: unc | Q95: unc | R95: unc | S95: =R95 -> unc | T95: =S95 -> unc | U95: =T95 -> unc | V95: =U95 -> unc | W95: =V95 -> unc | X95: =W95 -> unc | Y95: =X95 -> unc | Z95: =Y95 -> unc | ... AU95: =AT95 -> unc
A96: =A95 -> MOD_CNST_NO_COAL_NUC | B96: 1 | C96: RSA | D96: Generator | E96: ocgt_gas_h2_50 | F96: conventional | L96: unc | M96: unc | N96: unc | O96: unc | P96: unc | Q96: unc | R96: unc | S96: =R96 -> unc | T96: =S96 -> unc | U96: =T96 -> unc | V96: =U96 -> unc | W96: =V96 -> unc | X96: =W96 -> unc | Y96: =X96 -> unc | Z96: =Y96 -> unc | ... AU96: =AT96 -> unc
A97: =A96 -> MOD_CNST_NO_COAL_NUC | B97: 1 | C97: RSA | D97: Generator | E97: ocgt_gas_h2_55 | F97: conventional | L97: unc | M97: unc | N97: unc | O97: unc | P97: unc | Q97: unc | R97: unc | S97: =R97 -> unc | T97: =S97 -> unc | U97: =T97 -> unc | V97: =U97 -> unc | W97: =V97 -> unc | X97: =W97 -> unc | Y97: =X97 -> unc | Z97: =Y97 -> unc | ... AU97: =AT97 -> unc
A98: =A97 -> MOD_CNST_NO_COAL_NUC | B98: 1 | C98: RSA | D98: Generator | E98: ocgt_gas_h2_60 | F98: conventional | L98: unc | M98: unc | N98: unc | O98: unc | P98: unc | Q98: unc | R98: unc | S98: =R98 -> unc | T98: =S98 -> unc | U98: =T98 -> unc | V98: =U98 -> unc | W98: =V98 -> unc | X98: =W98 -> unc | Y98: =X98 -> unc | Z98: =Y98 -> unc | ... AU98: =AT98 -> unc
A99: =A96 -> MOD_CNST_NO_COAL_NUC | B99: 1 | C99: RSA | D99: Generator | E99: ocgt_diesel | F99: conventional | L99: unc | M99: unc | N99: unc | O99: unc | P99: unc | Q99: unc | R99: unc | S99: =R99 -> unc | T99: =S99 -> unc | U99: =T99 -> unc | V99: =U99 -> unc | W99: =V99 -> unc | X99: =W99 -> unc | Y99: =X99 -> unc | Z99: =Y99 -> unc | ... AU99: =AT99 -> unc
A100: =A97 -> MOD_CNST_NO_COAL_NUC | B100: 1 | C100: RSA | D100: Generator | E100: ocgt_blend | F100: conventional | L100: 0 | M100: 0 | N100: 0 | O100: 0 | P100: 0 | Q100: 0 | R100: 0 | S100: 0 | T100: 0 | U100: 0 | V100: 0 | W100: =V100 -> 0 | X100: =W100 -> 0 | Y100: =X100 -> 0 | Z100: =Y100 -> 0 | AA100: =Z100 -> 0 | AB100: =AA100 -> 0 | AC100: =AB100 -> 0 | AD100: =AC100 -> 0 | ... AU100: =AT100 -> 0
...

Sheet min_total_installed
A1: scenario | B1: supply_region | C1: location | D1: component | E1: carrier | F1: category | G1: 2025 | H1: =G1+1 -> 2026 | I1: =H1+1 -> 2027 | J1: =I1+1 -> 2028 | K1: =J1+1 -> 2029 | L1: =K1+1 -> 2030 | M1: =L1+1 -> 2031 | N1: =M1+1 -> 2032 | O1: =N1+1 -> 2033 | ... AP1: =AO1+1 -> 2060
A2: UNC | B2: 1 | C2: RSA | D2: Generator | E2: solar_pv_rooftop | F2: renewables | G2: 4624 | H2: =G2+0.75*900 -> 5299 | I2: =H2+0.75*900 -> 5974 | J2: =I2+0.75*900 -> 6649 | K2: =J2+0.75*900 -> 7324 | L2: =K2+0.75*900 -> 7999 | M2: =L2+0.75*900 -> 8674 | N2: =M2+0.75*900 -> 9349 | O2: =N2+0.75*900 -> 10024 | ... Q2: =P2+0.75*900 -> 11374 | R2: =Q2 -> 11374 | S2: =R2 -> 11374 | T2: =S2 -> 11374 | U2: =T2 -> 11374 | V2: =U2 -> 11374 | W2: =V2 -> 11374 | X2: =W2 -> 11374 | Y2: =X2 -> 11374 | ... AP2: =AO2 -> 11374
A3: UNC | B3: 1 | C3: RSA | D3: Generator | E3: solar_pv_low | F3: renewables | G3: 1541 | H3: =G3+0.25*900 -> 1766 | I3: =H3+0.25*900 -> 1991 | J3: =I3+0.25*900 -> 2216 | K3: =J3+0.25*900 -> 2441 | L3: =K3+0.25*900 -> 2666 | M3: =L3+0.25*900 -> 2891 | N3: =M3+0.25*900 -> 3116 | O3: =N3+0.25*900 -> 3341 | ... Q3: =P3+0.25*900 -> 3791 | R3: =Q3 -> 3791 | S3: =R3 -> 3791 | T3: =S3 -> 3791 | U3: =T3 -> 3791 | V3: =U3 -> 3791 | W3: =V3 -> 3791 | X3: =W3 -> 3791 | Y3: =X3 -> 3791 | ... AP3: =AO3 -> 3791
A4: ignore | B4: 1 | C4: RSA | D4: Generator | E4: solar_pv_low_tot | F4: renewables | G4: =G2+G3 -> 6165 | H4: =H2+H3 -> 7065 | I4: =I2+I3 -> 7965 | J4: =J2+J3 -> 8865 | K4: =K2+K3 -> 9765 | L4: =L2+L3 -> 10665 | M4: =M2+M3 -> 11565 | N4: =N2+N3 -> 12465 | ... Q4: =Q2+Q3 -> 15165 | R4: =Q4 -> 15165 | S4: =R4 -> 15165 | T4: =S4 -> 15165 | U4: =T4 -> 15165 | V4: =U4 -> 15165 | W4: =V4 -> 15165 | X4: =W4 -> 15165 | Y4: =X4 -> 15165 | ... AP4: =AO4 -> 15165
A5: MTSAO_BQ | B5: 1 | C5: RSA | D5: Generator | E5: solar_pv_low | F5: renewables | G5: =G3 -> 1541 | H5: =H3 -> 1766 | I5: =I3 -> 1991 | J5: =J3 -> 2216 | K5: =K3 -> 2441 | L5: 4768 | M5: 0 | N5: 0 | O5: 0 | P5: 0 | Q5: 0 | R5: 0 | S5: 0 | T5: 0 | U5: 0 | V5: 0 | W5: 0 | X5: 0 | Y5: 0 | Z5: 0 | AA5: 0 | AB5: 0 | AC5: 0 | AD5: 0 | AE5: 0 | AF5: 0 | AG5: =AF5 -> 0 | AH5: =AG5 -> 0 | AI5: =AH5 -> 0 | AJ5: =AI5 -> 0 | AK5: =AJ5 -> 0 | AL5: =AK5 -> 0 | AM5: =AL5 -> 0 | AN5: =AM5 -> 0 | ... AP5: =AO5 -> 0
A6: =A5 -> MTSAO_BQ | B6: 1 | C6: RSA | D6: Generator | E6: solar_pv_rooftop | F6: renewables | G6: =G2 -> 4624 | H6: =H2 -> 5299 | I6: =I2 -> 5974 | J6: =J2 -> 6649 | K6: =K2 -> 7324 | L6: =L2 -> 7999 | M6: =M2 -> 8674 | N6: =N2 -> 9349 | ... AP6: =AP2 -> 11374
A7: =A6 -> MTSAO_BQ | B7: 1 | C7: RSA | D7: Generator | E7: wind | F7: renewables | G7: 5 | H7: 0 | I7: 0 | J7: 0 | K7: 0 | L7: 3895 | M7: 0 | N7: 0 | O7: 0 | P7: 0 | Q7: 0 | R7: 0 | S7: 0 | T7: 0 | U7: 0 | V7: 0 | W7: 0 | X7: 0 | Y7: 0 | Z7: 0 | AA7: 0 | AB7: 0 | AC7: 0 | AD7: 0 | AE7: 0 | AF7: 0 | AG7: =AF7 -> 0 | AH7: =AG7 -> 0 | AI7: =AH7 -> 0 | AJ7: =AI7 -> 0 | AK7: =AJ7 -> 0 | AL7: =AK7 -> 0 | AM7: =AL7 -> 0 | AN7: =AM7 -> 0 | ... AP7: =AO7 -> 0
A8: =A7 -> MTSAO_BQ | B8: 1 | C8: RSA | D8: Generator | E8: wind_low | F8: renewables | G8: 5 | H8: 0 | I8: 0 | J8: 0 | K8: 0 | L8: 0 | M8: 0 | N8: 0 | O8: 0 | P8: 0 | Q8: 0 | R8: 0 | S8: 0 | T8: 0 | U8: 0 | V8: 0 | W8: 0 | X8: 0 | Y8: 0 | Z8: 0 | AA8: 0 | AB8: 0 | AC8: 0 | AD8: 0 | AE8: 0 | AF8: 0 | AG8: =AF8 -> 0 | AH8: =AG8 -> 0 | AI8: =AH8 -> 0 | AJ8: =AI8 -> 0 | AK8: =AJ8 -> 0 | AL8: =AK8 -> 0 | AM8: =AL8 -> 0 | AN8: =AM8 -> 0 | ... AP8: =AO8 -> 0
A9: =A8 -> MTSAO_BQ | B9: 1 | C9: RSA | D9: Generator | E9: battery_4h | F9: renewables | G9: 0 | H9: 0 | I9: 0 | J9: 0 | K9: 0 | L9: 2615 | M9: 0 | N9: 0 | O9: 0 | P9: 0 | Q9: 0 | R9: 0 | S9: 0 | T9: 0 | U9: 0 | V9: 0 | W9: 0 | X9: 0 | Y9: 0 | Z9: 0 | AA9: 0 | AB9: 0 | AC9: 0 | AD9: 0 | AE9: 0 | AF9: 0 | AG9: =AF9 -> 0 | AH9: =AG9 -> 0 | AI9: =AH9 -> 0 | AJ9: =AI9 -> 0 | AK9: =AJ9 -> 0 | AL9: =AK9 -> 0 | AM9: =AL9 -> 0 | AN9: =AM9 -> 0 | ... AP9: =AO9 -> 0
A10: IRP24_BQ_IGCAR | B10: 1 | C10: RSA | D10: Generator | E10: solar_pv_low | F10: renewables | G10: =G3 -> 1541 | H10: =H3 -> 1766 | I10: =I3 -> 1991 | J10: =J3 -> 2216 | K10: =K3 -> 2441 | L10: 6988 | M10: 0 | N10: 0 | O10: 0 | P10: 0 | Q10: 0 | R10: 0 | S10: 0 | T10: 0 | U10: 0 | V10: 0 | W10: 0 | X10: 0 | Y10: 0 | Z10: 0 | AA10: 0 | AB10: 0 | AC10: 0 | AD10: 0 | AE10: 0 | AF10: 0 | AG10: =AF10 -> 0 | AH10: =AG10 -> 0 | AI10: =AH10 -> 0 | AJ10: =AI10 -> 0 | AK10: =AJ10 -> 0 | AL10: =AK10 -> 0 | AM10: =AL10 -> 0 | AN10: =AM10 -> 0 | ... AP10: =AO10 -> 0
A11: =A10 -> IRP24_BQ_IGCAR | B11: 1 | C11: RSA | D11: Generator | E11: solar_pv_rooftop | F11: renewables | G11: =G2 -> 4624 | H11: =H2 -> 5299 | I11: =I2 -> 5974 | J11: =J2 -> 6649 | K11: =K2 -> 7324 | L11: =L2 -> 7999 | M11: =M2 -> 8674 | N11: =N2 -> 9349 | ... AP11: =AP2 -> 11374
A12: =A11 -> IRP24_BQ_IGCAR | B12: 1 | C12: RSA | D12: Generator | E12: wind | F12: renewables | G12: 5 | H12: 0 | I12: 0 | J12: 0 | K12: 0 | L12: 5888 | M12: 0 | N12: 0 | O12: 0 | P12: 0 | Q12: 0 | R12: 0 | S12: 0 | T12: 0 | U12: 0 | V12: 0 | W12: 0 | X12: 0 | Y12: 0 | Z12: 0 | AA12: 0 | AB12: 0 | AC12: 0 | AD12: 0 | AE12: 0 | AF12: 0 | AG12: =AF12 -> 0 | AH12: =AG12 -> 0 | AI12: =AH12 -> 0 | AJ12: =AI12 -> 0 | AK12: =AJ12 -> 0 | AL12: =AK12 -> 0 | AM12: =AL12 -> 0 | AN12: =AM12 -> 0 | ... AP12: =AO12 -> 0
A13: =A12 -> IRP24_BQ_IGCAR | B13: 1 | C13: RSA | D13: Generator | E13: wind_low | F13: renewables | G13: 5 | H13: 0 | I13: 0 | J13: 0 | K13: 0 | L13: 500 | M13: 0 | N13: 0 | O13: 0 | P13: 0 | Q13: 0 | R13: 0 | S13: 0 | T13: 0 | U13: 0 | V13: 0 | W13: 0 | X13: 0 | Y13: 0 | Z13: 0 | AA13: 0 | AB13: 0 | AC13: 0 | AD13: 0 | AE13: 0 | AF13: 0 | AG13: =AF13 -> 0 | AH13: =AG13 -> 0 | AI13: =AH13 -> 0 | AJ13: =AI13 -> 0 | AK13: =AJ13 -> 0 | AL13: =AK13 -> 0 | AM13: =AL13 -> 0 | AN13: =AM13 -> 0 | ... AP13: =AO13 -> 0
A14: =A13 -> IRP24_BQ_IGCAR | B14: 1 | C14: RSA | D14: Generator | E14: battery_4h | F14: renewables | G14: 0 | H14: 0 | I14: 0 | J14: 0 | K14: 0 | L14: 2615 | M14: 0 | N14: 0 | O14: 0 | P14: 0 | Q14: 0 | R14: 0 | S14: 0 | T14: 0 | U14: 0 | V14: 0 | W14: 0 | X14: 0 | Y14: 0 | Z14: 0 | AA14: 0 | AB14: 0 | AC14: 0 | AD14: 0 | AE14: 0 | AF14: 0 | AG14: =AF14 -> 0 | AH14: =AG14 -> 0 | AI14: =AH14 -> 0 | AJ14: =AI14 -> 0 | AK14: =AJ14 -> 0 | AL14: =AK14 -> 0 | AM14: =AL14 -> 0 | AN14: =AM14 -> 0 | ... AP14: =AO14 -> 0

Sheet max_annual_installed
A1: scenario | B1: supply_region | C1: location | D1: component | E1: carrier | F1: category | G1: 2020 | H1: 2021 | I1: 2022 | J1: 2023 | K1: 2024 | L1: 2025 | M1: 2026 | N1: 2027 | O1: 2028 | P1: 2029 | Q1: 2030 | R1: 2031 | S1: =R1+1 -> 2032 | T1: =S1+1 -> 2033 | U1: =T1+1 -> 2034 | V1: 2035 | W1: =V1+1 -> 2036 | X1: =W1+1 -> 2037 | Y1: =X1+1 -> 2038 | Z1: =Y1+1 -> 2039 | AA1: 2040 | AB1: =AA1+1 -> 2041 | AC1: =AB1+1 -> 2042 | AD1: =AC1+1 -> 2043 | AE1: =AD1+1 -> 2044 | AF1: 2045 | AG1: =AF1+1 -> 2046 | AH1: =AG1+1 -> 2047 | AI1: =AH1+1 -> 2048 | AJ1: =AI1+1 -> 2049 | AK1: 2050 | AL1: =AK1+1 -> 2051 | AM1: =AL1+1 -> 2052 | AN1: =AM1+1 -> 2053 | AO1: =AN1+1 -> 2054 | AP1: =AO1+1 -> 2055 | AQ1: =AP1+1 -> 2056 | AR1: =AQ1+1 -> 2057 | AS1: =AR1+1 -> 2058 | ... AU1: =AT1+1 -> 2060
A2: UNC | B2: 1 | C2: RSA | D2: Generator | E2: solar_pv | F2: renewables | G2: unc | L2: unc | M2: unc | N2: unc | O2: unc | P2: unc | Q2: unc | R2: unc | S2: unc | T2: unc | U2: unc | V2: unc | W2: unc | X2: unc | Y2: unc | Z2: unc | AA2: unc | AB2: unc | AC2: unc | AD2: unc | AE2: unc | AF2: unc | AG2: unc | AH2: unc | AI2: unc | AJ2: unc | AK2: =AF2 -> unc | AL2: =AK2 -> unc | AM2: =AL2 -> unc | AN2: =AM2 -> unc | AO2: =AN2 -> unc | AP2: =AO2 -> unc | AQ2: =AP2 -> unc | AR2: =AQ2 -> unc | AS2: =AR2 -> unc | ... AU2: =AT2 -> unc
A3: LEAST_CNST | B3: 1 | C3: RSA | D3: Generator | E3: solar_pv | F3: renewables | L3: 0 | M3: 0 | N3: 0 | O3: 0 | P3: 0 | Q3: 10000 | R3: 10000 | S3: 10000 | T3: 10000 | U3: 10000 | V3: 10000 | W3: 10000 | X3: 10000 | Y3: 10000 | Z3: 10000 | AA3: 10000 | AB3: 10000 | AC3: 10000 | AD3: 10000 | AE3: 10000 | AF3: 10000 | AG3: 10000 | AH3: 10000 | AI3: 10000 | AJ3: 10000 | AK3: 10000 | AL3: =AK3 -> 10000 | AM3: =AL3 -> 10000 | AN3: =AM3 -> 10000 | AO3: =AN3 -> 10000 | AP3: =AO3 -> 10000 | AQ3: =AP3 -> 10000 | AR3: =AQ3 -> 10000 | AS3: =AR3 -> 10000 | ... AU3: =AT3 -> 10000
A4: =A3 -> LEAST_CNST | B4: 1 | C4: RSA | D4: Generator | E4: solar_pv_low | F4: renewables | L4: 2000 | M4: 10000 | N4: 10000 | O4: 10000 | P4: 10000 | Q4: 10000 | R4: 10000 | S4: 10000 | T4: 10000 | U4: 10000 | V4: 10000 | W4: 10000 | X4: 10000 | Y4: 10000 | Z4: 10000 | AA4: 10000 | AB4: 10000 | AC4: 10000 | AD4: 10000 | AE4: 10000 | AF4: 10000 | AG4: 10000 | AH4: 10000 | AI4: 10000 | AJ4: 10000 | AK4: 10000 | AL4: =AK4 -> 10000 | AM4: =AL4 -> 10000 | AN4: =AM4 -> 10000 | AO4: =AN4 -> 10000 | AP4: =AO4 -> 10000 | AQ4: =AP4 -> 10000 | AR4: =AQ4 -> 10000 | AS4: =AR4 -> 10000 | ... AU4: =AT4 -> 10000
A5: =A4 -> LEAST_CNST | B5: 1 | C5: RSA | D5: Generator | E5: solar_csp | F5: renewables | L5: 0 | M5: 0 | N5: 0 | O5: 0 | P5: 0 | Q5: 1000 | R5: =Q5 -> 1000 | S5: =R5 -> 1000 | T5: =S5 -> 1000 | U5: =T5 -> 1000 | V5: =U5 -> 1000 | W5: =V5 -> 1000 | X5: =W5 -> 1000 | Y5: =X5 -> 1000 | ... AU5: =AT5 -> 1000
A6: =A5 -> LEAST_CNST | B6: 1 | C6: RSA | D6: Generator | E6: wind | F6: renewables | L6: 5 | M6: 1000 | N6: =M6+100 -> 1100 | O6: =N6+100 -> 1200 | P6: =O6+100 -> 1300 | Q6: =P6+100 -> 1400 | R6: =Q6+100 -> 1500 | S6: =R6+100 -> 1600 | T6: =S6+100 -> 1700 | U6: =T6+100 -> 1800 | ... AU6: =AT6+100 -> 4400
A7: =A6 -> LEAST_CNST | B7: 1 | C7: RSA | D7: Generator | E7: wind_low | F7: renewables | L7: 5 | M7: 0 | N7: 0 | O7: 0 | P7: 0 | Q7: 1500 | R7: =Q7 -> 1500 | S7: =R7 -> 1500 | T7: =S7 -> 1500 | U7: =T7 -> 1500 | V7: =U7 -> 1500 | W7: =V7 -> 1500 | X7: =W7 -> 1500 | Y7: =X7 -> 1500 | ... AU7: =AT7 -> 1500
A8: =A7 -> LEAST_CNST | B8: 1 | C8: RSA | D8: Generator | E8: ccgt_steam | F8: conventional | L8: 0 | M8: 0 | N8: 0 | O8: 0 | P8: 0 | Q8: unc | R8: unc | S8: =R8 -> unc | T8: =S8 -> unc | U8: =T8 -> unc | V8: =U8 -> unc | W8: =V8 -> unc | X8: =W8 -> unc | Y8: =X8 -> unc | Z8: =Y8 -> unc | ... AU8: =AT8 -> unc
A9: =A8 -> LEAST_CNST | B9: 1 | C9: RSA | D9: Generator | E9: ocgt_gas | F9: conventional | L9: 0 | M9: 0 | N9: 0 | O9: 0 | P9: 0 | Q9: unc | R9: unc | S9: =R9 -> unc | T9: =S9 -> unc | U9: =T9 -> unc | V9: =U9 -> unc | W9: =V9 -> unc | X9: =W9 -> unc | Y9: =X9 -> unc | Z9: =Y9 -> unc | ... AU9: =AT9 -> unc
A10: =A9 -> LEAST_CNST | B10: 1 | C10: RSA | D10: Generator | E10: ocgt_gas_h2_40 | F10: conventional | L10: 0 | M10: 0 | N10: 0 | O10: 0 | P10: 0 | Q10: unc | R10: 0 | S10: 0 | T10: 0 | U10: =T10 -> 0 | V10: =U10 -> 0 | W10: 0 | X10: =W10 -> 0 | Y10: =X10 -> 0 | Z10: =Y10 -> 0 | AA10: 0 | AB10: =AA10 -> 0 | AC10: =AB10 -> 0 | AD10: =AC10 -> 0 | AE10: =AD10 -> 0 | AF10: =AE10 -> 0 | AG10: =AF10 -> 0 | AH10: =AG10 -> 0 | AI10: =AH10 -> 0 | ... AU10: =AT10 -> 0
A11: =A10 -> LEAST_CNST | B11: 1 | C11: RSA | D11: Generator | E11: ocgt_gas_h2_45 | F11: conventional | L11: 0 | M11: 0 | N11: 0 | O11: 0 | P11: 0 | Q11: unc | R11: unc | S11: =R11 -> unc | T11: =S11 -> unc | U11: =T11 -> unc | V11: unc | W11: 0 | X11: 0 | Y11: =X11 -> 0 | Z11: =Y11 -> 0 | AA11: =Z11 -> 0 | AB11: 0 | AC11: =AB11 -> 0 | AD11: =AC11 -> 0 | AE11: =AD11 -> 0 | AF11: 0 | AG11: =AF11 -> 0 | AH11: =AG11 -> 0 | AI11: =AH11 -> 0 | AJ11: =AI11 -> 0 | AK11: =AJ11 -> 0 | AL11: =AK11 -> 0 | AM11: =AL11 -> 0 | AN11: =AM11 -> 0 | ... AU11: =AT11 -> 0
A12: =A11 -> LEAST_CNST | B12: 1 | C12: RSA | D12: Generator | E12: ocgt_gas_h2_50 | F12: conventional | L12: 0 | M12: 0 | N12: 0 | O12: 0 | P12: 0 | Q12: unc | R12: unc | S12: =R12 -> unc | T12: =S12 -> unc | U12: =T12 -> unc | V12: =U12 -> unc | W12: =V12 -> unc | X12: =W12 -> unc | Y12: =X12 -> unc | Z12: =Y12 -> unc | AA12: =Z12 -> unc | AB12: 0 | AC12: 0 | AD12: 0 | AE12: =AD12 -> 0 | AF12: =AE12 -> 0 | AG12: 0 | AH12: =AG12 -> 0 | AI12: =AH12 -> 0 | AJ12: =AI12 -> 0 | AK12: 0 | AL12: =AK12 -> 0 | AM12: =AL12 -> 0 | AN12: =AM12 -> 0 | AO12: =AN12 -> 0 | AP12: =AO12 -> 0 | AQ12: =AP12 -> 0 | AR12: =AQ12 -> 0 | AS12: =AR12 -> 0 | ... AU12: =AT12 -> 0
A13: =A12 -> LEAST_CNST | B13: 1 | C13: RSA | D13: Generator | E13: ocgt_gas_h2_55 | F13: conventional | L13: 0 | M13: 0 | N13: 0 | O13: 0 | P13: 0 | Q13: unc | R13: unc | S13: =R13 -> unc | T13: =S13 -> unc | U13: =T13 -> unc | V13: =U13 -> unc | W13: =V13 -> unc | X13: =W13 -> unc | Y13: =X13 -> unc | Z13: =Y13 -> unc | AA13: =Z13 -> unc | AB13: unc | AC13: =AB13 -> unc | AD13: =AC13 -> unc | AE13: =AD13 -> unc | AF13: =AE13 -> unc | AG13: 0 | AH13: =AG13 -> 0 | AI13: =AH13 -> 0 | AJ13: =AI13 -> 0 | AK13: =AJ13 -> 0 | AL13: 0 | AM13: =AL13 -> 0 | AN13: =AM13 -> 0 | AO13: =AN13 -> 0 | AP13: =AO13 -> 0 | AQ13: =AP13 -> 0 | AR13: =AQ13 -> 0 | AS13: =AR13 -> 0 | AT13: =AS13 -> 0 | AU13: =AT13 -> 0
A14: =A13 -> LEAST_CNST | B14: 1 | C14: RSA | D14: Generator | E14: ocgt_gas_h2_60 | F14: conventional | L14: 0 | M14: 0 | N14: 0 | O14: 0 | P14: 0 | Q14: unc | R14: unc | S14: =R14 -> unc | T14: =S14 -> unc | U14: =T14 -> unc | V14: =U14 -> unc | W14: =V14 -> unc | X14: =W14 -> unc | Y14: =X14 -> unc | Z14: =Y14 -> unc | ... AK14: =AJ14 -> unc | AL14: 0 | AM14: =AL14 -> 0 | AN14: =AM14 -> 0 | AO14: =AN14 -> 0 | AP14: =AO14 -> 0 | AQ14: 0 | AR14: =AQ14 -> 0 | AS14: =AR14 -> 0 | AT14: =AS14 -> 0 | AU14: =AT14 -> 0
A15: =A9 -> LEAST_CNST | B15: 1 | C15: RSA | D15: Generator | E15: ocgt_diesel | F15: conventional | L15: 0 | M15: 0 | N15: 0 | O15: 0 | P15: 0 | Q15: unc | R15: =Q15 -> unc | S15: =R15 -> unc | T15: =S15 -> unc | U15: =T15 -> unc | V15: =U15 -> unc | W15: =V15 -> unc | X15: =W15 -> unc | Y15: =X15 -> unc | ... AU15: =AT15 -> unc
A16: =A10 -> LEAST_CNST | B16: 1 | C16: RSA | D16: Generator | E16: ocgt_blend | F16: conventional | L16: 0 | M16: =L16 -> 0 | N16: =M16 -> 0 | O16: =N16 -> 0 | P16: =O16 -> 0 | Q16: =P16 -> 0 | R16: =Q16 -> 0 | S16: =R16 -> 0 | T16: =S16 -> 0 | ... AU16: =AT16 -> 0
A17: =A12 -> LEAST_CNST | B17: 1 | C17: RSA | D17: Generator | E17: coal | F17: conventional | L17: unc | M17: =L17 -> unc | N17: =M17 -> unc | O17: =N17 -> unc | P17: =O17 -> unc | Q17: =P17 -> unc | R17: =Q17 -> unc | S17: =R17 -> unc | T17: =S17 -> unc | ... AU17: =AT17 -> unc
A18: =A17 -> LEAST_CNST | B18: 1 | C18: RSA | D18: Generator | E18: nuclear | F18: conventional | L18: unc | M18: =L18 -> unc | N18: =M18 -> unc | O18: =N18 -> unc | P18: =O18 -> unc | Q18: =P18 -> unc | R18: =Q18 -> unc | S18: =R18 -> unc | T18: =S18 -> unc | ... AU18: =AT18 -> unc
A19: =A18 -> LEAST_CNST | B19: 1 | C19: RSA | D19: StorageUnit | E19: phs | F19: storage | L19: unc | M19: =L19 -> unc | N19: =M19 -> unc | O19: =N19 -> unc | P19: =O19 -> unc | Q19: =P19 -> unc | R19: =Q19 -> unc | S19: =R19 -> unc | T19: =S19 -> unc | ... AU19: =AT19 -> unc
A20: =A19 -> LEAST_CNST | B20: 1 | C20: RSA | D20: StorageUnit | E20: battery_1h | F20: storage | L20: unc | M20: =L20 -> unc | N20: =M20 -> unc | O20: =N20 -> unc | P20: =O20 -> unc | Q20: =P20 -> unc | R20: =Q20 -> unc | S20: =R20 -> unc | T20: =S20 -> unc | ... AU20: =AT20 -> unc
A21: =A20 -> LEAST_CNST | B21: 1 | C21: RSA | D21: StorageUnit | E21: battery_4h | F21: storage | L21: unc | M21: =L21 -> unc | N21: =M21 -> unc | O21: =N21 -> unc | P21: =O21 -> unc | Q21: =P21 -> unc | R21: =Q21 -> unc | S21: =R21 -> unc | T21: =S21 -> unc | ... AU21: =AT21 -> unc
A22: =A21 -> LEAST_CNST | B22: 1 | C22: RSA | D22: StorageUnit | E22: battery_8h | F22: storage | L22: unc | M22: =L22 -> unc | N22: =M22 -> unc | O22: =N22 -> unc | P22: =O22 -> unc | Q22: =P22 -> unc | R22: =Q22 -> unc | S22: =R22 -> unc | T22: =S22 -> unc | ... AU22: =AT22 -> unc
A23: LST_HIGH | B23: 1 | C23: RSA | D23: Generator | E23: wind | F23: renewables | L23: =L6 -> 5 | M23: =L23+M6 -> 1005 | N23: =M23+N6 -> 2105 | O23: =N23+O6 -> 3305 | P23: =O23+P6 -> 4605 | Q23: =P23+Q6 -> 6005 | R23: =Q23+R6 -> 7505 | S23: =R23+S6 -> 9105 | T23: =S23+T6 -> 10805 | ... AU23: =AT23+AU6 -> 94505
A24: LST_LOW | B24: 1 | C24: RSA | D24: Generator | E24: wind | F24: renewables | L24: =L7 -> 5 | M24: =L24+M7 -> 5 | N24: =M24+N7 -> 5 | O24: =N24+O7 -> 5 | P24: =O24+P7 -> 5 | Q24: =P24+Q7 -> 1505 | R24: =Q24+R7 -> 3005 | S24: =R24+S7 -> 4505 | T24: =S24+T7 -> 6005 | ... AU24: =AT24+AU7 -> 46505
A25: LST_TOT | B25: 1 | C25: RSA | D25: Generator | E25: wind | F25: renewables | L25: =L23+L24 -> 10 | M25: =M23+M24 -> 1010 | N25: =N23+N24 -> 2110 | O25: =O23+O24 -> 3310 | P25: =P23+P24 -> 4610 | Q25: =Q23+Q24 -> 7510 | R25: =R23+R24 -> 10510 | S25: =S23+S24 -> 13610 | ... AU25: =AU23+AU24 -> 141010
A26: MOD_CNST | B26: 1 | C26: RSA | D26: Generator | E26: solar_pv | F26: renewables | L26: 0 | M26: 0 | N26: 0 | O26: 0 | P26: 0 | Q26: 10000 | R26: 10000 | S26: 10000 | T26: 10000 | U26: 10000 | V26: 10000 | W26: 10000 | X26: 10000 | Y26: 10000 | Z26: 10000 | AA26: 10000 | AB26: 10000 | AC26: 10000 | AD26: 10000 | AE26: 10000 | AF26: 10000 | AG26: 10000 | AH26: 10000 | AI26: 10000 | AJ26: 10000 | AK26: 10000 | AL26: =AK26 -> 10000 | AM26: =AL26 -> 10000 | AN26: =AM26 -> 10000 | AO26: =AN26 -> 10000 | AP26: =AO26 -> 10000 | AQ26: =AP26 -> 10000 | AR26: =AQ26 -> 10000 | AS26: =AR26 -> 10000 | ... AU26: =AT26 -> 10000
A27: =A26 -> MOD_CNST | B27: 1 | C27: RSA | D27: Generator | E27: solar_pv_low | F27: renewables | L27: 2000 | M27: 10000 | N27: 10000 | O27: 10000 | P27: 10000 | Q27: 10000 | R27: 10000 | S27: 10000 | T27: 10000 | U27: 10000 | V27: 10000 | W27: 10000 | X27: 10000 | Y27: 10000 | Z27: 10000 | AA27: 10000 | AB27: 10000 | AC27: 10000 | AD27: 10000 | AE27: 10000 | AF27: 10000 | AG27: 10000 | AH27: 10000 | AI27: 10000 | AJ27: 10000 | AK27: 10000 | AL27: =AK27 -> 10000 | AM27: =AL27 -> 10000 | AN27: =AM27 -> 10000 | AO27: =AN27 -> 10000 | AP27: =AO27 -> 10000 | AQ27: =AP27 -> 10000 | AR27: =AQ27 -> 10000 | AS27: =AR27 -> 10000 | ... AU27: =AT27 -> 10000
A28: =A27 -> MOD_CNST | B28: 1 | C28: RSA | D28: Generator | E28: solar_csp | F28: renewables | L28: 0 | M28: 1000 | N28: =M28 -> 1000 | O28: =N28 -> 1000 | P28: =O28 -> 1000 | Q28: =P28 -> 1000 | R28: =Q28 -> 1000 | S28: =R28 -> 1000 | T28: =S28 -> 1000 | U28: =T28 -> 1000 | ... AU28: =AT28 -> 1000
A29: =A28 -> MOD_CNST | B29: 1 | C29: RSA | D29: Generator | E29: wind | F29: renewables | L29: 5 | M29: 1000 | N29: 1000 | O29: 1000 | P29: 1000 | Q29: =P29 -> 1000 | R29: =Q29+100 -> 1100 | S29: =R29+100 -> 1200 | T29: =S29+100 -> 1300 | U29: =T29+100 -> 1400 | V29: =U29+100 -> 1500 | W29: =V29+100 -> 1600 | X29: =W29+100 -> 1700 | Y29: =X29+100 -> 1800 | ... AU29: =AT29+100 -> 4000
A30: =A29 -> MOD_CNST | B30: 1 | C30: RSA | D30: Generator | E30: wind_low | F30: renewables | L30: 5 | M30: 0 | N30: 0 | O30: 0 | P30: 0 | Q30: 1000 | R30: =Q30 -> 1000 | S30: =R30 -> 1000 | T30: =S30 -> 1000 | U30: =T30 -> 1000 | V30: =U30 -> 1000 | W30: =V30 -> 1000 | X30: =W30 -> 1000 | Y30: =X30 -> 1000 | ... AU30: =AT30 -> 1000
A31: =A30 -> MOD_CNST | B31: 1 | C31: RSA | D31: Generator | E31: ccgt_steam | F31: conventional | L31: 0 | M31: 0 | N31: 0 | O31: 0 | P31: 0 | Q31: unc | R31: unc | S31: =R31 -> unc | T31: =S31 -> unc | U31: =T31 -> unc | V31: =U31 -> unc | W31: =V31 -> unc | X31: =W31 -> unc | Y31: =X31 -> unc | Z31: =Y31 -> unc | ... AU31: =AT31 -> unc
A32: =A31 -> MOD_CNST | B32: 1 | C32: RSA | D32: Generator | E32: ocgt_gas | F32: conventional | L32: 0 | M32: 0 | N32: 0 | O32: 0 | P32: 0 | Q32: unc | R32: unc | S32: =R32 -> unc | T32: =S32 -> unc | U32: =T32 -> unc | V32: =U32 -> unc | W32: =V32 -> unc | X32: =W32 -> unc | Y32: =X32 -> unc | Z32: =Y32 -> unc | ... AU32: =AT32 -> unc
A33: =A32 -> MOD_CNST | B33: 1 | C33: RSA | D33: Generator | E33: ocgt_gas_h2_40 | F33: conventional | L33: 0 | M33: 0 | N33: 0 | O33: 0 | P33: 0 | Q33: unc | R33: 0 | S33: 0 | T33: 0 | U33: =T33 -> 0 | V33: =U33 -> 0 | W33: 0 | X33: =W33 -> 0 | Y33: =X33 -> 0 | Z33: =Y33 -> 0 | AA33: 0 | AB33: =AA33 -> 0 | AC33: =AB33 -> 0 | AD33: =AC33 -> 0 | AE33: =AD33 -> 0 | AF33: =AE33 -> 0 | AG33: =AF33 -> 0 | AH33: =AG33 -> 0 | AI33: =AH33 -> 0 | ... AU33: =AT33 -> 0
A34: =A33 -> MOD_CNST | B34: 1 | C34: RSA | D34: Generator | E34: ocgt_gas_h2_45 | F34: conventional | L34: 0 | M34: 0 | N34: 0 | O34: 0 | P34: 0 | Q34: unc | R34: unc | S34: =R34 -> unc | T34: =S34 -> unc | U34: =T34 -> unc | V34: unc | W34: 0 | X34: 0 | Y34: =X34 -> 0 | Z34: =Y34 -> 0 | AA34: =Z34 -> 0 | AB34: 0 | AC34: =AB34 -> 0 | AD34: =AC34 -> 0 | AE34: =AD34 -> 0 | AF34: 0 | AG34: =AF34 -> 0 | AH34: =AG34 -> 0 | AI34: =AH34 -> 0 | AJ34: =AI34 -> 0 | AK34: =AJ34 -> 0 | AL34: =AK34 -> 0 | AM34: =AL34 -> 0 | AN34: =AM34 -> 0 | ... AU34: =AT34 -> 0
A35: =A34 -> MOD_CNST | B35: 1 | C35: RSA | D35: Generator | E35: ocgt_gas_h2_50 | F35: conventional | L35: 0 | M35: 0 | N35: 0 | O35: 0 | P35: 0 | Q35: unc | R35: unc | S35: =R35 -> unc | T35: =S35 -> unc | U35: =T35 -> unc | V35: =U35 -> unc | W35: =V35 -> unc | X35: =W35 -> unc | Y35: =X35 -> unc | Z35: =Y35 -> unc | AA35: =Z35 -> unc | AB35: 0 | AC35: 0 | AD35: 0 | AE35: =AD35 -> 0 | AF35: =AE35 -> 0 | AG35: 0 | AH35: =AG35 -> 0 | AI35: =AH35 -> 0 | AJ35: =AI35 -> 0 | AK35: 0 | AL35: =AK35 -> 0 | AM35: =AL35 -> 0 | AN35: =AM35 -> 0 | AO35: =AN35 -> 0 | AP35: =AO35 -> 0 | AQ35: =AP35 -> 0 | AR35: =AQ35 -> 0 | AS35: =AR35 -> 0 | ... AU35: =AT35 -> 0
A36: =A35 -> MOD_CNST | B36: 1 | C36: RSA | D36: Generator | E36: ocgt_gas_h2_55 | F36: conventional | L36: 0 | M36: 0 | N36: 0 | O36: 0 | P36: 0 | Q36: unc | R36: unc | S36: =R36 -> unc | T36: =S36 -> unc | U36: =T36 -> unc | V36: =U36 -> unc | W36: =V36 -> unc | X36: =W36 -> unc | Y36: =X36 -> unc | Z36: =Y36 -> unc | AA36: =Z36 -> unc | AB36: unc | AC36: =AB36 -> unc | AD36: =AC36 -> unc | AE36: =AD36 -> unc | AF36: =AE36 -> unc | AG36: 0 | AH36: =AG36 -> 0 | AI36: =AH36 -> 0 | AJ36: =AI36 -> 0 | AK36: =AJ36 -> 0 | AL36: 0 | AM36: =AL36 -> 0 | AN36: =AM36 -> 0 | AO36: =AN36 -> 0 | AP36: =AO36 -> 0 | AQ36: =AP36 -> 0 | AR36: =AQ36 -> 0 | AS36: =AR36 -> 0 | AT36: =AS36 -> 0 | AU36: =AT36 -> 0
A37: =A36 -> MOD_CNST | B37: 1 | C37: RSA | D37: Generator | E37: ocgt_gas_h2_60 | F37: conventional | L37: 0 | M37: 0 | N37: 0 | O37: 0 | P37: 0 | Q37: unc | R37: unc | S37: =R37 -> unc | T37: =S37 -> unc | U37: =T37 -> unc | V37: =U37 -> unc | W37: =V37 -> unc | X37: =W37 -> unc | Y37: =X37 -> unc | Z37: =Y37 -> unc | ... AK37: =AJ37 -> unc | AL37: 0 | AM37: =AL37 -> 0 | AN37: =AM37 -> 0 | AO37: =AN37 -> 0 | AP37: =AO37 -> 0 | AQ37: 0 | AR37: =AQ37 -> 0 | AS37: =AR37 -> 0 | AT37: =AS37 -> 0 | AU37: =AT37 -> 0
A38: =A33 -> MOD_CNST | B38: 1 | C38: RSA | D38: Generator | E38: ocgt_diesel | F38: conventional | L38: 0 | M38: 0 | N38: 0 | O38: 0 | P38: 0 | Q38: unc | R38: unc | S38: =R38 -> unc | T38: =S38 -> unc | U38: =T38 -> unc | V38: =U38 -> unc | W38: =V38 -> unc | X38: =W38 -> unc | Y38: =X38 -> unc | Z38: =Y38 -> unc | ... AU38: =AT38 -> unc
A39: =A32 -> MOD_CNST | B39: 1 | C39: RSA | D39: Generator | E39: ocgt_blend | F39: conventional | L39: 0 | M39: 0 | N39: 0 | O39: 0 | P39: 0 | Q39: 0 | R39: 0 | S39: 0 | T39: 0 | U39: 0 | V39: 0 | W39: 0 | X39: 0 | Y39: 0 | Z39: 0 | AA39: 0 | AB39: 0 | AC39: 0 | AD39: 0 | AE39: 0 | AF39: 0 | AG39: 0 | AH39: 0 | AI39: 0 | AJ39: 0 | AK39: 0 | AL39: 0 | AM39: 0 | AN39: 0 | AO39: 0 | AP39: 0 | AQ39: 0 | AR39: 0 | AS39: 0 | AT39: 0 | AU39: 0
A40: =A35 -> MOD_CNST | B40: 1 | C40: RSA | D40: Generator | E40: coal | F40: conventional | L40: 0 | M40: =L40 -> 0 | N40: =M40 -> 0 | O40: =N40 -> 0 | P40: =O40 -> 0 | Q40: unc | R40: unc | S40: unc | T40: unc | U40: unc | V40: unc | W40: unc | X40: unc | Y40: unc | Z40: unc | AA40: unc | AB40: unc | AC40: unc | AD40: unc | AE40: unc | AF40: unc | AG40: unc | AH40: unc | AI40: unc | AJ40: unc | AK40: unc | AL40: unc | AM40: unc | AN40: unc | AO40: unc | AP40: unc | AQ40: unc | AR40: unc | AS40: unc | AT40: unc | AU40: unc
A41: =A40 -> MOD_CNST | B41: 1 | C41: RSA | D41: Generator | E41: nuclear | F41: conventional | L41: 0 | M41: =L41 -> 0 | N41: =M41 -> 0 | O41: =N41 -> 0 | P41: =O41 -> 0 | Q41: unc | R41: unc | S41: unc | T41: unc | U41: unc | V41: unc | W41: unc | X41: unc | Y41: unc | Z41: unc | AA41: unc | AB41: unc | AC41: unc | AD41: unc | AE41: unc | AF41: unc | AG41: unc | AH41: unc | AI41: unc | AJ41: unc | AK41: unc | AL41: unc | AM41: unc | AN41: unc | AO41: unc | AP41: unc | AQ41: unc | AR41: unc | AS41: unc | AT41: unc | AU41: unc
A42: =A41 -> MOD_CNST | B42: 1 | C42: RSA | D42: StorageUnit | E42: phs | F42: storage | L42: 0 | M42: =L42 -> 0 | N42: =M42 -> 0 | O42: =N42 -> 0 | P42: =O42 -> 0 | Q42: unc | R42: unc | S42: unc | T42: unc | U42: unc | V42: unc | W42: unc | X42: unc | Y42: unc | Z42: unc | AA42: unc | AB42: unc | AC42: unc | AD42: unc | AE42: unc | AF42: unc | AG42: unc | AH42: unc | AI42: unc | AJ42: unc | AK42: unc | AL42: unc | AM42: unc | AN42: unc | AO42: unc | AP42: unc | AQ42: unc | AR42: unc | AS42: unc | AT42: unc | AU42: unc
A43: =A42 -> MOD_CNST | B43: 1 | C43: RSA | D43: StorageUnit | E43: battery_1h | F43: storage | L43: unc | M43: unc | N43: unc | O43: unc | P43: unc | Q43: unc | R43: unc | S43: unc | T43: unc | U43: unc | V43: unc | W43: unc | X43: unc | Y43: unc | Z43: unc | AA43: unc | AB43: unc | AC43: unc | AD43: unc | AE43: unc | AF43: unc | AG43: unc | AH43: unc | AI43: unc | AJ43: unc | AK43: unc | AL43: unc | AM43: unc | AN43: unc | AO43: unc | AP43: unc | AQ43: unc | AR43: unc | AS43: unc | AT43: unc | AU43: unc
A44: =A43 -> MOD_CNST | B44: 1 | C44: RSA | D44: StorageUnit | E44: battery_4h | F44: storage | L44: unc | M44: unc | N44: unc | O44: unc | P44: unc | Q44: unc | R44: unc | S44: unc | T44: unc | U44: unc | V44: unc | W44: unc | X44: unc | Y44: unc | Z44: unc | AA44: unc | AB44: unc | AC44: unc | AD44: unc | AE44: unc | AF44: unc | AG44: unc | AH44: unc | AI44: unc | AJ44: unc | AK44: unc | AL44: unc | AM44: unc | AN44: unc | AO44: unc | AP44: unc | AQ44: unc | AR44: unc | AS44: unc | AT44: unc | AU44: unc
A45: =A44 -> MOD_CNST | B45: 1 | C45: RSA | D45: StorageUnit | E45: battery_8h | F45: storage | L45: unc | M45: unc | N45: unc | O45: unc | P45: unc | Q45: unc | R45: unc | S45: unc | T45: unc | U45: unc | V45: unc | W45: unc | X45: unc | Y45: unc | Z45: unc | AA45: unc | AB45: unc | AC45: unc | AD45: unc | AE45: unc | AF45: unc | AG45: unc | AH45: unc | AI45: unc | AJ45: unc | AK45: unc | AL45: unc | AM45: unc | AN45: unc | AO45: unc | AP45: unc | AQ45: unc | AR45: unc | AS45: unc | AT45: unc | AU45: unc
A46: MOD_HIGH | B46: 1 | C46: RSA | D46: Generator | E46: wind | F46: renewables | L46: 0 | M46: =L46+M29 -> 1000 | N46: =M46+N29 -> 2000 | O46: =N46+O29 -> 3000 | P46: =O46+P29 -> 4000 | Q46: =P46+Q29 -> 5000 | R46: =Q46+R29 -> 6100 | S46: =R46+S29 -> 7300 | T46: =S46+T29 -> 8600 | ... AU46: =AT46+AU29 -> 81500
A47: MOD_LOW | B47: 1 | C47: RSA | D47: Generator | E47: wind | F47: renewables | L47: 0 | M47: =L47+M30 -> 0 | N47: =M47+N30 -> 0 | O47: =N47+O30 -> 0 | P47: =O47+P30 -> 0 | Q47: =P47+Q30 -> 1000 | R47: =Q47+R30 -> 2000 | S47: =R47+S30 -> 3000 | T47: =S47+T30 -> 4000 | ... AU47: =AT47+AU30 -> 31000
A48: MOD_TOT | B48: 1 | C48: RSA | D48: Generator | E48: wind | F48: renewables | L48: 0 | M48: =M46+M47 -> 1000 | N48: =N46+N47 -> 2000 | O48: =O46+O47 -> 3000 | P48: =P46+P47 -> 4000 | Q48: =Q46+Q47 -> 6000 | R48: =R46+R47 -> 8100 | S48: =S46+S47 -> 10300 | T48: =T46+T47 -> 12600 | ... AU48: =AU46+AU47 -> 112500
A49: MOST_CNST | B49: 1 | C49: RSA | D49: Generator | E49: solar_pv | F49: renewables | L49: 0 | M49: 0 | N49: 0 | O49: 0 | P49: 0 | Q49: 10000 | R49: 10000 | S49: 10000 | T49: 10000 | U49: 10000 | V49: 10000 | W49: 10000 | X49: 10000 | Y49: 10000 | Z49: 10000 | AA49: 10000 | AB49: 10000 | AC49: 10000 | AD49: 10000 | AE49: 10000 | AF49: 10000 | AG49: 10000 | AH49: 10000 | AI49: 10000 | AJ49: 10000 | AK49: 10000 | AL49: =AK49 -> 10000 | AM49: =AL49 -> 10000 | AN49: =AM49 -> 10000 | AO49: =AN49 -> 10000 | AP49: =AO49 -> 10000 | AQ49: =AP49 -> 10000 | AR49: =AQ49 -> 10000 | AS49: =AR49 -> 10000 | ... AU49: =AT49 -> 10000
A50: =A49 -> MOST_CNST | B50: 1 | C50: RSA | D50: Generator | E50: solar_pv_low | F50: renewables | L50: 2000 | M50: 10000 | N50: 10000 | O50: 10000 | P50: 10000 | Q50: 10000 | R50: 10000 | S50: 10000 | T50: 10000 | U50: 10000 | V50: 10000 | W50: 10000 | X50: 10000 | Y50: 10000 | Z50: 10000 | AA50: 10000 | AB50: 10000 | AC50: 10000 | AD50: 10000 | AE50: 10000 | AF50: 10000 | AG50: 10000 | AH50: 10000 | AI50: 10000 | AJ50: 10000 | AK50: 10000 | AL50: =AK50 -> 10000 | AM50: =AL50 -> 10000 | AN50: =AM50 -> 10000 | AO50: =AN50 -> 10000 | AP50: =AO50 -> 10000 | AQ50: =AP50 -> 10000 | AR50: =AQ50 -> 10000 | AS50: =AR50 -> 10000 | ... AU50: =AT50 -> 10000
A51: =A50 -> MOST_CNST | B51: 1 | C51: RSA | D51: Generator | E51: solar_csp | F51: renewables | L51: 0 | M51: 1000 | N51: =M51 -> 1000 | O51: =N51 -> 1000 | P51: =O51 -> 1000 | Q51: =P51 -> 1000 | R51: =Q51 -> 1000 | S51: =R51 -> 1000 | T51: =S51 -> 1000 | U51: =T51 -> 1000 | ... AU51: =AT51 -> 1000
A52: =A51 -> MOST_CNST | B52: 1 | C52: RSA | D52: Generator | E52: wind | F52: renewables | L52: 5 | M52: 1000 | N52: 1000 | O52: 1000 | P52: 1000 | Q52: 1000 | R52: 1000 | S52: 1000 | T52: 1000 | U52: 1000 | V52: 1000 | W52: =V52+100 -> 1100 | X52: =W52+100 -> 1200 | Y52: =X52+100 -> 1300 | Z52: =Y52+100 -> 1400 | AA52: =Z52+100 -> 1500 | AB52: =AA52+100 -> 1600 | AC52: =AB52+100 -> 1700 | AD52: =AC52+100 -> 1800 | ... AU52: =AT52+100 -> 3500
A53: =A52 -> MOST_CNST | B53: 1 | C53: RSA | D53: Generator | E53: wind_low | F53: renewables | L53: 5 | M53: 0 | N53: 0 | O53: 0 | P53: 0 | Q53: 500 | R53: =Q53 -> 500 | S53: =R53 -> 500 | T53: =S53 -> 500 | U53: =T53 -> 500 | V53: =U53 -> 500 | W53: =V53 -> 500 | X53: =W53 -> 500 | Y53: =X53 -> 500 | ... AU53: =AT53 -> 500
A54: =A53 -> MOST_CNST | B54: 1 | C54: RSA | D54: Generator | E54: ccgt_steam | F54: conventional | L54: 0 | M54: 0 | N54: 0 | O54: 0 | P54: 0 | Q54: unc | R54: unc | S54: =R54 -> unc | T54: =S54 -> unc | U54: =T54 -> unc | V54: =U54 -> unc | W54: =V54 -> unc | X54: =W54 -> unc | Y54: =X54 -> unc | Z54: =Y54 -> unc | ... AU54: =AT54 -> unc
A55: =A54 -> MOST_CNST | B55: 1 | C55: RSA | D55: Generator | E55: ocgt_gas | F55: conventional | L55: 0 | M55: 0 | N55: 0 | O55: 0 | P55: 0 | Q55: unc | R55: unc | S55: =R55 -> unc | T55: =S55 -> unc | U55: =T55 -> unc | V55: =U55 -> unc | W55: =V55 -> unc | X55: =W55 -> unc | Y55: =X55 -> unc | Z55: =Y55 -> unc | ... AU55: =AT55 -> unc
A56: =A55 -> MOST_CNST | B56: 1 | C56: RSA | D56: Generator | E56: ocgt_gas_h2_40 | F56: conventional | L56: 0 | M56: 0 | N56: 0 | O56: 0 | P56: 0 | Q56: unc | R56: 0 | S56: 0 | T56: 0 | U56: =T56 -> 0 | V56: =U56 -> 0 | W56: 0 | X56: =W56 -> 0 | Y56: =X56 -> 0 | Z56: =Y56 -> 0 | AA56: 0 | AB56: =AA56 -> 0 | AC56: =AB56 -> 0 | AD56: =AC56 -> 0 | AE56: =AD56 -> 0 | AF56: =AE56 -> 0 | AG56: =AF56 -> 0 | AH56: =AG56 -> 0 | AI56: =AH56 -> 0 | ... AU56: =AT56 -> 0
A57: =A56 -> MOST_CNST | B57: 1 | C57: RSA | D57: Generator | E57: ocgt_gas_h2_45 | F57: conventional | L57: 0 | M57: 0 | N57: 0 | O57: 0 | P57: 0 | Q57: unc | R57: unc | S57: =R57 -> unc | T57: =S57 -> unc | U57: =T57 -> unc | V57: unc | W57: 0 | X57: 0 | Y57: =X57 -> 0 | Z57: =Y57 -> 0 | AA57: =Z57 -> 0 | AB57: 0 | AC57: =AB57 -> 0 | AD57: =AC57 -> 0 | AE57: =AD57 -> 0 | AF57: 0 | AG57: =AF57 -> 0 | AH57: =AG57 -> 0 | AI57: =AH57 -> 0 | AJ57: =AI57 -> 0 | AK57: =AJ57 -> 0 | AL57: =AK57 -> 0 | AM57: =AL57 -> 0 | AN57: =AM57 -> 0 | ... AU57: =AT57 -> 0
A58: =A57 -> MOST_CNST | B58: 1 | C58: RSA | D58: Generator | E58: ocgt_gas_h2_50 | F58: conventional | L58: 0 | M58: 0 | N58: 0 | O58: 0 | P58: 0 | Q58: unc | R58: unc | S58: =R58 -> unc | T58: =S58 -> unc | U58: =T58 -> unc | V58: =U58 -> unc | W58: =V58 -> unc | X58: =W58 -> unc | Y58: =X58 -> unc | Z58: =Y58 -> unc | AA58: =Z58 -> unc | AB58: 0 | AC58: 0 | AD58: 0 | AE58: =AD58 -> 0 | AF58: =AE58 -> 0 | AG58: 0 | AH58: =AG58 -> 0 | AI58: =AH58 -> 0 | AJ58: =AI58 -> 0 | AK58: 0 | AL58: =AK58 -> 0 | AM58: =AL58 -> 0 | AN58: =AM58 -> 0 | AO58: =AN58 -> 0 | AP58: =AO58 -> 0 | AQ58: =AP58 -> 0 | AR58: =AQ58 -> 0 | AS58: =AR58 -> 0 | ... AU58: =AT58 -> 0
A59: =A58 -> MOST_CNST | B59: 1 | C59: RSA | D59: Generator | E59: ocgt_gas_h2_55 | F59: conventional | L59: 0 | M59: 0 | N59: 0 | O59: 0 | P59: 0 | Q59: unc | R59: unc | S59: =R59 -> unc | T59: =S59 -> unc | U59: =T59 -> unc | V59: =U59 -> unc | W59: =V59 -> unc | X59: =W59 -> unc | Y59: =X59 -> unc | Z59: =Y59 -> unc | AA59: =Z59 -> unc | AB59: unc | AC59: =AB59 -> unc | AD59: =AC59 -> unc | AE59: =AD59 -> unc | AF59: =AE59 -> unc | AG59: 0 | AH59: =AG59 -> 0 | AI59: =AH59 -> 0 | AJ59: =AI59 -> 0 | AK59: =AJ59 -> 0 | AL59: 0 | AM59: =AL59 -> 0 | AN59: =AM59 -> 0 | AO59: =AN59 -> 0 | AP59: =AO59 -> 0 | AQ59: =AP59 -> 0 | AR59: =AQ59 -> 0 | AS59: =AR59 -> 0 | AT59: =AS59 -> 0 | AU59: =AT59 -> 0
A60: =A59 -> MOST_CNST | B60: 1 | C60: RSA | D60: Generator | E60: ocgt_gas_h2_60 | F60: conventional | L60: 0 | M60: 0 | N60: 0 | O60: 0 | P60: 0 | Q60: unc | R60: unc | S60: =R60 -> unc | T60: =S60 -> unc | U60: =T60 -> unc | V60: =U60 -> unc | W60: =V60 -> unc | X60: =W60 -> unc | Y60: =X60 -> unc | Z60: =Y60 -> unc | ... AK60: =AJ60 -> unc | AL60: 0 | AM60: =AL60 -> 0 | AN60: =AM60 -> 0 | AO60: =AN60 -> 0 | AP60: =AO60 -> 0 | AQ60: 0 | AR60: =AQ60 -> 0 | AS60: =AR60 -> 0 | AT60: =AS60 -> 0 | AU60: =AT60 -> 0
A61: =A55 -> MOST_CNST | B61: 1 | C61: RSA | D61: Generator | E61: ocgt_diesel | F61: conventional | L61: 0 | M61: 0 | N61: 0 | O61: 0 | P61: 0 | Q61: unc | R61: unc | S61: =R61 -> unc | T61: =S61 -> unc | U61: =T61 -> unc | V61: =U61 -> unc | W61: =V61 -> unc | X61: =W61 -> unc | Y61: =X61 -> unc | Z61: =Y61 -> unc | ... AU61: =AT61 -> unc
A62: =A56 -> MOST_CNST | B62: 1 | C62: RSA | D62: Generator | E62: ocgt_blend | F62: conventional | L62: 0 | M62: 0 | N62: 0 | O62: 0 | P62: 0 | Q62: 0 | R62: 0 | S62: 0 | T62: 0 | U62: 0 | V62: 0 | W62: 0 | X62: 0 | Y62: 0 | Z62: 0 | AA62: 0 | AB62: 0 | AC62: 0 | AD62: 0 | AE62: 0 | AF62: 0 | AG62: 0 | AH62: 0 | AI62: 0 | AJ62: 0 | AK62: 0 | AL62: 0 | AM62: 0 | AN62: 0 | AO62: 0 | AP62: 0 | AQ62: 0 | AR62: 0 | AS62: 0 | AT62: 0 | AU62: 0
A63: =A58 -> MOST_CNST | B63: 1 | C63: RSA | D63: Generator | E63: coal | F63: conventional | L63: 0 | M63: 0 | N63: 0 | O63: 0 | P63: 0 | Q63: =P63 -> 0 | R63: =Q63 -> 0 | S63: =R63 -> 0 | T63: =S63 -> 0 | U63: =T63 -> 0 | V63: unc | W63: =V63 -> unc | X63: =W63 -> unc | Y63: =X63 -> unc | Z63: =Y63 -> unc | AA63: =Z63 -> unc | AB63: =AA63 -> unc | AC63: =AB63 -> unc | AD63: =AC63 -> unc | ... AU63: =AT63 -> unc
A64: =A63 -> MOST_CNST | B64: 1 | C64: RSA | D64: Generator | E64: nuclear | F64: conventional | L64: 0 | M64: 0 | N64: 0 | O64: 0 | P64: 0 | Q64: =P64 -> 0 | R64: =Q64 -> 0 | S64: =R64 -> 0 | T64: =S64 -> 0 | U64: =T64 -> 0 | V64: unc | W64: =V64 -> unc | X64: =W64 -> unc | Y64: =X64 -> unc | Z64: =Y64 -> unc | AA64: =Z64 -> unc | AB64: =AA64 -> unc | AC64: =AB64 -> unc | AD64: =AC64 -> unc | ... AU64: =AT64 -> unc
A65: =A64 -> MOST_CNST | B65: 1 | C65: RSA | D65: StorageUnit | E65: phs | F65: storage | L65: 0 | M65: 0 | N65: 0 | O65: 0 | P65: 0 | Q65: =P65 -> 0 | R65: =Q65 -> 0 | S65: =R65 -> 0 | T65: =S65 -> 0 | U65: =T65 -> 0 | V65: unc | W65: =V65 -> unc | X65: =W65 -> unc | Y65: =X65 -> unc | Z65: =Y65 -> unc | AA65: =Z65 -> unc | AB65: =AA65 -> unc | AC65: =AB65 -> unc | AD65: =AC65 -> unc | ... AU65: =AT65 -> unc
A66: =A65 -> MOST_CNST | B66: 1 | C66: RSA | D66: StorageUnit | E66: battery_1h | F66: storage | L66: unc | M66: unc | N66: unc | O66: unc | P66: unc | Q66: unc | R66: unc | S66: unc | T66: unc | U66: unc | V66: unc | W66: unc | X66: unc | Y66: unc | Z66: unc | AA66: unc | AB66: unc | AC66: unc | AD66: unc | AE66: unc | AF66: unc | AG66: unc | AH66: unc | AI66: unc | AJ66: unc | AK66: unc | AL66: unc | AM66: unc | AN66: unc | AO66: unc | AP66: unc | AQ66: unc | AR66: unc | AS66: unc | AT66: unc | AU66: unc
A67: =A66 -> MOST_CNST | B67: 1 | C67: RSA | D67: StorageUnit | E67: battery_4h | F67: storage | L67: unc | M67: unc | N67: unc | O67: unc | P67: unc | Q67: unc | R67: unc | S67: unc | T67: unc | U67: unc | V67: unc | W67: unc | X67: unc | Y67: unc | Z67: unc | AA67: unc | AB67: unc | AC67: unc | AD67: unc | AE67: unc | AF67: unc | AG67: unc | AH67: unc | AI67: unc | AJ67: unc | AK67: unc | AL67: unc | AM67: unc | AN67: unc | AO67: unc | AP67: unc | AQ67: unc | AR67: unc | AS67: unc | AT67: unc | AU67: unc
A68: =A67 -> MOST_CNST | B68: 1 | C68: RSA | D68: StorageUnit | E68: battery_8h | F68: storage | L68: unc | M68: unc | N68: unc | O68: unc | P68: unc | Q68: unc | R68: unc | S68: unc | T68: unc | U68: unc | V68: unc | W68: unc | X68: unc | Y68: unc | Z68: unc | AA68: unc | AB68: unc | AC68: unc | AD68: unc | AE68: unc | AF68: unc | AG68: unc | AH68: unc | AI68: unc | AJ68: unc | AK68: unc | AL68: unc | AM68: unc | AN68: unc | AO68: unc | AP68: unc | AQ68: unc | AR68: unc | AS68: unc | AT68: unc | AU68: unc
A69: MST_HIGH | B69: 1 | C69: RSA | D69: Generator | E69: wind | F69: renewables | L69: 0 | M69: =L69+M52 -> 1000 | N69: =M69+N52 -> 2000 | O69: =N69+O52 -> 3000 | P69: =O69+P52 -> 4000 | Q69: =P69+Q52 -> 5000 | R69: =Q69+R52 -> 6000 | S69: =R69+S52 -> 7000 | T69: =S69+T52 -> 8000 | ... AU69: =AT69+AU52 -> 67500
A70: MST_LOW | B70: 1 | C70: RSA | D70: Generator | E70: wind | F70: renewables | L70: 0 | M70: =L70+M53 -> 0 | N70: =M70+N53 -> 0 | O70: =N70+O53 -> 0 | P70: =O70+P53 -> 0 | Q70: =P70+Q53 -> 500 | R70: =Q70+R53 -> 1000 | S70: =R70+S53 -> 1500 | T70: =S70+T53 -> 2000 | ... AU70: =AT70+AU53 -> 15500
A71: MST_TOT | B71: 1 | C71: RSA | D71: Generator | E71: wind | F71: renewables | L71: 0 | M71: =M69+M70 -> 1000 | N71: =N69+N70 -> 2000 | O71: =O69+O70 -> 3000 | P71: =P69+P70 -> 4000 | Q71: =Q69+Q70 -> 5500 | R71: =R69+R70 -> 7000 | S71: =S69+S70 -> 8500 | T71: =T69+T70 -> 10000 | ... AU71: =AU69+AU70 -> 83000

Sheet min_annual_installed
A1: scenario | B1: supply_region | C1: location | D1: component | E1: carrier | F1: category | G1: 2020 | H1: 2021 | I1: 2022 | J1: 2023 | K1: 2024 | L1: 2025 | M1: 2026 | N1: 2027 | O1: 2028 | P1: 2029 | Q1: 2030 | R1: 2031 | S1: 2032 | T1: 2033 | U1: 2034 | V1: 2035 | W1: 2036 | X1: 2037 | Y1: 2038 | Z1: 2039 | AA1: 2040 | AB1: 2041 | AC1: 2042 | AD1: 2043 | AE1: 2044 | AF1: 2045 | AG1: 2046 | AH1: 2047 | AI1: 2048 | AJ1: 2049 | AK1: 2050 | AL1: =AK1+1 -> 2051 | AM1: =AL1+1 -> 2052 | AN1: =AM1+1 -> 2053 | AO1: =AN1+1 -> 2054 | AP1: =AO1+1 -> 2055 | AQ1: =AP1+1 -> 2056 | AR1: =AQ1+1 -> 2057 | AS1: =AR1+1 -> 2058 | ... AU1: =AT1+1 -> 2060
A2: UNC | B2: 1 | C2: RSA | D2: Generator | E2: solar_pv | F2: conventional | G2: 0 | H2: 0 | I2: 0 | J2: 0 | K2: 0 | L2: 0 | M2: 0 | N2: 0 | O2: 0 | P2: =O2 -> 0 | Q2: =P2 -> 0 | R2: 0 | S2: 0 | T2: 0 | U2: 0 | V2: 0 | W2: 0 | X2: 0 | Y2: 0 | Z2: 0 | AA2: =Z2 -> 0 | AB2: =AA2 -> 0 | AC2: =AB2 -> 0 | AD2: =AC2 -> 0 | AE2: =AD2 -> 0 | AF2: =AE2 -> 0 | AG2: =AF2 -> 0 | AH2: =AG2 -> 0 | ... AU2: =AT2 -> 0
A3: 3GW_GAS | B3: 1 | C3: RSA | D3: Generator | E3: ccgt_steam | F3: conventional | G3: 0 | H3: 0 | I3: 0 | J3: 0 | K3: 0 | L3: 0 | M3: 0 | N3: 0 | O3: 0 | P3: 0 | Q3: 900 | R3: 0 | S3: 0 | T3: 0 | U3: 0 | V3: 0 | W3: 0 | X3: 0 | Y3: 0 | Z3: 0 | AA3: =Z3 -> 0 | AB3: =AA3 -> 0 | AC3: =AB3 -> 0 | AD3: =AC3 -> 0 | AE3: =AD3 -> 0 | AF3: =AE3 -> 0 | AG3: =AF3 -> 0 | AH3: =AG3 -> 0 | ... AU3: =AT3 -> 0
A4: 3GW_GAS | B4: 1 | C4: RSA | D4: Generator | E4: ocgt_gas | F4: conventional | G4: 0 | H4: 0 | I4: 0 | J4: 0 | K4: 0 | L4: 0 | M4: 0 | N4: 0 | O4: 0 | P4: 0 | Q4: 2100 | R4: 0 | S4: 0 | T4: 0 | U4: 0 | V4: 0 | W4: 0 | X4: 0 | Y4: 0 | Z4: 0 | AA4: =Z4 -> 0 | AB4: =AA4 -> 0 | AC4: =AB4 -> 0 | AD4: =AC4 -> 0 | AE4: =AD4 -> 0 | AF4: =AE4 -> 0 | AG4: =AF4 -> 0 | AH4: =AG4 -> 0 | ... AU4: =AT4 -> 0
A5: 6GW_GAS | B5: 1 | C5: RSA | D5: Generator | E5: ccgt_steam | F5: conventional | G5: 0 | H5: 0 | I5: 0 | J5: 0 | K5: 0 | L5: 0 | M5: 0 | N5: 0 | O5: 0 | P5: 0 | Q5: 900 | R5: 0 | S5: 0 | T5: 0 | U5: 0 | V5: 0 | W5: 0 | X5: 0 | Y5: 0 | Z5: 0 | AA5: =Z5 -> 0 | AB5: =AA5 -> 0 | AC5: =AB5 -> 0 | AD5: =AC5 -> 0 | AE5: =AD5 -> 0 | AF5: =AE5 -> 0 | AG5: =AF5 -> 0 | AH5: =AG5 -> 0 | ... AU5: =AT5 -> 0
A6: 6GW_GAS | B6: 1 | C6: RSA | D6: Generator | E6: ocgt_gas | F6: conventional | G6: 0 | H6: 0 | I6: 0 | J6: 0 | K6: 0 | L6: 0 | M6: 0 | N6: 0 | O6: 0 | P6: 0 | Q6: 2100 | R6: 0 | S6: 0 | T6: 0 | U6: 0 | V6: 0 | W6: 0 | X6: 0 | Y6: 0 | Z6: 0 | AA6: =Z6 -> 0 | AB6: =AA6 -> 0 | AC6: =AB6 -> 0 | AD6: =AC6 -> 0 | AE6: =AD6 -> 0 | AF6: =AE6 -> 0 | AG6: =AF6 -> 0 | AH6: =AG6 -> 0 | ... AU6: =AT6 -> 0
A7: DLY_3GW_GAS | B7: 1 | C7: RSA | D7: Generator | E7: ccgt_steam | F7: conventional | G7: 0 | H7: 0 | I7: 0 | J7: 0 | K7: 0 | L7: 0 | M7: 0 | N7: 0 | O7: 0 | P7: 0 | Q7: 0 | R7: 0 | S7: 0 | T7: 0 | U7: 0 | V7: 900 | W7: 0 | X7: 0 | Y7: 0 | Z7: 0 | AA7: =Z7 -> 0 | AB7: =AA7 -> 0 | AC7: =AB7 -> 0 | AD7: =AC7 -> 0 | AE7: =AD7 -> 0 | AF7: =AE7 -> 0 | AG7: =AF7 -> 0 | AH7: =AG7 -> 0 | ... AU7: =AT7 -> 0
A8: DLY_3GW_GAS | B8: 1 | C8: RSA | D8: Generator | E8: ocgt_gas | F8: conventional | G8: 0 | H8: 0 | I8: 0 | J8: 0 | K8: 0 | L8: 0 | M8: 0 | N8: 0 | O8: 0 | P8: 0 | Q8: 0 | R8: 0 | S8: 0 | T8: 0 | U8: 0 | V8: 2100 | W8: 0 | X8: 0 | Y8: 0 | Z8: 0 | AA8: =Z8 -> 0 | AB8: =AA8 -> 0 | AC8: =AB8 -> 0 | AD8: =AC8 -> 0 | AE8: =AD8 -> 0 | AF8: =AE8 -> 0 | AG8: =AF8 -> 0 | AH8: =AG8 -> 0 | ... AU8: =AT8 -> 0
